Workbook

Sheet LEEME
A1: Ciclo Kalina KCS-11 — resultados de la campaña final de barridos (M1–M10b)
A3: Para qué es este libro: presentar las tablas y gráficos del análisis, ordenados por pregunta.
A4: Cómo se numera: pregunta (1–6) → estudio (2.4) → parte (2.4a). Ver la hoja Nomenclatura. Solo se comparan puntos de la misma parte.
A5: Cómo leer cada hoja: las primeras filas dicen qué caso es, el punto base, los datos fijos y barridos (parte por parte si hay varias), el filtro y la fuente; la tabla empieza después de una fila en blanco (con filtros); las notas van al final.
A6: Hoja Tablero: elija un estudio o una parte en la celda B2 y se actualizan las cifras, las condiciones y los gráficos.
A7: Hojas 'N Gráficos': gráficos nativos de Excel de cada pregunta (pase el cursor para ver los valores); cada uno lleva arriba su ID y título y abajo su pie con los datos fijos.
A8: Hojas 'N Datos de gráficos': los números con los que Excel dibuja cada gráfico, un bloque por figura (si cambia un número, el gráfico cambia).
A9: Cada gráfico, además, tiene una copia junto a la tabla de la que salen sus datos: a la derecha de su parte o variable en la hoja 'N.M-R Resultados por barrido', o debajo de su tabla resumen (3.1-3, 3.2-4, 4.3-3, 6.1-3, S-1). Los de 'N Gráficos' siguen donde estaban.
A10: Hojas 'N.M-R Resultados por barrido': por estudio, la tabla de cada barrido con el valor de la variable barrida, la clase, η, W_net, ΔP, r_P y si está fuera de rango (los mismos puntos del tablero HTML).
A12: Glosario:
A13: • PP (punto del profesor): Los datos del enunciado: P_alta 3000 kPa, P_baja 400 kPa, x_b 0.50, T_fuente 623.15 K, T_sumidero 300.03 K, η_t 0.85, η_p 0.75, ε_HRVG 0.85, ε_reg 0.75, ε_cond 0.80. Con ellos el ciclo no converge.
A14: • A* (punto ancla): El punto del profesor con solo dos cambios: T_fuente = 403 K y P_baja = 563.64 kPa. Es KALINA con η = 8.48 %. Se eligió en M2 como el cambio intermedio que vuelve funcional el ciclo, y M3 estudia la sensibilidad a su alrededor.
... A32: Falso convergido: el solver dijo que convergió, pero no es un ciclo real (no cuenta)

Sheet Nomenclatura
A1: Cómo se numera todo (como los capítulos de un informe)
A3: • PREGUNTA (1 a 6): qué queremos saber. El anexo A es una curiosidad que no entra en las conclusiones.
A4: • ESTUDIO (por ejemplo 2.4): un barrido que responde esa pregunta. El primer número es la pregunta.
A5: • PARTE (por ejemplo 2.4a): cuando un estudio tiene partes con datos fijos distintos, cada una lleva una letra. REGLA: solo se comparan puntos de la misma parte.
A6: • Tabla 4.1-1, Figura 3.2-2: tablas y figuras van numeradas por estudio (4.1-1 = tabla 1 del estudio 4.1). Las de síntesis de toda la campaña llevan S (Tabla S-4, Figura S-1).
A7: • En cada estudio, la Tabla x.y-1 son las condiciones (qué quedó fijo y qué se barrió), la x.y-2 el conteo de corridas por clase y las siguientes, los resultados.
A8: • El 'código de origen' (M05, KF-M05-3, B09-3…) es el nombre interno de los archivos de cálculo; solo sirve para rastrear un dato hasta su CSV.
A10: Pregunta | B10: Estudio | C10: Nombre del estudio | D10: Partes (letra = datos fijos distintos) | E10: Código de origen
A11: 1 · ¿Funciona el ciclo con los datos del profesor? | B11: 1.1 | C11: Repetir el caso del profesor | D11: 1.1a: punto del profesor | 1.1b: solo P_alta | 1.1c: solo x_b | 1.1d: temperatura ambiente hora a hora | E11: M01
A12: 2 · ¿Qué es lo mínimo que hay que cambiar para que funcione? | B12: 2.1 | C12: Un solo cambio | D12: una variable a la vez | E12: M02-N1
A13: 2 · ¿Qué es lo mínimo que hay que cambiar para que funcione? | B13: 2.2 | C13: Dos cambios | D13: 2.2a: conservar la fuente (ε_HRVG × P_baja) | 2.2b: bajar la fuente (T_fuente × P_baja) | E13: M02-N2
A14: 2 · ¿Qué es lo mínimo que hay que cambiar para que funcione? | B14: 2.3 | C14: Dos cambios con η y ε en 0.40–0.95 | D14: 2.3a: un cambio | 2.3b: ε_HRVG × ε_cond | 2.3c: ε_HRVG × P_baja | 2.3d: T_fuente × ε_cond | E14: M02R
A15: 2 · ¿Qué es lo mínimo que hay que cambiar para que funcione? | B15: 2.4 | C15: Sumidero más frío | D15: 2.4a: fuente a 403 K | 2.4b: fuente a 420 K | 2.4c: ε_HRVG = 0.40 (fuente del profesor) | 2.4d: datos exactos del profesor | E15: M02S
A16: 3 · ¿Qué variables importan y cuánto? | B16: 3.1 | C16: Sensibilidad local alrededor de A* | D16: alrededor de A* | E16: M03
A17: 3 · ¿Qué variables importan y cuánto? | B17: 3.2 | C17: Sensibilidad global (500 puntos) | D17: muestra de 300 puntos | muestra de 200 puntos | E17: M04, M04b
A18: 3 · ¿Qué variables importan y cuánto? | B18: 3.3 | C18: P_baja alta (1500–2500 kPa) | D18: P_baja de 1500 a 2500 kPa | E18: M04c
A19: 4 · ¿Qué datos del profesor se pueden conservar? | B19: 4.1 | C19: Escenarios de conservación | D19: 4.1a: conserva sus temperaturas | 4.1b: conserva sus presiones | 4.1c: conserva sus presiones y su clima | 4.1d: conserva su P_alta y sus temperaturas | 4.1e: conserva su fuente y su x_b | E19: M05
A20: 4 · ¿Qué datos del profesor se pueden conservar? | B20: 4.2 | C20: Mapa con las presiones del profesor | D20: presiones del profesor, malla T_fuente × ε_cond × clima | E20: M05c
A21: 4 · ¿Qué datos del profesor se pueden conservar? | B21: 4.3 | C21: Escalera de conservación | D21: rondas 0 a 3; cada conjunto se nombra con sus variables (p. ej. 4.3 x_b+P_alta) | E21: M09
... A25: A · Anexo: equipos fuera del rango realista (no entra en las conclusiones) | B25: A.1 | C25: Equipos fuera del rango realista | D25: η y ε de 0.20 a 0.99 | E25: M08

Sheet Tablero
A1: Tablero de resultados — elija un estudio o una parte en B2
A2: Estudio / parte: | B2: 3.2 · Sensibilidad global (500 puntos) | C2: =INDEX(Aux_tablero!$B$11:$AY$11,MATCH($B$2,Aux_tablero!$B$1:$AY$1,0))
D4: Corridas | E4: Genuinas | F4: KALINA | G4: KALINA confiables | H4: η máx. KALINA [%] | I4: Criterio que más bloquea | K4: Eje X: | L4: =INDEX(Aux_tablero!$B$8:$AY$8,MATCH($B$2,Aux_tablero!$B$1:$AY$1,0)) | AC4: xK | AD4: yK | AE4: xC | AF4: yC | AG4: xI | AH4: yI | AI4: xN | AJ4: yN
D5: =INDEX(Aux_tablero!$B$2:$AY$2,MATCH($B$2,Aux_tablero!$B$1:$AY$1,0)) | E5: =INDEX(Aux_tablero!$B$3:$AY$3,MATCH($B$2,Aux_tablero!$B$1:$AY$1,0)) | F5: =INDEX(Aux_tablero!$B$4:$AY$4,MATCH($B$2,Aux_tablero!$B$1:$AY$1,0)) | G5: =INDEX(Aux_tablero!$B$5:$AY$5,MATCH($B$2,Aux_tablero!$B$1:$AY$1,0)) | H5: =INDEX(Aux_tablero!$B$6:$AY$6,MATCH($B$2,Aux_tablero!$B$1:$AY$1,0)) | I5: =INDEX(Aux_tablero!$B$7:$AY$7,MATCH($B$2,Aux_tablero!$B$1:$AY$1,0)) | K5: Eje Y: | L5: =INDEX(Aux_tablero!$B$9:$AY$9,MATCH($B$2,Aux_tablero!$B$1:$AY$1,0)) | Z5: KALINA | AA5: =INDEX(Aux_tablero!$B$12:$AY$12,MATCH($B$2,Aux_tablero!$B$1:$AY$1,0)) | AC5: =IFERROR(IF(INDEX(Aux_puntos!$A$2:$OJ$901,1,MATCH($B$2&"|xK",Aux_puntos!$1:$1,0))="",NA(),INDEX(Aux_puntos!$A$2:$OJ$901,1,MATCH($B$2&"|xK",Aux_puntos!$1:$1,0))),NA()) | AD5: =IFERROR(IF(INDEX(Aux_puntos!$A$2:$OJ$901,1,MATCH($B$2&"|yK",Aux_puntos!$1:$1,0))="",NA(),INDEX(Aux_puntos!$A$2:$OJ$901,1,MATCH($B$2&"|yK",Aux_puntos!$1:$1,0))),NA()) | AE5: =IFERROR(IF(INDEX(Aux_puntos!$A$2:$OJ$901,1,MATCH($B$2&"|xC",Aux_puntos!$1:$1,0))="",NA(),INDEX(Aux_puntos!$A$2:$OJ$901,1,MATCH($B$2&"|xC",Aux_puntos!$1:$1,0))),NA()) | AF5: =IFERROR(IF(INDEX(Aux_puntos!$A$2:$OJ$901,1,MATCH($B$2&"|yC",Aux_puntos!$1:$1,0))="",NA(),INDEX(Aux_puntos!$A$2:$OJ$901,1,MATCH($B$2&"|yC",Aux_puntos!$1:$1,0))),NA()) | AG5: =IFERROR(IF(INDEX(Aux_puntos!$A$2:$OJ$901,1,MATCH($B$2&"|xI",Aux_puntos!$1:$1,0))="",NA(),INDEX(Aux_puntos!$A$2:$OJ$901,1,MATCH($B$2&"|xI",Aux_puntos!$1:$1,0))),NA()) | AH5: =IFERROR(IF(INDEX(Aux_puntos!$A$2:$OJ$901,1,MATCH($B$2&"|yI",Aux_puntos!$1:$1,0))="",NA(),INDEX(Aux_puntos!$A$2:$OJ$901,1,MATCH($B$2&"|yI",Aux_puntos!$1:$1,0))),NA()) | AI5: =IFERROR(IF(INDEX(Aux_puntos!$A$2:$OJ$901,1,MATCH($B$2&"|xN",Aux_puntos!$1:$1,0))="",NA(),INDEX(Aux_puntos!$A$2:$OJ$901,1,MATCH($B$2&"|xN",Aux_puntos!$1:$1,0))),NA()) | AJ5: =IFERROR(IF(INDEX(Aux_puntos!$A$2:$OJ$901,1,MATCH($B$2&"|yN",Aux_puntos!$1:$1,0))="",NA(),INDEX(Aux_puntos!$A$2:$OJ$901,1,MATCH($B$2&"|yN",Aux_puntos!$1:$1,0))),NA())
Z6: Corregible | AA6: =INDEX(Aux_tablero!$B$13:$AY$13,MATCH($B$2,Aux_tablero!$B$1:$AY$1,0)) | AC6: =IFERROR(IF(INDEX(Aux_puntos!$A$2:$OJ$901,2,MATCH($B$2&"|xK",Aux_puntos!$1:$1,0))="",NA(),INDEX(Aux_puntos!$A$2:$OJ$901,2,MATCH($B$2&"|xK",Aux_puntos!$1:$1,0))),NA()) | AD6: =IFERROR(IF(INDEX(Aux_puntos!$A$2:$OJ$901,2,MATCH($B$2&"|yK",Aux_puntos!$1:$1,0))="",NA(),INDEX(Aux_puntos!$A$2:$OJ$901,2,MATCH($B$2&"|yK",Aux_puntos!$1:$1,0))),NA()) | AE6: =IFERROR(IF(INDEX(Aux_puntos!$A$2:$OJ$901,2,MATCH($B$2&"|xC",Aux_puntos!$1:$1,0))="",NA(),INDEX(Aux_puntos!$A$2:$OJ$901,2,MATCH($B$2&"|xC",Aux_puntos!$1:$1,0))),NA()) | AF6: =IFERROR(IF(INDEX(Aux_puntos!$A$2:$OJ$901,2,MATCH($B$2&"|yC",Aux_puntos!$1:$1,0))="",NA(),INDEX(Aux_puntos!$A$2:$OJ$901,2,MATCH($B$2&"|yC",Aux_puntos!$1:$1,0))),NA()) | AG6: =IFERROR(IF(INDEX(Aux_puntos!$A$2:$OJ$901,2,MATCH($B$2&"|xI",Aux_puntos!$1:$1,0))="",NA(),INDEX(Aux_puntos!$A$2:$OJ$901,2,MATCH($B$2&"|xI",Aux_puntos!$1:$1,0))),NA()) | AH6: =IFERROR(IF(INDEX(Aux_puntos!$A$2:$OJ$901,2,MATCH($B$2&"|yI",Aux_puntos!$1:$1,0))="",NA(),INDEX(Aux_puntos!$A$2:$OJ$901,2,MATCH($B$2&"|yI",Aux_puntos!$1:$1,0))),NA()) | AI6: =IFERROR(IF(INDEX(Aux_puntos!$A$2:$OJ$901,2,MATCH($B$2&"|xN",Aux_puntos!$1:$1,0))="",NA(),INDEX(Aux_puntos!$A$2:$OJ$901,2,MATCH($B$2&"|xN",Aux_puntos!$1:$1,0))),NA()) | AJ6: =IFERROR(IF(INDEX(Aux_puntos!$A$2:$OJ$901,2,MATCH($B$2&"|yN",Aux_puntos!$1:$1,0))="",NA(),INDEX(Aux_puntos!$A$2:$OJ$901,2,MATCH($B$2&"|yN",Aux_puntos!$1:$1,0))),NA())
A7: Condiciones (datos fijos y barridos) | Z7: Inviable | AA7: =INDEX(Aux_tablero!$B$14:$AY$14,MATCH($B$2,Aux_tablero!$B$1:$AY$1,0)) | AC7: =IFERROR(IF(INDEX(Aux_puntos!$A$2:$OJ$901,3,MATCH($B$2&"|xK",Aux_puntos!$1:$1,0))="",NA(),INDEX(Aux_puntos!$A$2:$OJ$901,3,MATCH($B$2&"|xK",Aux_puntos!$1:$1,0))),NA()) | AD7: =IFERROR(IF(INDEX(Aux_puntos!$A$2:$OJ$901,3,MATCH($B$2&"|yK",Aux_puntos!$1:$1,0))="",NA(),INDEX(Aux_puntos!$A$2:$OJ$901,3,MATCH($B$2&"|yK",Aux_puntos!$1:$1,0))),NA()) | AE7: =IFERROR(IF(INDEX(Aux_puntos!$A$2:$OJ$901,3,MATCH($B$2&"|xC",Aux_puntos!$1:$1,0))="",NA(),INDEX(Aux_puntos!$A$2:$OJ$901,3,MATCH($B$2&"|xC",Aux_puntos!$1:$1,0))),NA()) | AF7: =IFERROR(IF(INDEX(Aux_puntos!$A$2:$OJ$901,3,MATCH($B$2&"|yC",Aux_puntos!$1:$1,0))="",NA(),INDEX(Aux_puntos!$A$2:$OJ$901,3,MATCH($B$2&"|yC",Aux_puntos!$1:$1,0))),NA()) | AG7: =IFERROR(IF(INDEX(Aux_puntos!$A$2:$OJ$901,3,MATCH($B$2&"|xI",Aux_puntos!$1:$1,0))="",NA(),INDEX(Aux_puntos!$A$2:$OJ$901,3,MATCH($B$2&"|xI",Aux_puntos!$1:$1,0))),NA()) | AH7: =IFERROR(IF(INDEX(Aux_puntos!$A$2:$OJ$901,3,MATCH($B$2&"|yI",Aux_puntos!$1:$1,0))="",NA(),INDEX(Aux_puntos!$A$2:$OJ$901,3,MATCH($B$2&"|yI",Aux_puntos!$1:$1,0))),NA()) | AI7: =IFERROR(IF(INDEX(Aux_puntos!$A$2:$OJ$901,3,MATCH($B$2&"|xN",Aux_puntos!$1:$1,0))="",NA(),INDEX(Aux_puntos!$A$2:$OJ$901,3,MATCH($B$2&"|xN",Aux_puntos!$1:$1,0))),NA()) | AJ7: =IFERROR(IF(INDEX(Aux_puntos!$A$2:$OJ$901,3,MATCH($B$2&"|yN",Aux_puntos!$1:$1,0))="",NA(),INDEX(Aux_puntos!$A$2:$OJ$901,3,MATCH($B$2&"|yN",Aux_puntos!$1:$1,0))),NA())
A8: Temperatura de la fuente, T_fuente [K] | B8: =INDEX(Aux_tablero!$B$21:$AY$21,MATCH($B$2,Aux_tablero!$B$1:$AY$1,0)) | Z8: No convergió | AA8: =INDEX(Aux_tablero!$B$15:$AY$15,MATCH($B$2,Aux_tablero!$B$1:$AY$1,0)) | AC8: =IFERROR(IF(INDEX(Aux_puntos!$A$2:$OJ$901,4,MATCH($B$2&"|xK",Aux_puntos!$1:$1,0))="",NA(),INDEX(Aux_puntos!$A$2:$OJ$901,4,MATCH($B$2&"|xK",Aux_puntos!$1:$1,0))),NA()) | AD8: =IFERROR(IF(INDEX(Aux_puntos!$A$2:$OJ$901,4,MATCH($B$2&"|yK",Aux_puntos!$1:$1,0))="",NA(),INDEX(Aux_puntos!$A$2:$OJ$901,4,MATCH($B$2&"|yK",Aux_puntos!$1:$1,0))),NA()) | AE8: =IFERROR(IF(INDEX(Aux_puntos!$A$2:$OJ$901,4,MATCH($B$2&"|xC",Aux_puntos!$1:$1,0))="",NA(),INDEX(Aux_puntos!$A$2:$OJ$901,4,MATCH($B$2&"|xC",Aux_puntos!$1:$1,0))),NA()) | AF8: =IFERROR(IF(INDEX(Aux_puntos!$A$2:$OJ$901,4,MATCH($B$2&"|yC",Aux_puntos!$1:$1,0))="",NA(),INDEX(Aux_puntos!$A$2:$OJ$901,4,MATCH($B$2&"|yC",Aux_puntos!$1:$1,0))),NA()) | AG8: =IFERROR(IF(INDEX(Aux_puntos!$A$2:$OJ$901,4,MATCH($B$2&"|xI",Aux_puntos!$1:$1,0))="",NA(),INDEX(Aux_puntos!$A$2:$OJ$901,4,MATCH($B$2&"|xI",Aux_puntos!$1:$1,0))),NA()) | AH8: =IFERROR(IF(INDEX(Aux_puntos!$A$2:$OJ$901,4,MATCH($B$2&"|yI",Aux_puntos!$1:$1,0))="",NA(),INDEX(Aux_puntos!$A$2:$OJ$901,4,MATCH($B$2&"|yI",Aux_puntos!$1:$1,0))),NA()) | AI8: =IFERROR(IF(INDEX(Aux_puntos!$A$2:$OJ$901,4,MATCH($B$2&"|xN",Aux_puntos!$1:$1,0))="",NA(),INDEX(Aux_puntos!$A$2:$OJ$901,4,MATCH($B$2&"|xN",Aux_puntos!$1:$1,0))),NA()) | AJ8: =IFERROR(IF(INDEX(Aux_puntos!$A$2:$OJ$901,4,MATCH($B$2&"|yN",Aux_puntos!$1:$1,0))="",NA(),INDEX(Aux_puntos!$A$2:$OJ$901,4,MATCH($B$2&"|yN",Aux_puntos!$1:$1,0))),NA())
A9: Temperatura del sumidero, T_sumidero [K] | B9: =INDEX(Aux_tablero!$B$22:$AY$22,MATCH($B$2,Aux_tablero!$B$1:$AY$1,0)) | Z9: Falso convergido | AA9: =INDEX(Aux_tablero!$B$16:$AY$16,MATCH($B$2,Aux_tablero!$B$1:$AY$1,0)) | AC9: =IFERROR(IF(INDEX(Aux_puntos!$A$2:$OJ$901,5,MATCH($B$2&"|xK",Aux_puntos!$1:$1,0))="",NA(),INDEX(Aux_puntos!$A$2:$OJ$901,5,MATCH($B$2&"|xK",Aux_puntos!$1:$1,0))),NA()) | AD9: =IFERROR(IF(INDEX(Aux_puntos!$A$2:$OJ$901,5,MATCH($B$2&"|yK",Aux_puntos!$1:$1,0))="",NA(),INDEX(Aux_puntos!$A$2:$OJ$901,5,MATCH($B$2&"|yK",Aux_puntos!$1:$1,0))),NA()) | AE9: =IFERROR(IF(INDEX(Aux_puntos!$A$2:$OJ$901,5,MATCH($B$2&"|xC",Aux_puntos!$1:$1,0))="",NA(),INDEX(Aux_puntos!$A$2:$OJ$901,5,MATCH($B$2&"|xC",Aux_puntos!$1:$1,0))),NA()) | AF9: =IFERROR(IF(INDEX(Aux_puntos!$A$2:$OJ$901,5,MATCH($B$2&"|yC",Aux_puntos!$1:$1,0))="",NA(),INDEX(Aux_puntos!$A$2:$OJ$901,5,MATCH($B$2&"|yC",Aux_puntos!$1:$1,0))),NA()) | AG9: =IFERROR(IF(INDEX(Aux_puntos!$A$2:$OJ$901,5,MATCH($B$2&"|xI",Aux_puntos!$1:$1,0))="",NA(),INDEX(Aux_puntos!$A$2:$OJ$901,5,MATCH($B$2&"|xI",Aux_puntos!$1:$1,0))),NA()) | AH9: =IFERROR(IF(INDEX(Aux_puntos!$A$2:$OJ$901,5,MATCH($B$2&"|yI",Aux_puntos!$1:$1,0))="",NA(),INDEX(Aux_puntos!$A$2:$OJ$901,5,MATCH($B$2&"|yI",Aux_puntos!$1:$1,0))),NA()) | AI9: =IFERROR(IF(INDEX(Aux_puntos!$A$2:$OJ$901,5,MATCH($B$2&"|xN",Aux_puntos!$1:$1,0))="",NA(),INDEX(Aux_puntos!$A$2:$OJ$901,5,MATCH($B$2&"|xN",Aux_puntos!$1:$1,0))),NA()) | AJ9: =IFERROR(IF(INDEX(Aux_puntos!$A$2:$OJ$901,5,MATCH($B$2&"|yN",Aux_puntos!$1:$1,0))="",NA(),INDEX(Aux_puntos!$A$2:$OJ$901,5,MATCH($B$2&"|yN",Aux_puntos!$1:$1,0))),NA())
A10: Presión de alta, P_alta [kPa] | B10: =INDEX(Aux_tablero!$B$23:$AY$23,MATCH($B$2,Aux_tablero!$B$1:$AY$1,0)) | AC10: =IFERROR(IF(INDEX(Aux_puntos!$A$2:$OJ$901,6,MATCH($B$2&"|xK",Aux_puntos!$1:$1,0))="",NA(),INDEX(Aux_puntos!$A$2:$OJ$901,6,MATCH($B$2&"|xK",Aux_puntos!$1:$1,0))),NA()) | AD10: =IFERROR(IF(INDEX(Aux_puntos!$A$2:$OJ$901,6,MATCH($B$2&"|yK",Aux_puntos!$1:$1,0))="",NA(),INDEX(Aux_puntos!$A$2:$OJ$901,6,MATCH($B$2&"|yK",Aux_puntos!$1:$1,0))),NA()) | AE10: =IFERROR(IF(INDEX(Aux_puntos!$A$2:$OJ$901,6,MATCH($B$2&"|xC",Aux_puntos!$1:$1,0))="",NA(),INDEX(Aux_puntos!$A$2:$OJ$901,6,MATCH($B$2&"|xC",Aux_puntos!$1:$1,0))),NA()) | AF10: =IFERROR(IF(INDEX(Aux_puntos!$A$2:$OJ$901,6,MATCH($B$2&"|yC",Aux_puntos!$1:$1,0))="",NA(),INDEX(Aux_puntos!$A$2:$OJ$901,6,MATCH($B$2&"|yC",Aux_puntos!$1:$1,0))),NA()) | AG10: =IFERROR(IF(INDEX(Aux_puntos!$A$2:$OJ$901,6,MATCH($B$2&"|xI",Aux_puntos!$1:$1,0))="",NA(),INDEX(Aux_puntos!$A$2:$OJ$901,6,MATCH($B$2&"|xI",Aux_puntos!$1:$1,0))),NA()) | AH10: =IFERROR(IF(INDEX(Aux_puntos!$A$2:$OJ$901,6,MATCH($B$2&"|yI",Aux_puntos!$1:$1,0))="",NA(),INDEX(Aux_puntos!$A$2:$OJ$901,6,MATCH($B$2&"|yI",Aux_puntos!$1:$1,0))),NA()) | AI10: =IFERROR(IF(INDEX(Aux_puntos!$A$2:$OJ$901,6,MATCH($B$2&"|xN",Aux_puntos!$1:$1,0))="",NA(),INDEX(Aux_puntos!$A$2:$OJ$901,6,MATCH($B$2&"|xN",Aux_puntos!$1:$1,0))),NA()) | AJ10: =IFERROR(IF(INDEX(Aux_puntos!$A$2:$OJ$901,6,MATCH($B$2&"|yN",Aux_puntos!$1:$1,0))="",NA(),INDEX(Aux_puntos!$A$2:$OJ$901,6,MATCH($B$2&"|yN",Aux_puntos!$1:$1,0))),NA())
A11: Presión de baja, P_baja [kPa] | B11: =INDEX(Aux_tablero!$B$24:$AY$24,MATCH($B$2,Aux_tablero!$B$1:$AY$1,0)) | AC11: =IFERROR(IF(INDEX(Aux_puntos!$A$2:$OJ$901,7,MATCH($B$2&"|xK",Aux_puntos!$1:$1,0))="",NA(),INDEX(Aux_puntos!$A$2:$OJ$901,7,MATCH($B$2&"|xK",Aux_puntos!$1:$1,0))),NA()) | AD11: =IFERROR(IF(INDEX(Aux_puntos!$A$2:$OJ$901,7,MATCH($B$2&"|yK",Aux_puntos!$1:$1,0))="",NA(),INDEX(Aux_puntos!$A$2:$OJ$901,7,MATCH($B$2&"|yK",Aux_puntos!$1:$1,0))),NA()) | AE11: =IFERROR(IF(INDEX(Aux_puntos!$A$2:$OJ$901,7,MATCH($B$2&"|xC",Aux_puntos!$1:$1,0))="",NA(),INDEX(Aux_puntos!$A$2:$OJ$901,7,MATCH($B$2&"|xC",Aux_puntos!$1:$1,0))),NA()) | AF11: =IFERROR(IF(INDEX(Aux_puntos!$A$2:$OJ$901,7,MATCH($B$2&"|yC",Aux_puntos!$1:$1,0))="",NA(),INDEX(Aux_puntos!$A$2:$OJ$901,7,MATCH($B$2&"|yC",Aux_puntos!$1:$1,0))),NA()) | AG11: =IFERROR(IF(INDEX(Aux_puntos!$A$2:$OJ$901,7,MATCH($B$2&"|xI",Aux_puntos!$1:$1,0))="",NA(),INDEX(Aux_puntos!$A$2:$OJ$901,7,MATCH($B$2&"|xI",Aux_puntos!$1:$1,0))),NA()) | AH11: =IFERROR(IF(INDEX(Aux_puntos!$A$2:$OJ$901,7,MATCH($B$2&"|yI",Aux_puntos!$1:$1,0))="",NA(),INDEX(Aux_puntos!$A$2:$OJ$901,7,MATCH($B$2&"|yI",Aux_puntos!$1:$1,0))),NA()) | AI11: =IFERROR(IF(INDEX(Aux_puntos!$A$2:$OJ$901,7,MATCH($B$2&"|xN",Aux_puntos!$1:$1,0))="",NA(),INDEX(Aux_puntos!$A$2:$OJ$901,7,MATCH($B$2&"|xN",Aux_puntos!$1:$1,0))),NA()) | AJ11: =IFERROR(IF(INDEX(Aux_puntos!$A$2:$OJ$901,7,MATCH($B$2&"|yN",Aux_puntos!$1:$1,0))="",NA(),INDEX(Aux_puntos!$A$2:$OJ$901,7,MATCH($B$2&"|yN",Aux_puntos!$1:$1,0))),NA())
A12: Fracción de amoníaco de la mezcla base, x_b [–] | B12: =INDEX(Aux_tablero!$B$25:$AY$25,MATCH($B$2,Aux_tablero!$B$1:$AY$1,0)) | Z12: O1 título | AA12: =INDEX(Aux_tablero!$B$17:$AY$17,MATCH($B$2,Aux_tablero!$B$1:$AY$1,0)) | AC12: =IFERROR(IF(INDEX(Aux_puntos!$A$2:$OJ$901,8,MATCH($B$2&"|xK",Aux_puntos!$1:$1,0))="",NA(),INDEX(Aux_puntos!$A$2:$OJ$901,8,MATCH($B$2&"|xK",Aux_puntos!$1:$1,0))),NA()) | AD12: =IFERROR(IF(INDEX(Aux_puntos!$A$2:$OJ$901,8,MATCH($B$2&"|yK",Aux_puntos!$1:$1,0))="",NA(),INDEX(Aux_puntos!$A$2:$OJ$901,8,MATCH($B$2&"|yK",Aux_puntos!$1:$1,0))),NA()) | AE12: =IFERROR(IF(INDEX(Aux_puntos!$A$2:$OJ$901,8,MATCH($B$2&"|xC",Aux_puntos!$1:$1,0))="",NA(),INDEX(Aux_puntos!$A$2:$OJ$901,8,MATCH($B$2&"|xC",Aux_puntos!$1:$1,0))),NA()) | AF12: =IFERROR(IF(INDEX(Aux_puntos!$A$2:$OJ$901,8,MATCH($B$2&"|yC",Aux_puntos!$1:$1,0))="",NA(),INDEX(Aux_puntos!$A$2:$OJ$901,8,MATCH($B$2&"|yC",Aux_puntos!$1:$1,0))),NA()) | AG12: =IFERROR(IF(INDEX(Aux_puntos!$A$2:$OJ$901,8,MATCH($B$2&"|xI",Aux_puntos!$1:$1,0))="",NA(),INDEX(Aux_puntos!$A$2:$OJ$901,8,MATCH($B$2&"|xI",Aux_puntos!$1:$1,0))),NA()) | AH12: =IFERROR(IF(INDEX(Aux_puntos!$A$2:$OJ$901,8,MATCH($B$2&"|yI",Aux_puntos!$1:$1,0))="",NA(),INDEX(Aux_puntos!$A$2:$OJ$901,8,MATCH($B$2&"|yI",Aux_puntos!$1:$1,0))),NA()) | AI12: =IFERROR(IF(INDEX(Aux_puntos!$A$2:$OJ$901,8,MATCH($B$2&"|xN",Aux_puntos!$1:$1,0))="",NA(),INDEX(Aux_puntos!$A$2:$OJ$901,8,MATCH($B$2&"|xN",Aux_puntos!$1:$1,0))),NA()) | AJ12: =IFERROR(IF(INDEX(Aux_puntos!$A$2:$OJ$901,8,MATCH($B$2&"|yN",Aux_puntos!$1:$1,0))="",NA(),INDEX(Aux_puntos!$A$2:$OJ$901,8,MATCH($B$2&"|yN",Aux_puntos!$1:$1,0))),NA())
A13: Flujo másico base, m_b [kg/s] | B13: =INDEX(Aux_tablero!$B$26:$AY$26,MATCH($B$2,Aux_tablero!$B$1:$AY$1,0)) | Z13: O2 cavitación | AA13: =INDEX(Aux_tablero!$B$18:$AY$18,MATCH($B$2,Aux_tablero!$B$1:$AY$1,0)) | AC13: =IFERROR(IF(INDEX(Aux_puntos!$A$2:$OJ$901,9,MATCH($B$2&"|xK",Aux_puntos!$1:$1,0))="",NA(),INDEX(Aux_puntos!$A$2:$OJ$901,9,MATCH($B$2&"|xK",Aux_puntos!$1:$1,0))),NA()) | AD13: =IFERROR(IF(INDEX(Aux_puntos!$A$2:$OJ$901,9,MATCH($B$2&"|yK",Aux_puntos!$1:$1,0))="",NA(),INDEX(Aux_puntos!$A$2:$OJ$901,9,MATCH($B$2&"|yK",Aux_puntos!$1:$1,0))),NA()) | AE13: =IFERROR(IF(INDEX(Aux_puntos!$A$2:$OJ$901,9,MATCH($B$2&"|xC",Aux_puntos!$1:$1,0))="",NA(),INDEX(Aux_puntos!$A$2:$OJ$901,9,MATCH($B$2&"|xC",Aux_puntos!$1:$1,0))),NA()) | AF13: =IFERROR(IF(INDEX(Aux_puntos!$A$2:$OJ$901,9,MATCH($B$2&"|yC",Aux_puntos!$1:$1,0))="",NA(),INDEX(Aux_puntos!$A$2:$OJ$901,9,MATCH($B$2&"|yC",Aux_puntos!$1:$1,0))),NA()) | AG13: =IFERROR(IF(INDEX(Aux_puntos!$A$2:$OJ$901,9,MATCH($B$2&"|xI",Aux_puntos!$1:$1,0))="",NA(),INDEX(Aux_puntos!$A$2:$OJ$901,9,MATCH($B$2&"|xI",Aux_puntos!$1:$1,0))),NA()) | AH13: =IFERROR(IF(INDEX(Aux_puntos!$A$2:$OJ$901,9,MATCH($B$2&"|yI",Aux_puntos!$1:$1,0))="",NA(),INDEX(Aux_puntos!$A$2:$OJ$901,9,MATCH($B$2&"|yI",Aux_puntos!$1:$1,0))),NA()) | AI13: =IFERROR(IF(INDEX(Aux_puntos!$A$2:$OJ$901,9,MATCH($B$2&"|xN",Aux_puntos!$1:$1,0))="",NA(),INDEX(Aux_puntos!$A$2:$OJ$901,9,MATCH($B$2&"|xN",Aux_puntos!$1:$1,0))),NA()) | AJ13: =IFERROR(IF(INDEX(Aux_puntos!$A$2:$OJ$901,9,MATCH($B$2&"|yN",Aux_puntos!$1:$1,0))="",NA(),INDEX(Aux_puntos!$A$2:$OJ$901,9,MATCH($B$2&"|yN",Aux_puntos!$1:$1,0))),NA())
A14: Eficiencia isentrópica de la turbina, η_t [–] | B14: =INDEX(Aux_tablero!$B$27:$AY$27,MATCH($B$2,Aux_tablero!$B$1:$AY$1,0)) | Z14: O3 trabajo neto | AA14: =INDEX(Aux_tablero!$B$19:$AY$19,MATCH($B$2,Aux_tablero!$B$1:$AY$1,0)) | AC14: =IFERROR(IF(INDEX(Aux_puntos!$A$2:$OJ$901,10,MATCH($B$2&"|xK",Aux_puntos!$1:$1,0))="",NA(),INDEX(Aux_puntos!$A$2:$OJ$901,10,MATCH($B$2&"|xK",Aux_puntos!$1:$1,0))),NA()) | AD14: =IFERROR(IF(INDEX(Aux_puntos!$A$2:$OJ$901,10,MATCH($B$2&"|yK",Aux_puntos!$1:$1,0))="",NA(),INDEX(Aux_puntos!$A$2:$OJ$901,10,MATCH($B$2&"|yK",Aux_puntos!$1:$1,0))),NA()) | AE14: =IFERROR(IF(INDEX(Aux_puntos!$A$2:$OJ$901,10,MATCH($B$2&"|xC",Aux_puntos!$1:$1,0))="",NA(),INDEX(Aux_puntos!$A$2:$OJ$901,10,MATCH($B$2&"|xC",Aux_puntos!$1:$1,0))),NA()) | AF14: =IFERROR(IF(INDEX(Aux_puntos!$A$2:$OJ$901,10,MATCH($B$2&"|yC",Aux_puntos!$1:$1,0))="",NA(),INDEX(Aux_puntos!$A$2:$OJ$901,10,MATCH($B$2&"|yC",Aux_puntos!$1:$1,0))),NA()) | AG14: =IFERROR(IF(INDEX(Aux_puntos!$A$2:$OJ$901,10,MATCH($B$2&"|xI",Aux_puntos!$1:$1,0))="",NA(),INDEX(Aux_puntos!$A$2:$OJ$901,10,MATCH($B$2&"|xI",Aux_puntos!$1:$1,0))),NA()) | AH14: =IFERROR(IF(INDEX(Aux_puntos!$A$2:$OJ$901,10,MATCH($B$2&"|yI",Aux_puntos!$1:$1,0))="",NA(),INDEX(Aux_puntos!$A$2:$OJ$901,10,MATCH($B$2&"|yI",Aux_puntos!$1:$1,0))),NA()) | AI14: =IFERROR(IF(INDEX(Aux_puntos!$A$2:$OJ$901,10,MATCH($B$2&"|xN",Aux_puntos!$1:$1,0))="",NA(),INDEX(Aux_puntos!$A$2:$OJ$901,10,MATCH($B$2&"|xN",Aux_puntos!$1:$1,0))),NA()) | AJ14: =IFERROR(IF(INDEX(Aux_puntos!$A$2:$OJ$901,10,MATCH($B$2&"|yN",Aux_puntos!$1:$1,0))="",NA(),INDEX(Aux_puntos!$A$2:$OJ$901,10,MATCH($B$2&"|yN",Aux_puntos!$1:$1,0))),NA())
A15: Eficiencia isentrópica de la bomba, η_p [–] | B15: =INDEX(Aux_tablero!$B$28:$AY$28,MATCH($B$2,Aux_tablero!$B$1:$AY$1,0)) | Z15: O5 separador | AA15: =INDEX(Aux_tablero!$B$20:$AY$20,MATCH($B$2,Aux_tablero!$B$1:$AY$1,0)) | AC15: =IFERROR(IF(INDEX(Aux_puntos!$A$2:$OJ$901,11,MATCH($B$2&"|xK",Aux_puntos!$1:$1,0))="",NA(),INDEX(Aux_puntos!$A$2:$OJ$901,11,MATCH($B$2&"|xK",Aux_puntos!$1:$1,0))),NA()) | AD15: =IFERROR(IF(INDEX(Aux_puntos!$A$2:$OJ$901,11,MATCH($B$2&"|yK",Aux_puntos!$1:$1,0))="",NA(),INDEX(Aux_puntos!$A$2:$OJ$901,11,MATCH($B$2&"|yK",Aux_puntos!$1:$1,0))),NA()) | AE15: =IFERROR(IF(INDEX(Aux_puntos!$A$2:$OJ$901,11,MATCH($B$2&"|xC",Aux_puntos!$1:$1,0))="",NA(),INDEX(Aux_puntos!$A$2:$OJ$901,11,MATCH($B$2&"|xC",Aux_puntos!$1:$1,0))),NA()) | AF15: =IFERROR(IF(INDEX(Aux_puntos!$A$2:$OJ$901,11,MATCH($B$2&"|yC",Aux_puntos!$1:$1,0))="",NA(),INDEX(Aux_puntos!$A$2:$OJ$901,11,MATCH($B$2&"|yC",Aux_puntos!$1:$1,0))),NA()) | AG15: =IFERROR(IF(INDEX(Aux_puntos!$A$2:$OJ$901,11,MATCH($B$2&"|xI",Aux_puntos!$1:$1,0))="",NA(),INDEX(Aux_puntos!$A$2:$OJ$901,11,MATCH($B$2&"|xI",Aux_puntos!$1:$1,0))),NA()) | AH15: =IFERROR(IF(INDEX(Aux_puntos!$A$2:$OJ$901,11,MATCH($B$2&"|yI",Aux_puntos!$1:$1,0))="",NA(),INDEX(Aux_puntos!$A$2:$OJ$901,11,MATCH($B$2&"|yI",Aux_puntos!$1:$1,0))),NA()) | AI15: =IFERROR(IF(INDEX(Aux_puntos!$A$2:$OJ$901,11,MATCH($B$2&"|xN",Aux_puntos!$1:$1,0))="",NA(),INDEX(Aux_puntos!$A$2:$OJ$901,11,MATCH($B$2&"|xN",Aux_puntos!$1:$1,0))),NA()) | AJ15: =IFERROR(IF(INDEX(Aux_puntos!$A$2:$OJ$901,11,MATCH($B$2&"|yN",Aux_puntos!$1:$1,0))="",NA(),INDEX(Aux_puntos!$A$2:$OJ$901,11,MATCH($B$2&"|yN",Aux_puntos!$1:$1,0))),NA())
A16: Efectividad del generador de vapor, ε_HRVG [–] | B16: =INDEX(Aux_tablero!$B$29:$AY$29,MATCH($B$2,Aux_tablero!$B$1:$AY$1,0)) | AC16: =IFERROR(IF(INDEX(Aux_puntos!$A$2:$OJ$901,12,MATCH($B$2&"|xK",Aux_puntos!$1:$1,0))="",NA(),INDEX(Aux_puntos!$A$2:$OJ$901,12,MATCH($B$2&"|xK",Aux_puntos!$1:$1,0))),NA()) | AD16: =IFERROR(IF(INDEX(Aux_puntos!$A$2:$OJ$901,12,MATCH($B$2&"|yK",Aux_puntos!$1:$1,0))="",NA(),INDEX(Aux_puntos!$A$2:$OJ$901,12,MATCH($B$2&"|yK",Aux_puntos!$1:$1,0))),NA()) | AE16: =IFERROR(IF(INDEX(Aux_puntos!$A$2:$OJ$901,12,MATCH($B$2&"|xC",Aux_puntos!$1:$1,0))="",NA(),INDEX(Aux_puntos!$A$2:$OJ$901,12,MATCH($B$2&"|xC",Aux_puntos!$1:$1,0))),NA()) | AF16: =IFERROR(IF(INDEX(Aux_puntos!$A$2:$OJ$901,12,MATCH($B$2&"|yC",Aux_puntos!$1:$1,0))="",NA(),INDEX(Aux_puntos!$A$2:$OJ$901,12,MATCH($B$2&"|yC",Aux_puntos!$1:$1,0))),NA()) | AG16: =IFERROR(IF(INDEX(Aux_puntos!$A$2:$OJ$901,12,MATCH($B$2&"|xI",Aux_puntos!$1:$1,0))="",NA(),INDEX(Aux_puntos!$A$2:$OJ$901,12,MATCH($B$2&"|xI",Aux_puntos!$1:$1,0))),NA()) | AH16: =IFERROR(IF(INDEX(Aux_puntos!$A$2:$OJ$901,12,MATCH($B$2&"|yI",Aux_puntos!$1:$1,0))="",NA(),INDEX(Aux_puntos!$A$2:$OJ$901,12,MATCH($B$2&"|yI",Aux_puntos!$1:$1,0))),NA()) | AI16: =IFERROR(IF(INDEX(Aux_puntos!$A$2:$OJ$901,12,MATCH($B$2&"|xN",Aux_puntos!$1:$1,0))="",NA(),INDEX(Aux_puntos!$A$2:$OJ$901,12,MATCH($B$2&"|xN",Aux_puntos!$1:$1,0))),NA()) | AJ16: =IFERROR(IF(INDEX(Aux_puntos!$A$2:$OJ$901,12,MATCH($B$2&"|yN",Aux_puntos!$1:$1,0))="",NA(),INDEX(Aux_puntos!$A$2:$OJ$901,12,MATCH($B$2&"|yN",Aux_puntos!$1:$1,0))),NA())
A17: Efectividad del regenerador, ε_reg [–] | B17: =INDEX(Aux_tablero!$B$30:$AY$30,MATCH($B$2,Aux_tablero!$B$1:$AY$1,0)) | AC17: =IFERROR(IF(INDEX(Aux_puntos!$A$2:$OJ$901,13,MATCH($B$2&"|xK",Aux_puntos!$1:$1,0))="",NA(),INDEX(Aux_puntos!$A$2:$OJ$901,13,MATCH($B$2&"|xK",Aux_puntos!$1:$1,0))),NA()) | AD17: =IFERROR(IF(INDEX(Aux_puntos!$A$2:$OJ$901,13,MATCH($B$2&"|yK",Aux_puntos!$1:$1,0))="",NA(),INDEX(Aux_puntos!$A$2:$OJ$901,13,MATCH($B$2&"|yK",Aux_puntos!$1:$1,0))),NA()) | AE17: =IFERROR(IF(INDEX(Aux_puntos!$A$2:$OJ$901,13,MATCH($B$2&"|xC",Aux_puntos!$1:$1,0))="",NA(),INDEX(Aux_puntos!$A$2:$OJ$901,13,MATCH($B$2&"|xC",Aux_puntos!$1:$1,0))),NA()) | AF17: =IFERROR(IF(INDEX(Aux_puntos!$A$2:$OJ$901,13,MATCH($B$2&"|yC",Aux_puntos!$1:$1,0))="",NA(),INDEX(Aux_puntos!$A$2:$OJ$901,13,MATCH($B$2&"|yC",Aux_puntos!$1:$1,0))),NA()) | AG17: =IFERROR(IF(INDEX(Aux_puntos!$A$2:$OJ$901,13,MATCH($B$2&"|xI",Aux_puntos!$1:$1,0))="",NA(),INDEX(Aux_puntos!$A$2:$OJ$901,13,MATCH($B$2&"|xI",Aux_puntos!$1:$1,0))),NA()) | AH17: =IFERROR(IF(INDEX(Aux_puntos!$A$2:$OJ$901,13,MATCH($B$2&"|yI",Aux_puntos!$1:$1,0))="",NA(),INDEX(Aux_puntos!$A$2:$OJ$901,13,MATCH($B$2&"|yI",Aux_puntos!$1:$1,0))),NA()) | AI17: =IFERROR(IF(INDEX(Aux_puntos!$A$2:$OJ$901,13,MATCH($B$2&"|xN",Aux_puntos!$1:$1,0))="",NA(),INDEX(Aux_puntos!$A$2:$OJ$901,13,MATCH($B$2&"|xN",Aux_puntos!$1:$1,0))),NA()) | AJ17: =IFERROR(IF(INDEX(Aux_puntos!$A$2:$OJ$901,13,MATCH($B$2&"|yN",Aux_puntos!$1:$1,0))="",NA(),INDEX(Aux_puntos!$A$2:$OJ$901,13,MATCH($B$2&"|yN",Aux_puntos!$1:$1,0))),NA())
A18: Efectividad del condensador, ε_cond [–] | B18: =INDEX(Aux_tablero!$B$31:$AY$31,MATCH($B$2,Aux_tablero!$B$1:$AY$1,0)) | AC18: =IFERROR(IF(INDEX(Aux_puntos!$A$2:$OJ$901,14,MATCH($B$2&"|xK",Aux_puntos!$1:$1,0))="",NA(),INDEX(Aux_puntos!$A$2:$OJ$901,14,MATCH($B$2&"|xK",Aux_puntos!$1:$1,0))),NA()) | AD18: =IFERROR(IF(INDEX(Aux_puntos!$A$2:$OJ$901,14,MATCH($B$2&"|yK",Aux_puntos!$1:$1,0))="",NA(),INDEX(Aux_puntos!$A$2:$OJ$901,14,MATCH($B$2&"|yK",Aux_puntos!$1:$1,0))),NA()) | AE18: =IFERROR(IF(INDEX(Aux_puntos!$A$2:$OJ$901,14,MATCH($B$2&"|xC",Aux_puntos!$1:$1,0))="",NA(),INDEX(Aux_puntos!$A$2:$OJ$901,14,MATCH($B$2&"|xC",Aux_puntos!$1:$1,0))),NA()) | AF18: =IFERROR(IF(INDEX(Aux_puntos!$A$2:$OJ$901,14,MATCH($B$2&"|yC",Aux_puntos!$1:$1,0))="",NA(),INDEX(Aux_puntos!$A$2:$OJ$901,14,MATCH($B$2&"|yC",Aux_puntos!$1:$1,0))),NA()) | AG18: =IFERROR(IF(INDEX(Aux_puntos!$A$2:$OJ$901,14,MATCH($B$2&"|xI",Aux_puntos!$1:$1,0))="",NA(),INDEX(Aux_puntos!$A$2:$OJ$901,14,MATCH($B$2&"|xI",Aux_puntos!$1:$1,0))),NA()) | AH18: =IFERROR(IF(INDEX(Aux_puntos!$A$2:$OJ$901,14,MATCH($B$2&"|yI",Aux_puntos!$1:$1,0))="",NA(),INDEX(Aux_puntos!$A$2:$OJ$901,14,MATCH($B$2&"|yI",Aux_puntos!$1:$1,0))),NA()) | AI18: =IFERROR(IF(INDEX(Aux_puntos!$A$2:$OJ$901,14,MATCH($B$2&"|xN",Aux_puntos!$1:$1,0))="",NA(),INDEX(Aux_puntos!$A$2:$OJ$901,14,MATCH($B$2&"|xN",Aux_puntos!$1:$1,0))),NA()) | AJ18: =IFERROR(IF(INDEX(Aux_puntos!$A$2:$OJ$901,14,MATCH($B$2&"|yN",Aux_puntos!$1:$1,0))="",NA(),INDEX(Aux_puntos!$A$2:$OJ$901,14,MATCH($B$2&"|yN",Aux_puntos!$1:$1,0))),NA())
A19: Piso de O2 (T de diseño de la bomba) [K] | B19: =INDEX(Aux_tablero!$B$32:$AY$32,MATCH($B$2,Aux_tablero!$B$1:$AY$1,0)) | AC19: =IFERROR(IF(INDEX(Aux_puntos!$A$2:$OJ$901,15,MATCH($B$2&"|xK",Aux_puntos!$1:$1,0))="",NA(),INDEX(Aux_puntos!$A$2:$OJ$901,15,MATCH($B$2&"|xK",Aux_puntos!$1:$1,0))),NA()) | AD19: =IFERROR(IF(INDEX(Aux_puntos!$A$2:$OJ$901,15,MATCH($B$2&"|yK",Aux_puntos!$1:$1,0))="",NA(),INDEX(Aux_puntos!$A$2:$OJ$901,15,MATCH($B$2&"|yK",Aux_puntos!$1:$1,0))),NA()) | AE19: =IFERROR(IF(INDEX(Aux_puntos!$A$2:$OJ$901,15,MATCH($B$2&"|xC",Aux_puntos!$1:$1,0))="",NA(),INDEX(Aux_puntos!$A$2:$OJ$901,15,MATCH($B$2&"|xC",Aux_puntos!$1:$1,0))),NA()) | AF19: =IFERROR(IF(INDEX(Aux_puntos!$A$2:$OJ$901,15,MATCH($B$2&"|yC",Aux_puntos!$1:$1,0))="",NA(),INDEX(Aux_puntos!$A$2:$OJ$901,15,MATCH($B$2&"|yC",Aux_puntos!$1:$1,0))),NA()) | AG19: =IFERROR(IF(INDEX(Aux_puntos!$A$2:$OJ$901,15,MATCH($B$2&"|xI",Aux_puntos!$1:$1,0))="",NA(),INDEX(Aux_puntos!$A$2:$OJ$901,15,MATCH($B$2&"|xI",Aux_puntos!$1:$1,0))),NA()) | AH19: =IFERROR(IF(INDEX(Aux_puntos!$A$2:$OJ$901,15,MATCH($B$2&"|yI",Aux_puntos!$1:$1,0))="",NA(),INDEX(Aux_puntos!$A$2:$OJ$901,15,MATCH($B$2&"|yI",Aux_puntos!$1:$1,0))),NA()) | AI19: =IFERROR(IF(INDEX(Aux_puntos!$A$2:$OJ$901,15,MATCH($B$2&"|xN",Aux_puntos!$1:$1,0))="",NA(),INDEX(Aux_puntos!$A$2:$OJ$901,15,MATCH($B$2&"|xN",Aux_puntos!$1:$1,0))),NA()) | AJ19: =IFERROR(IF(INDEX(Aux_puntos!$A$2:$OJ$901,15,MATCH($B$2&"|yN",Aux_puntos!$1:$1,0))="",NA(),INDEX(Aux_puntos!$A$2:$OJ$901,15,MATCH($B$2&"|yN",Aux_puntos!$1:$1,0))),NA())
A20: motor | B20: =INDEX(Aux_tablero!$B$33:$AY$33,MATCH($B$2,Aux_tablero!$B$1:$AY$1,0)) | AC20: =IFERROR(IF(INDEX(Aux_puntos!$A$2:$OJ$901,16,MATCH($B$2&"|xK",Aux_puntos!$1:$1,0))="",NA(),INDEX(Aux_puntos!$A$2:$OJ$901,16,MATCH($B$2&"|xK",Aux_puntos!$1:$1,0))),NA()) | AD20: =IFERROR(IF(INDEX(Aux_puntos!$A$2:$OJ$901,16,MATCH($B$2&"|yK",Aux_puntos!$1:$1,0))="",NA(),INDEX(Aux_puntos!$A$2:$OJ$901,16,MATCH($B$2&"|yK",Aux_puntos!$1:$1,0))),NA()) | AE20: =IFERROR(IF(INDEX(Aux_puntos!$A$2:$OJ$901,16,MATCH($B$2&"|xC",Aux_puntos!$1:$1,0))="",NA(),INDEX(Aux_puntos!$A$2:$OJ$901,16,MATCH($B$2&"|xC",Aux_puntos!$1:$1,0))),NA()) | AF20: =IFERROR(IF(INDEX(Aux_puntos!$A$2:$OJ$901,16,MATCH($B$2&"|yC",Aux_puntos!$1:$1,0))="",NA(),INDEX(Aux_puntos!$A$2:$OJ$901,16,MATCH($B$2&"|yC",Aux_puntos!$1:$1,0))),NA()) | AG20: =IFERROR(IF(INDEX(Aux_puntos!$A$2:$OJ$901,16,MATCH($B$2&"|xI",Aux_puntos!$1:$1,0))="",NA(),INDEX(Aux_puntos!$A$2:$OJ$901,16,MATCH($B$2&"|xI",Aux_puntos!$1:$1,0))),NA()) | AH20: =IFERROR(IF(INDEX(Aux_puntos!$A$2:$OJ$901,16,MATCH($B$2&"|yI",Aux_puntos!$1:$1,0))="",NA(),INDEX(Aux_puntos!$A$2:$OJ$901,16,MATCH($B$2&"|yI",Aux_puntos!$1:$1,0))),NA()) | AI20: =IFERROR(IF(INDEX(Aux_puntos!$A$2:$OJ$901,16,MATCH($B$2&"|xN",Aux_puntos!$1:$1,0))="",NA(),INDEX(Aux_puntos!$A$2:$OJ$901,16,MATCH($B$2&"|xN",Aux_puntos!$1:$1,0))),NA()) | AJ20: =IFERROR(IF(INDEX(Aux_puntos!$A$2:$OJ$901,16,MATCH($B$2&"|yN",Aux_puntos!$1:$1,0))="",NA(),INDEX(Aux_puntos!$A$2:$OJ$901,16,MATCH($B$2&"|yN",Aux_puntos!$1:$1,0))),NA())
AC21: =IFERROR(IF(INDEX(Aux_puntos!$A$2:$OJ$901,17,MATCH($B$2&"|xK",Aux_puntos!$1:$1,0))="",NA(),INDEX(Aux_puntos!$A$2:$OJ$901,17,MATCH($B$2&"|xK",Aux_puntos!$1:$1,0))),NA()) | AD21: =IFERROR(IF(INDEX(Aux_puntos!$A$2:$OJ$901,17,MATCH($B$2&"|yK",Aux_puntos!$1:$1,0))="",NA(),INDEX(Aux_puntos!$A$2:$OJ$901,17,MATCH($B$2&"|yK",Aux_puntos!$1:$1,0))),NA()) | AE21: =IFERROR(IF(INDEX(Aux_puntos!$A$2:$OJ$901,17,MATCH($B$2&"|xC",Aux_puntos!$1:$1,0))="",NA(),INDEX(Aux_puntos!$A$2:$OJ$901,17,MATCH($B$2&"|xC",Aux_puntos!$1:$1,0))),NA()) | AF21: =IFERROR(IF(INDEX(Aux_puntos!$A$2:$OJ$901,17,MATCH($B$2&"|yC",Aux_puntos!$1:$1,0))="",NA(),INDEX(Aux_puntos!$A$2:$OJ$901,17,MATCH($B$2&"|yC",Aux_puntos!$1:$1,0))),NA()) | AG21: =IFERROR(IF(INDEX(Aux_puntos!$A$2:$OJ$901,17,MATCH($B$2&"|xI",Aux_puntos!$1:$1,0))="",NA(),INDEX(Aux_puntos!$A$2:$OJ$901,17,MATCH($B$2&"|xI",Aux_puntos!$1:$1,0))),NA()) | AH21: =IFERROR(IF(INDEX(Aux_puntos!$A$2:$OJ$901,17,MATCH($B$2&"|yI",Aux_puntos!$1:$1,0))="",NA(),INDEX(Aux_puntos!$A$2:$OJ$901,17,MATCH($B$2&"|yI",Aux_puntos!$1:$1,0))),NA()) | AI21: =IFERROR(IF(INDEX(Aux_puntos!$A$2:$OJ$901,17,MATCH($B$2&"|xN",Aux_puntos!$1:$1,0))="",NA(),INDEX(Aux_puntos!$A$2:$OJ$901,17,MATCH($B$2&"|xN",Aux_puntos!$1:$1,0))),NA()) | AJ21: =IFERROR(IF(INDEX(Aux_puntos!$A$2:$OJ$901,17,MATCH($B$2&"|yN",Aux_puntos!$1:$1,0))="",NA(),INDEX(Aux_puntos!$A$2:$OJ$901,17,MATCH($B$2&"|yN",Aux_puntos!$1:$1,0))),NA())
A22: Pie: | AC22: =IFERROR(IF(INDEX(Aux_puntos!$A$2:$OJ$901,18,MATCH($B$2&"|xK",Aux_puntos!$1:$1,0))="",NA(),INDEX(Aux_puntos!$A$2:$OJ$901,18,MATCH($B$2&"|xK",Aux_puntos!$1:$1,0))),NA()) | AD22: =IFERROR(IF(INDEX(Aux_puntos!$A$2:$OJ$901,18,MATCH($B$2&"|yK",Aux_puntos!$1:$1,0))="",NA(),INDEX(Aux_puntos!$A$2:$OJ$901,18,MATCH($B$2&"|yK",Aux_puntos!$1:$1,0))),NA()) | AE22: =IFERROR(IF(INDEX(Aux_puntos!$A$2:$OJ$901,18,MATCH($B$2&"|xC",Aux_puntos!$1:$1,0))="",NA(),INDEX(Aux_puntos!$A$2:$OJ$901,18,MATCH($B$2&"|xC",Aux_puntos!$1:$1,0))),NA()) | AF22: =IFERROR(IF(INDEX(Aux_puntos!$A$2:$OJ$901,18,MATCH($B$2&"|yC",Aux_puntos!$1:$1,0))="",NA(),INDEX(Aux_puntos!$A$2:$OJ$901,18,MATCH($B$2&"|yC",Aux_puntos!$1:$1,0))),NA()) | AG22: =IFERROR(IF(INDEX(Aux_puntos!$A$2:$OJ$901,18,MATCH($B$2&"|xI",Aux_puntos!$1:$1,0))="",NA(),INDEX(Aux_puntos!$A$2:$OJ$901,18,MATCH($B$2&"|xI",Aux_puntos!$1:$1,0))),NA()) | AH22: =IFERROR(IF(INDEX(Aux_puntos!$A$2:$OJ$901,18,MATCH($B$2&"|yI",Aux_puntos!$1:$1,0))="",NA(),INDEX(Aux_puntos!$A$2:$OJ$901,18,MATCH($B$2&"|yI",Aux_puntos!$1:$1,0))),NA()) | AI22: =IFERROR(IF(INDEX(Aux_puntos!$A$2:$OJ$901,18,MATCH($B$2&"|xN",Aux_puntos!$1:$1,0))="",NA(),INDEX(Aux_puntos!$A$2:$OJ$901,18,MATCH($B$2&"|xN",Aux_puntos!$1:$1,0))),NA()) | AJ22: =IFERROR(IF(INDEX(Aux_puntos!$A$2:$OJ$901,18,MATCH($B$2&"|yN",Aux_puntos!$1:$1,0))="",NA(),INDEX(Aux_puntos!$A$2:$OJ$901,18,MATCH($B$2&"|yN",Aux_puntos!$1:$1,0))),NA())
A23: =INDEX(Aux_tablero!$B$10:$AY$10,MATCH($B$2,Aux_tablero!$B$1:$AY$1,0)) | AC23: =IFERROR(IF(INDEX(Aux_puntos!$A$2:$OJ$901,19,MATCH($B$2&"|xK",Aux_puntos!$1:$1,0))="",NA(),INDEX(Aux_puntos!$A$2:$OJ$901,19,MATCH($B$2&"|xK",Aux_puntos!$1:$1,0))),NA()) | AD23: =IFERROR(IF(INDEX(Aux_puntos!$A$2:$OJ$901,19,MATCH($B$2&"|yK",Aux_puntos!$1:$1,0))="",NA(),INDEX(Aux_puntos!$A$2:$OJ$901,19,MATCH($B$2&"|yK",Aux_puntos!$1:$1,0))),NA()) | AE23: =IFERROR(IF(INDEX(Aux_puntos!$A$2:$OJ$901,19,MATCH($B$2&"|xC",Aux_puntos!$1:$1,0))="",NA(),INDEX(Aux_puntos!$A$2:$OJ$901,19,MATCH($B$2&"|xC",Aux_puntos!$1:$1,0))),NA()) | AF23: =IFERROR(IF(INDEX(Aux_puntos!$A$2:$OJ$901,19,MATCH($B$2&"|yC",Aux_puntos!$1:$1,0))="",NA(),INDEX(Aux_puntos!$A$2:$OJ$901,19,MATCH($B$2&"|yC",Aux_puntos!$1:$1,0))),NA()) | AG23: =IFERROR(IF(INDEX(Aux_puntos!$A$2:$OJ$901,19,MATCH($B$2&"|xI",Aux_puntos!$1:$1,0))="",NA(),INDEX(Aux_puntos!$A$2:$OJ$901,19,MATCH($B$2&"|xI",Aux_puntos!$1:$1,0))),NA()) | AH23: =IFERROR(IF(INDEX(Aux_puntos!$A$2:$OJ$901,19,MATCH($B$2&"|yI",Aux_puntos!$1:$1,0))="",NA(),INDEX(Aux_puntos!$A$2:$OJ$901,19,MATCH($B$2&"|yI",Aux_puntos!$1:$1,0))),NA()) | AI23: =IFERROR(IF(INDEX(Aux_puntos!$A$2:$OJ$901,19,MATCH($B$2&"|xN",Aux_puntos!$1:$1,0))="",NA(),INDEX(Aux_puntos!$A$2:$OJ$901,19,MATCH($B$2&"|xN",Aux_puntos!$1:$1,0))),NA()) | AJ23: =IFERROR(IF(INDEX(Aux_puntos!$A$2:$OJ$901,19,MATCH($B$2&"|yN",Aux_puntos!$1:$1,0))="",NA(),INDEX(Aux_puntos!$A$2:$OJ$901,19,MATCH($B$2&"|yN",Aux_puntos!$1:$1,0))),NA())
AC24: =IFERROR(IF(INDEX(Aux_puntos!$A$2:$OJ$901,20,MATCH($B$2&"|xK",Aux_puntos!$1:$1,0))="",NA(),INDEX(Aux_puntos!$A$2:$OJ$901,20,MATCH($B$2&"|xK",Aux_puntos!$1:$1,0))),NA()) | AD24: =IFERROR(IF(INDEX(Aux_puntos!$A$2:$OJ$901,20,MATCH($B$2&"|yK",Aux_puntos!$1:$1,0))="",NA(),INDEX(Aux_puntos!$A$2:$OJ$901,20,MATCH($B$2&"|yK",Aux_puntos!$1:$1,0))),NA()) | AE24: =IFERROR(IF(INDEX(Aux_puntos!$A$2:$OJ$901,20,MATCH($B$2&"|xC",Aux_puntos!$1:$1,0))="",NA(),INDEX(Aux_puntos!$A$2:$OJ$901,20,MATCH($B$2&"|xC",Aux_puntos!$1:$1,0))),NA()) | AF24: =IFERROR(IF(INDEX(Aux_puntos!$A$2:$OJ$901,20,MATCH($B$2&"|yC",Aux_puntos!$1:$1,0))="",NA(),INDEX(Aux_puntos!$A$2:$OJ$901,20,MATCH($B$2&"|yC",Aux_puntos!$1:$1,0))),NA()) | AG24: =IFERROR(IF(INDEX(Aux_puntos!$A$2:$OJ$901,20,MATCH($B$2&"|xI",Aux_puntos!$1:$1,0))="",NA(),INDEX(Aux_puntos!$A$2:$OJ$901,20,MATCH($B$2&"|xI",Aux_puntos!$1:$1,0))),NA()) | AH24: =IFERROR(IF(INDEX(Aux_puntos!$A$2:$OJ$901,20,MATCH($B$2&"|yI",Aux_puntos!$1:$1,0))="",NA(),INDEX(Aux_puntos!$A$2:$OJ$901,20,MATCH($B$2&"|yI",Aux_puntos!$1:$1,0))),NA()) | AI24: =IFERROR(IF(INDEX(Aux_puntos!$A$2:$OJ$901,20,MATCH($B$2&"|xN",Aux_puntos!$1:$1,0))="",NA(),INDEX(Aux_puntos!$A$2:$OJ$901,20,MATCH($B$2&"|xN",Aux_puntos!$1:$1,0))),NA()) | AJ24: =IFERROR(IF(INDEX(Aux_puntos!$A$2:$OJ$901,20,MATCH($B$2&"|yN",Aux_puntos!$1:$1,0))="",NA(),INDEX(Aux_puntos!$A$2:$OJ$901,20,MATCH($B$2&"|yN",Aux_puntos!$1:$1,0))),NA())
AC25: =IFERROR(IF(INDEX(Aux_puntos!$A$2:$OJ$901,21,MATCH($B$2&"|xK",Aux_puntos!$1:$1,0))="",NA(),INDEX(Aux_puntos!$A$2:$OJ$901,21,MATCH($B$2&"|xK",Aux_puntos!$1:$1,0))),NA()) | AD25: =IFERROR(IF(INDEX(Aux_puntos!$A$2:$OJ$901,21,MATCH($B$2&"|yK",Aux_puntos!$1:$1,0))="",NA(),INDEX(Aux_puntos!$A$2:$OJ$901,21,MATCH($B$2&"|yK",Aux_puntos!$1:$1,0))),NA()) | AE25: =IFERROR(IF(INDEX(Aux_puntos!$A$2:$OJ$901,21,MATCH($B$2&"|xC",Aux_puntos!$1:$1,0))="",NA(),INDEX(Aux_puntos!$A$2:$OJ$901,21,MATCH($B$2&"|xC",Aux_puntos!$1:$1,0))),NA()) | AF25: =IFERROR(IF(INDEX(Aux_puntos!$A$2:$OJ$901,21,MATCH($B$2&"|yC",Aux_puntos!$1:$1,0))="",NA(),INDEX(Aux_puntos!$A$2:$OJ$901,21,MATCH($B$2&"|yC",Aux_puntos!$1:$1,0))),NA()) | AG25: =IFERROR(IF(INDEX(Aux_puntos!$A$2:$OJ$901,21,MATCH($B$2&"|xI",Aux_puntos!$1:$1,0))="",NA(),INDEX(Aux_puntos!$A$2:$OJ$901,21,MATCH($B$2&"|xI",Aux_puntos!$1:$1,0))),NA()) | AH25: =IFERROR(IF(INDEX(Aux_puntos!$A$2:$OJ$901,21,MATCH($B$2&"|yI",Aux_puntos!$1:$1,0))="",NA(),INDEX(Aux_puntos!$A$2:$OJ$901,21,MATCH($B$2&"|yI",Aux_puntos!$1:$1,0))),NA()) | AI25: =IFERROR(IF(INDEX(Aux_puntos!$A$2:$OJ$901,21,MATCH($B$2&"|xN",Aux_puntos!$1:$1,0))="",NA(),INDEX(Aux_puntos!$A$2:$OJ$901,21,MATCH($B$2&"|xN",Aux_puntos!$1:$1,0))),NA()) | AJ25: =IFERROR(IF(INDEX(Aux_puntos!$A$2:$OJ$901,21,MATCH($B$2&"|yN",Aux_puntos!$1:$1,0))="",NA(),INDEX(Aux_puntos!$A$2:$OJ$901,21,MATCH($B$2&"|yN",Aux_puntos!$1:$1,0))),NA())
AC26: =IFERROR(IF(INDEX(Aux_puntos!$A$2:$OJ$901,22,MATCH($B$2&"|xK",Aux_puntos!$1:$1,0))="",NA(),INDEX(Aux_puntos!$A$2:$OJ$901,22,MATCH($B$2&"|xK",Aux_puntos!$1:$1,0))),NA()) | AD26: =IFERROR(IF(INDEX(Aux_puntos!$A$2:$OJ$901,22,MATCH($B$2&"|yK",Aux_puntos!$1:$1,0))="",NA(),INDEX(Aux_puntos!$A$2:$OJ$901,22,MATCH($B$2&"|yK",Aux_puntos!$1:$1,0))),NA()) | AE26: =IFERROR(IF(INDEX(Aux_puntos!$A$2:$OJ$901,22,MATCH($B$2&"|xC",Aux_puntos!$1:$1,0))="",NA(),INDEX(Aux_puntos!$A$2:$OJ$901,22,MATCH($B$2&"|xC",Aux_puntos!$1:$1,0))),NA()) | AF26: =IFERROR(IF(INDEX(Aux_puntos!$A$2:$OJ$901,22,MATCH($B$2&"|yC",Aux_puntos!$1:$1,0))="",NA(),INDEX(Aux_puntos!$A$2:$OJ$901,22,MATCH($B$2&"|yC",Aux_puntos!$1:$1,0))),NA()) | AG26: =IFERROR(IF(INDEX(Aux_puntos!$A$2:$OJ$901,22,MATCH($B$2&"|xI",Aux_puntos!$1:$1,0))="",NA(),INDEX(Aux_puntos!$A$2:$OJ$901,22,MATCH($B$2&"|xI",Aux_puntos!$1:$1,0))),NA()) | AH26: =IFERROR(IF(INDEX(Aux_puntos!$A$2:$OJ$901,22,MATCH($B$2&"|yI",Aux_puntos!$1:$1,0))="",NA(),INDEX(Aux_puntos!$A$2:$OJ$901,22,MATCH($B$2&"|yI",Aux_puntos!$1:$1,0))),NA()) | AI26: =IFERROR(IF(INDEX(Aux_puntos!$A$2:$OJ$901,22,MATCH($B$2&"|xN",Aux_puntos!$1:$1,0))="",NA(),INDEX(Aux_puntos!$A$2:$OJ$901,22,MATCH($B$2&"|xN",Aux_puntos!$1:$1,0))),NA()) | AJ26: =IFERROR(IF(INDEX(Aux_puntos!$A$2:$OJ$901,22,MATCH($B$2&"|yN",Aux_puntos!$1:$1,0))="",NA(),INDEX(Aux_puntos!$A$2:$OJ$901,22,MATCH($B$2&"|yN",Aux_puntos!$1:$1,0))),NA())
AC27: =IFERROR(IF(INDEX(Aux_puntos!$A$2:$OJ$901,23,MATCH($B$2&"|xK",Aux_puntos!$1:$1,0))="",NA(),INDEX(Aux_puntos!$A$2:$OJ$901,23,MATCH($B$2&"|xK",Aux_puntos!$1:$1,0))),NA()) | AD27: =IFERROR(IF(INDEX(Aux_puntos!$A$2:$OJ$901,23,MATCH($B$2&"|yK",Aux_puntos!$1:$1,0))="",NA(),INDEX(Aux_puntos!$A$2:$OJ$901,23,MATCH($B$2&"|yK",Aux_puntos!$1:$1,0))),NA()) | AE27: =IFERROR(IF(INDEX(Aux_puntos!$A$2:$OJ$901,23,MATCH($B$2&"|xC",Aux_puntos!$1:$1,0))="",NA(),INDEX(Aux_puntos!$A$2:$OJ$901,23,MATCH($B$2&"|xC",Aux_puntos!$1:$1,0))),NA()) | AF27: =IFERROR(IF(INDEX(Aux_puntos!$A$2:$OJ$901,23,MATCH($B$2&"|yC",Aux_puntos!$1:$1,0))="",NA(),INDEX(Aux_puntos!$A$2:$OJ$901,23,MATCH($B$2&"|yC",Aux_puntos!$1:$1,0))),NA()) | AG27: =IFERROR(IF(INDEX(Aux_puntos!$A$2:$OJ$901,23,MATCH($B$2&"|xI",Aux_puntos!$1:$1,0))="",NA(),INDEX(Aux_puntos!$A$2:$OJ$901,23,MATCH($B$2&"|xI",Aux_puntos!$1:$1,0))),NA()) | AH27: =IFERROR(IF(INDEX(Aux_puntos!$A$2:$OJ$901,23,MATCH($B$2&"|yI",Aux_puntos!$1:$1,0))="",NA(),INDEX(Aux_puntos!$A$2:$OJ$901,23,MATCH($B$2&"|yI",Aux_puntos!$1:$1,0))),NA()) | AI27: =IFERROR(IF(INDEX(Aux_puntos!$A$2:$OJ$901,23,MATCH($B$2&"|xN",Aux_puntos!$1:$1,0))="",NA(),INDEX(Aux_puntos!$A$2:$OJ$901,23,MATCH($B$2&"|xN",Aux_puntos!$1:$1,0))),NA()) | AJ27: =IFERROR(IF(INDEX(Aux_puntos!$A$2:$OJ$901,23,MATCH($B$2&"|yN",Aux_puntos!$1:$1,0))="",NA(),INDEX(Aux_puntos!$A$2:$OJ$901,23,MATCH($B$2&"|yN",Aux_puntos!$1:$1,0))),NA())
AC28: =IFERROR(IF(INDEX(Aux_puntos!$A$2:$OJ$901,24,MATCH($B$2&"|xK",Aux_puntos!$1:$1,0))="",NA(),INDEX(Aux_puntos!$A$2:$OJ$901,24,MATCH($B$2&"|xK",Aux_puntos!$1:$1,0))),NA()) | AD28: =IFERROR(IF(INDEX(Aux_puntos!$A$2:$OJ$901,24,MATCH($B$2&"|yK",Aux_puntos!$1:$1,0))="",NA(),INDEX(Aux_puntos!$A$2:$OJ$901,24,MATCH($B$2&"|yK",Aux_puntos!$1:$1,0))),NA()) | AE28: =IFERROR(IF(INDEX(Aux_puntos!$A$2:$OJ$901,24,MATCH($B$2&"|xC",Aux_puntos!$1:$1,0))="",NA(),INDEX(Aux_puntos!$A$2:$OJ$901,24,MATCH($B$2&"|xC",Aux_puntos!$1:$1,0))),NA()) | AF28: =IFERROR(IF(INDEX(Aux_puntos!$A$2:$OJ$901,24,MATCH($B$2&"|yC",Aux_puntos!$1:$1,0))="",NA(),INDEX(Aux_puntos!$A$2:$OJ$901,24,MATCH($B$2&"|yC",Aux_puntos!$1:$1,0))),NA()) | AG28: =IFERROR(IF(INDEX(Aux_puntos!$A$2:$OJ$901,24,MATCH($B$2&"|xI",Aux_puntos!$1:$1,0))="",NA(),INDEX(Aux_puntos!$A$2:$OJ$901,24,MATCH($B$2&"|xI",Aux_puntos!$1:$1,0))),NA()) | AH28: =IFERROR(IF(INDEX(Aux_puntos!$A$2:$OJ$901,24,MATCH($B$2&"|yI",Aux_puntos!$1:$1,0))="",NA(),INDEX(Aux_puntos!$A$2:$OJ$901,24,MATCH($B$2&"|yI",Aux_puntos!$1:$1,0))),NA()) | AI28: =IFERROR(IF(INDEX(Aux_puntos!$A$2:$OJ$901,24,MATCH($B$2&"|xN",Aux_puntos!$1:$1,0))="",NA(),INDEX(Aux_puntos!$A$2:$OJ$901,24,MATCH($B$2&"|xN",Aux_puntos!$1:$1,0))),NA()) | AJ28: =IFERROR(IF(INDEX(Aux_puntos!$A$2:$OJ$901,24,MATCH($B$2&"|yN",Aux_puntos!$1:$1,0))="",NA(),INDEX(Aux_puntos!$A$2:$OJ$901,24,MATCH($B$2&"|yN",Aux_puntos!$1:$1,0))),NA())
AC29: =IFERROR(IF(INDEX(Aux_puntos!$A$2:$OJ$901,25,MATCH($B$2&"|xK",Aux_puntos!$1:$1,0))="",NA(),INDEX(Aux_puntos!$A$2:$OJ$901,25,MATCH($B$2&"|xK",Aux_puntos!$1:$1,0))),NA()) | AD29: =IFERROR(IF(INDEX(Aux_puntos!$A$2:$OJ$901,25,MATCH($B$2&"|yK",Aux_puntos!$1:$1,0))="",NA(),INDEX(Aux_puntos!$A$2:$OJ$901,25,MATCH($B$2&"|yK",Aux_puntos!$1:$1,0))),NA()) | AE29: =IFERROR(IF(INDEX(Aux_puntos!$A$2:$OJ$901,25,MATCH($B$2&"|xC",Aux_puntos!$1:$1,0))="",NA(),INDEX(Aux_puntos!$A$2:$OJ$901,25,MATCH($B$2&"|xC",Aux_puntos!$1:$1,0))),NA()) | AF29: =IFERROR(IF(INDEX(Aux_puntos!$A$2:$OJ$901,25,MATCH($B$2&"|yC",Aux_puntos!$1:$1,0))="",NA(),INDEX(Aux_puntos!$A$2:$OJ$901,25,MATCH($B$2&"|yC",Aux_puntos!$1:$1,0))),NA()) | AG29: =IFERROR(IF(INDEX(Aux_puntos!$A$2:$OJ$901,25,MATCH($B$2&"|xI",Aux_puntos!$1:$1,0))="",NA(),INDEX(Aux_puntos!$A$2:$OJ$901,25,MATCH($B$2&"|xI",Aux_puntos!$1:$1,0))),NA()) | AH29: =IFERROR(IF(INDEX(Aux_puntos!$A$2:$OJ$901,25,MATCH($B$2&"|yI",Aux_puntos!$1:$1,0))="",NA(),INDEX(Aux_puntos!$A$2:$OJ$901,25,MATCH($B$2&"|yI",Aux_puntos!$1:$1,0))),NA()) | AI29: =IFERROR(IF(INDEX(Aux_puntos!$A$2:$OJ$901,25,MATCH($B$2&"|xN",Aux_puntos!$1:$1,0))="",NA(),INDEX(Aux_puntos!$A$2:$OJ$901,25,MATCH($B$2&"|xN",Aux_puntos!$1:$1,0))),NA()) | AJ29: =IFERROR(IF(INDEX(Aux_puntos!$A$2:$OJ$901,25,MATCH($B$2&"|yN",Aux_puntos!$1:$1,0))="",NA(),INDEX(Aux_puntos!$A$2:$OJ$901,25,MATCH($B$2&"|yN",Aux_puntos!$1:$1,0))),NA())
AC30: =IFERROR(IF(INDEX(Aux_puntos!$A$2:$OJ$901,26,MATCH($B$2&"|xK",Aux_puntos!$1:$1,0))="",NA(),INDEX(Aux_puntos!$A$2:$OJ$901,26,MATCH($B$2&"|xK",Aux_puntos!$1:$1,0))),NA()) | AD30: =IFERROR(IF(INDEX(Aux_puntos!$A$2:$OJ$901,26,MATCH($B$2&"|yK",Aux_puntos!$1:$1,0))="",NA(),INDEX(Aux_puntos!$A$2:$OJ$901,26,MATCH($B$2&"|yK",Aux_puntos!$1:$1,0))),NA()) | AE30: =IFERROR(IF(INDEX(Aux_puntos!$A$2:$OJ$901,26,MATCH($B$2&"|xC",Aux_puntos!$1:$1,0))="",NA(),INDEX(Aux_puntos!$A$2:$OJ$901,26,MATCH($B$2&"|xC",Aux_puntos!$1:$1,0))),NA()) | AF30: =IFERROR(IF(INDEX(Aux_puntos!$A$2:$OJ$901,26,MATCH($B$2&"|yC",Aux_puntos!$1:$1,0))="",NA(),INDEX(Aux_puntos!$A$2:$OJ$901,26,MATCH($B$2&"|yC",Aux_puntos!$1:$1,0))),NA()) | AG30: =IFERROR(IF(INDEX(Aux_puntos!$A$2:$OJ$901,26,MATCH($B$2&"|xI",Aux_puntos!$1:$1,0))="",NA(),INDEX(Aux_puntos!$A$2:$OJ$901,26,MATCH($B$2&"|xI",Aux_puntos!$1:$1,0))),NA()) | AH30: =IFERROR(IF(INDEX(Aux_puntos!$A$2:$OJ$901,26,MATCH($B$2&"|yI",Aux_puntos!$1:$1,0))="",NA(),INDEX(Aux_puntos!$A$2:$OJ$901,26,MATCH($B$2&"|yI",Aux_puntos!$1:$1,0))),NA()) | AI30: =IFERROR(IF(INDEX(Aux_puntos!$A$2:$OJ$901,26,MATCH($B$2&"|xN",Aux_puntos!$1:$1,0))="",NA(),INDEX(Aux_puntos!$A$2:$OJ$901,26,MATCH($B$2&"|xN",Aux_puntos!$1:$1,0))),NA()) | AJ30: =IFERROR(IF(INDEX(Aux_puntos!$A$2:$OJ$901,26,MATCH($B$2&"|yN",Aux_puntos!$1:$1,0))="",NA(),INDEX(Aux_puntos!$A$2:$OJ$901,26,MATCH($B$2&"|yN",Aux_puntos!$1:$1,0))),NA())
AC31: =IFERROR(IF(INDEX(Aux_puntos!$A$2:$OJ$901,27,MATCH($B$2&"|xK",Aux_puntos!$1:$1,0))="",NA(),INDEX(Aux_puntos!$A$2:$OJ$901,27,MATCH($B$2&"|xK",Aux_puntos!$1:$1,0))),NA()) | AD31: =IFERROR(IF(INDEX(Aux_puntos!$A$2:$OJ$901,27,MATCH($B$2&"|yK",Aux_puntos!$1:$1,0))="",NA(),INDEX(Aux_puntos!$A$2:$OJ$901,27,MATCH($B$2&"|yK",Aux_puntos!$1:$1,0))),NA()) | AE31: =IFERROR(IF(INDEX(Aux_puntos!$A$2:$OJ$901,27,MATCH($B$2&"|xC",Aux_puntos!$1:$1,0))="",NA(),INDEX(Aux_puntos!$A$2:$OJ$901,27,MATCH($B$2&"|xC",Aux_puntos!$1:$1,0))),NA()) | AF31: =IFERROR(IF(INDEX(Aux_puntos!$A$2:$OJ$901,27,MATCH($B$2&"|yC",Aux_puntos!$1:$1,0))="",NA(),INDEX(Aux_puntos!$A$2:$OJ$901,27,MATCH($B$2&"|yC",Aux_puntos!$1:$1,0))),NA()) | AG31: =IFERROR(IF(INDEX(Aux_puntos!$A$2:$OJ$901,27,MATCH($B$2&"|xI",Aux_puntos!$1:$1,0))="",NA(),INDEX(Aux_puntos!$A$2:$OJ$901,27,MATCH($B$2&"|xI",Aux_puntos!$1:$1,0))),NA()) | AH31: =IFERROR(IF(INDEX(Aux_puntos!$A$2:$OJ$901,27,MATCH($B$2&"|yI",Aux_puntos!$1:$1,0))="",NA(),INDEX(Aux_puntos!$A$2:$OJ$901,27,MATCH($B$2&"|yI",Aux_puntos!$1:$1,0))),NA()) | AI31: =IFERROR(IF(INDEX(Aux_puntos!$A$2:$OJ$901,27,MATCH($B$2&"|xN",Aux_puntos!$1:$1,0))="",NA(),INDEX(Aux_puntos!$A$2:$OJ$901,27,MATCH($B$2&"|xN",Aux_puntos!$1:$1,0))),NA()) | AJ31: =IFERROR(IF(INDEX(Aux_puntos!$A$2:$OJ$901,27,MATCH($B$2&"|yN",Aux_puntos!$1:$1,0))="",NA(),INDEX(Aux_puntos!$A$2:$OJ$901,27,MATCH($B$2&"|yN",Aux_puntos!$1:$1,0))),NA())
AC32: =IFERROR(IF(INDEX(Aux_puntos!$A$2:$OJ$901,28,MATCH($B$2&"|xK",Aux_puntos!$1:$1,0))="",NA(),INDEX(Aux_puntos!$A$2:$OJ$901,28,MATCH($B$2&"|xK",Aux_puntos!$1:$1,0))),NA()) | AD32: =IFERROR(IF(INDEX(Aux_puntos!$A$2:$OJ$901,28,MATCH($B$2&"|yK",Aux_puntos!$1:$1,0))="",NA(),INDEX(Aux_puntos!$A$2:$OJ$901,28,MATCH($B$2&"|yK",Aux_puntos!$1:$1,0))),NA()) | AE32: =IFERROR(IF(INDEX(Aux_puntos!$A$2:$OJ$901,28,MATCH($B$2&"|xC",Aux_puntos!$1:$1,0))="",NA(),INDEX(Aux_puntos!$A$2:$OJ$901,28,MATCH($B$2&"|xC",Aux_puntos!$1:$1,0))),NA()) | AF32: =IFERROR(IF(INDEX(Aux_puntos!$A$2:$OJ$901,28,MATCH($B$2&"|yC",Aux_puntos!$1:$1,0))="",NA(),INDEX(Aux_puntos!$A$2:$OJ$901,28,MATCH($B$2&"|yC",Aux_puntos!$1:$1,0))),NA()) | AG32: =IFERROR(IF(INDEX(Aux_puntos!$A$2:$OJ$901,28,MATCH($B$2&"|xI",Aux_puntos!$1:$1,0))="",NA(),INDEX(Aux_puntos!$A$2:$OJ$901,28,MATCH($B$2&"|xI",Aux_puntos!$1:$1,0))),NA()) | AH32: =IFERROR(IF(INDEX(Aux_puntos!$A$2:$OJ$901,28,MATCH($B$2&"|yI",Aux_puntos!$1:$1,0))="",NA(),INDEX(Aux_puntos!$A$2:$OJ$901,28,MATCH($B$2&"|yI",Aux_puntos!$1:$1,0))),NA()) | AI32: =IFERROR(IF(INDEX(Aux_puntos!$A$2:$OJ$901,28,MATCH($B$2&"|xN",Aux_puntos!$1:$1,0))="",NA(),INDEX(Aux_puntos!$A$2:$OJ$901,28,MATCH($B$2&"|xN",Aux_puntos!$1:$1,0))),NA()) | AJ32: =IFERROR(IF(INDEX(Aux_puntos!$A$2:$OJ$901,28,MATCH($B$2&"|yN",Aux_puntos!$1:$1,0))="",NA(),INDEX(Aux_puntos!$A$2:$OJ$901,28,MATCH($B$2&"|yN",Aux_puntos!$1:$1,0))),NA())
AC33: =IFERROR(IF(INDEX(Aux_puntos!$A$2:$OJ$901,29,MATCH($B$2&"|xK",Aux_puntos!$1:$1,0))="",NA(),INDEX(Aux_puntos!$A$2:$OJ$901,29,MATCH($B$2&"|xK",Aux_puntos!$1:$1,0))),NA()) | AD33: =IFERROR(IF(INDEX(Aux_puntos!$A$2:$OJ$901,29,MATCH($B$2&"|yK",Aux_puntos!$1:$1,0))="",NA(),INDEX(Aux_puntos!$A$2:$OJ$901,29,MATCH($B$2&"|yK",Aux_puntos!$1:$1,0))),NA()) | AE33: =IFERROR(IF(INDEX(Aux_puntos!$A$2:$OJ$901,29,MATCH($B$2&"|xC",Aux_puntos!$1:$1,0))="",NA(),INDEX(Aux_puntos!$A$2:$OJ$901,29,MATCH($B$2&"|xC",Aux_puntos!$1:$1,0))),NA()) | AF33: =IFERROR(IF(INDEX(Aux_puntos!$A$2:$OJ$901,29,MATCH($B$2&"|yC",Aux_puntos!$1:$1,0))="",NA(),INDEX(Aux_puntos!$A$2:$OJ$901,29,MATCH($B$2&"|yC",Aux_puntos!$1:$1,0))),NA()) | AG33: =IFERROR(IF(INDEX(Aux_puntos!$A$2:$OJ$901,29,MATCH($B$2&"|xI",Aux_puntos!$1:$1,0))="",NA(),INDEX(Aux_puntos!$A$2:$OJ$901,29,MATCH($B$2&"|xI",Aux_puntos!$1:$1,0))),NA()) | AH33: =IFERROR(IF(INDEX(Aux_puntos!$A$2:$OJ$901,29,MATCH($B$2&"|yI",Aux_puntos!$1:$1,0))="",NA(),INDEX(Aux_puntos!$A$2:$OJ$901,29,MATCH($B$2&"|yI",Aux_puntos!$1:$1,0))),NA()) | AI33: =IFERROR(IF(INDEX(Aux_puntos!$A$2:$OJ$901,29,MATCH($B$2&"|xN",Aux_puntos!$1:$1,0))="",NA(),INDEX(Aux_puntos!$A$2:$OJ$901,29,MATCH($B$2&"|xN",Aux_puntos!$1:$1,0))),NA()) | AJ33: =IFERROR(IF(INDEX(Aux_puntos!$A$2:$OJ$901,29,MATCH($B$2&"|yN",Aux_puntos!$1:$1,0))="",NA(),INDEX(Aux_puntos!$A$2:$OJ$901,29,MATCH($B$2&"|yN",Aux_puntos!$1:$1,0))),NA())
AC34: =IFERROR(IF(INDEX(Aux_puntos!$A$2:$OJ$901,30,MATCH($B$2&"|xK",Aux_puntos!$1:$1,0))="",NA(),INDEX(Aux_puntos!$A$2:$OJ$901,30,MATCH($B$2&"|xK",Aux_puntos!$1:$1,0))),NA()) | AD34: =IFERROR(IF(INDEX(Aux_puntos!$A$2:$OJ$901,30,MATCH($B$2&"|yK",Aux_puntos!$1:$1,0))="",NA(),INDEX(Aux_puntos!$A$2:$OJ$901,30,MATCH($B$2&"|yK",Aux_puntos!$1:$1,0))),NA()) | AE34: =IFERROR(IF(INDEX(Aux_puntos!$A$2:$OJ$901,30,MATCH($B$2&"|xC",Aux_puntos!$1:$1,0))="",NA(),INDEX(Aux_puntos!$A$2:$OJ$901,30,MATCH($B$2&"|xC",Aux_puntos!$1:$1,0))),NA()) | AF34: =IFERROR(IF(INDEX(Aux_puntos!$A$2:$OJ$901,30,MATCH($B$2&"|yC",Aux_puntos!$1:$1,0))="",NA(),INDEX(Aux_puntos!$A$2:$OJ$901,30,MATCH($B$2&"|yC",Aux_puntos!$1:$1,0))),NA()) | AG34: =IFERROR(IF(INDEX(Aux_puntos!$A$2:$OJ$901,30,MATCH($B$2&"|xI",Aux_puntos!$1:$1,0))="",NA(),INDEX(Aux_puntos!$A$2:$OJ$901,30,MATCH($B$2&"|xI",Aux_puntos!$1:$1,0))),NA()) | AH34: =IFERROR(IF(INDEX(Aux_puntos!$A$2:$OJ$901,30,MATCH($B$2&"|yI",Aux_puntos!$1:$1,0))="",NA(),INDEX(Aux_puntos!$A$2:$OJ$901,30,MATCH($B$2&"|yI",Aux_puntos!$1:$1,0))),NA()) | AI34: =IFERROR(IF(INDEX(Aux_puntos!$A$2:$OJ$901,30,MATCH($B$2&"|xN",Aux_puntos!$1:$1,0))="",NA(),INDEX(Aux_puntos!$A$2:$OJ$901,30,MATCH($B$2&"|xN",Aux_puntos!$1:$1,0))),NA()) | AJ34: =IFERROR(IF(INDEX(Aux_puntos!$A$2:$OJ$901,30,MATCH($B$2&"|yN",Aux_puntos!$1:$1,0))="",NA(),INDEX(Aux_puntos!$A$2:$OJ$901,30,MATCH($B$2&"|yN",Aux_puntos!$1:$1,0))),NA())
AC35: =IFERROR(IF(INDEX(Aux_puntos!$A$2:$OJ$901,31,MATCH($B$2&"|xK",Aux_puntos!$1:$1,0))="",NA(),INDEX(Aux_puntos!$A$2:$OJ$901,31,MATCH($B$2&"|xK",Aux_puntos!$1:$1,0))),NA()) | AD35: =IFERROR(IF(INDEX(Aux_puntos!$A$2:$OJ$901,31,MATCH($B$2&"|yK",Aux_puntos!$1:$1,0))="",NA(),INDEX(Aux_puntos!$A$2:$OJ$901,31,MATCH($B$2&"|yK",Aux_puntos!$1:$1,0))),NA()) | AE35: =IFERROR(IF(INDEX(Aux_puntos!$A$2:$OJ$901,31,MATCH($B$2&"|xC",Aux_puntos!$1:$1,0))="",NA(),INDEX(Aux_puntos!$A$2:$OJ$901,31,MATCH($B$2&"|xC",Aux_puntos!$1:$1,0))),NA()) | AF35: =IFERROR(IF(INDEX(Aux_puntos!$A$2:$OJ$901,31,MATCH($B$2&"|yC",Aux_puntos!$1:$1,0))="",NA(),INDEX(Aux_puntos!$A$2:$OJ$901,31,MATCH($B$2&"|yC",Aux_puntos!$1:$1,0))),NA()) | AG35: =IFERROR(IF(INDEX(Aux_puntos!$A$2:$OJ$901,31,MATCH($B$2&"|xI",Aux_puntos!$1:$1,0))="",NA(),INDEX(Aux_puntos!$A$2:$OJ$901,31,MATCH($B$2&"|xI",Aux_puntos!$1:$1,0))),NA()) | AH35: =IFERROR(IF(INDEX(Aux_puntos!$A$2:$OJ$901,31,MATCH($B$2&"|yI",Aux_puntos!$1:$1,0))="",NA(),INDEX(Aux_puntos!$A$2:$OJ$901,31,MATCH($B$2&"|yI",Aux_puntos!$1:$1,0))),NA()) | AI35: =IFERROR(IF(INDEX(Aux_puntos!$A$2:$OJ$901,31,MATCH($B$2&"|xN",Aux_puntos!$1:$1,0))="",NA(),INDEX(Aux_puntos!$A$2:$OJ$901,31,MATCH($B$2&"|xN",Aux_puntos!$1:$1,0))),NA()) | AJ35: =IFERROR(IF(INDEX(Aux_puntos!$A$2:$OJ$901,31,MATCH($B$2&"|yN",Aux_puntos!$1:$1,0))="",NA(),INDEX(Aux_puntos!$A$2:$OJ$901,31,MATCH($B$2&"|yN",Aux_puntos!$1:$1,0))),NA())
AC36: =IFERROR(IF(INDEX(Aux_puntos!$A$2:$OJ$901,32,MATCH($B$2&"|xK",Aux_puntos!$1:$1,0))="",NA(),INDEX(Aux_puntos!$A$2:$OJ$901,32,MATCH($B$2&"|xK",Aux_puntos!$1:$1,0))),NA()) | AD36: =IFERROR(IF(INDEX(Aux_puntos!$A$2:$OJ$901,32,MATCH($B$2&"|yK",Aux_puntos!$1:$1,0))="",NA(),INDEX(Aux_puntos!$A$2:$OJ$901,32,MATCH($B$2&"|yK",Aux_puntos!$1:$1,0))),NA()) | AE36: =IFERROR(IF(INDEX(Aux_puntos!$A$2:$OJ$901,32,MATCH($B$2&"|xC",Aux_puntos!$1:$1,0))="",NA(),INDEX(Aux_puntos!$A$2:$OJ$901,32,MATCH($B$2&"|xC",Aux_puntos!$1:$1,0))),NA()) | AF36: =IFERROR(IF(INDEX(Aux_puntos!$A$2:$OJ$901,32,MATCH($B$2&"|yC",Aux_puntos!$1:$1,0))="",NA(),INDEX(Aux_puntos!$A$2:$OJ$901,32,MATCH($B$2&"|yC",Aux_puntos!$1:$1,0))),NA()) | AG36: =IFERROR(IF(INDEX(Aux_puntos!$A$2:$OJ$901,32,MATCH($B$2&"|xI",Aux_puntos!$1:$1,0))="",NA(),INDEX(Aux_puntos!$A$2:$OJ$901,32,MATCH($B$2&"|xI",Aux_puntos!$1:$1,0))),NA()) | AH36: =IFERROR(IF(INDEX(Aux_puntos!$A$2:$OJ$901,32,MATCH($B$2&"|yI",Aux_puntos!$1:$1,0))="",NA(),INDEX(Aux_puntos!$A$2:$OJ$901,32,MATCH($B$2&"|yI",Aux_puntos!$1:$1,0))),NA()) | AI36: =IFERROR(IF(INDEX(Aux_puntos!$A$2:$OJ$901,32,MATCH($B$2&"|xN",Aux_puntos!$1:$1,0))="",NA(),INDEX(Aux_puntos!$A$2:$OJ$901,32,MATCH($B$2&"|xN",Aux_puntos!$1:$1,0))),NA()) | AJ36: =IFERROR(IF(INDEX(Aux_puntos!$A$2:$OJ$901,32,MATCH($B$2&"|yN",Aux_puntos!$1:$1,0))="",NA(),INDEX(Aux_puntos!$A$2:$OJ$901,32,MATCH($B$2&"|yN",Aux_puntos!$1:$1,0))),NA())
AC37: =IFERROR(IF(INDEX(Aux_puntos!$A$2:$OJ$901,33,MATCH($B$2&"|xK",Aux_puntos!$1:$1,0))="",NA(),INDEX(Aux_puntos!$A$2:$OJ$901,33,MATCH($B$2&"|xK",Aux_puntos!$1:$1,0))),NA()) | AD37: =IFERROR(IF(INDEX(Aux_puntos!$A$2:$OJ$901,33,MATCH($B$2&"|yK",Aux_puntos!$1:$1,0))="",NA(),INDEX(Aux_puntos!$A$2:$OJ$901,33,MATCH($B$2&"|yK",Aux_puntos!$1:$1,0))),NA()) | AE37: =IFERROR(IF(INDEX(Aux_puntos!$A$2:$OJ$901,33,MATCH($B$2&"|xC",Aux_puntos!$1:$1,0))="",NA(),INDEX(Aux_puntos!$A$2:$OJ$901,33,MATCH($B$2&"|xC",Aux_puntos!$1:$1,0))),NA()) | AF37: =IFERROR(IF(INDEX(Aux_puntos!$A$2:$OJ$901,33,MATCH($B$2&"|yC",Aux_puntos!$1:$1,0))="",NA(),INDEX(Aux_puntos!$A$2:$OJ$901,33,MATCH($B$2&"|yC",Aux_puntos!$1:$1,0))),NA()) | AG37: =IFERROR(IF(INDEX(Aux_puntos!$A$2:$OJ$901,33,MATCH($B$2&"|xI",Aux_puntos!$1:$1,0))="",NA(),INDEX(Aux_puntos!$A$2:$OJ$901,33,MATCH($B$2&"|xI",Aux_puntos!$1:$1,0))),NA()) | AH37: =IFERROR(IF(INDEX(Aux_puntos!$A$2:$OJ$901,33,MATCH($B$2&"|yI",Aux_puntos!$1:$1,0))="",NA(),INDEX(Aux_puntos!$A$2:$OJ$901,33,MATCH($B$2&"|yI",Aux_puntos!$1:$1,0))),NA()) | AI37: =IFERROR(IF(INDEX(Aux_puntos!$A$2:$OJ$901,33,MATCH($B$2&"|xN",Aux_puntos!$1:$1,0))="",NA(),INDEX(Aux_puntos!$A$2:$OJ$901,33,MATCH($B$2&"|xN",Aux_puntos!$1:$1,0))),NA()) | AJ37: =IFERROR(IF(INDEX(Aux_puntos!$A$2:$OJ$901,33,MATCH($B$2&"|yN",Aux_puntos!$1:$1,0))="",NA(),INDEX(Aux_puntos!$A$2:$OJ$901,33,MATCH($B$2&"|yN",Aux_puntos!$1:$1,0))),NA())
AC38: =IFERROR(IF(INDEX(Aux_puntos!$A$2:$OJ$901,34,MATCH($B$2&"|xK",Aux_puntos!$1:$1,0))="",NA(),INDEX(Aux_puntos!$A$2:$OJ$901,34,MATCH($B$2&"|xK",Aux_puntos!$1:$1,0))),NA()) | AD38: =IFERROR(IF(INDEX(Aux_puntos!$A$2:$OJ$901,34,MATCH($B$2&"|yK",Aux_puntos!$1:$1,0))="",NA(),INDEX(Aux_puntos!$A$2:$OJ$901,34,MATCH($B$2&"|yK",Aux_puntos!$1:$1,0))),NA()) | AE38: =IFERROR(IF(INDEX(Aux_puntos!$A$2:$OJ$901,34,MATCH($B$2&"|xC",Aux_puntos!$1:$1,0))="",NA(),INDEX(Aux_puntos!$A$2:$OJ$901,34,MATCH($B$2&"|xC",Aux_puntos!$1:$1,0))),NA()) | AF38: =IFERROR(IF(INDEX(Aux_puntos!$A$2:$OJ$901,34,MATCH($B$2&"|yC",Aux_puntos!$1:$1,0))="",NA(),INDEX(Aux_puntos!$A$2:$OJ$901,34,MATCH($B$2&"|yC",Aux_puntos!$1:$1,0))),NA()) | AG38: =IFERROR(IF(INDEX(Aux_puntos!$A$2:$OJ$901,34,MATCH($B$2&"|xI",Aux_puntos!$1:$1,0))="",NA(),INDEX(Aux_puntos!$A$2:$OJ$901,34,MATCH($B$2&"|xI",Aux_puntos!$1:$1,0))),NA()) | AH38: =IFERROR(IF(INDEX(Aux_puntos!$A$2:$OJ$901,34,MATCH($B$2&"|yI",Aux_puntos!$1:$1,0))="",NA(),INDEX(Aux_puntos!$A$2:$OJ$901,34,MATCH($B$2&"|yI",Aux_puntos!$1:$1,0))),NA()) | AI38: =IFERROR(IF(INDEX(Aux_puntos!$A$2:$OJ$901,34,MATCH($B$2&"|xN",Aux_puntos!$1:$1,0))="",NA(),INDEX(Aux_puntos!$A$2:$OJ$901,34,MATCH($B$2&"|xN",Aux_puntos!$1:$1,0))),NA()) | AJ38: =IFERROR(IF(INDEX(Aux_puntos!$A$2:$OJ$901,34,MATCH($B$2&"|yN",Aux_puntos!$1:$1,0))="",NA(),INDEX(Aux_puntos!$A$2:$OJ$901,34,MATCH($B$2&"|yN",Aux_puntos!$1:$1,0))),NA())
AC39: =IFERROR(IF(INDEX(Aux_puntos!$A$2:$OJ$901,35,MATCH($B$2&"|xK",Aux_puntos!$1:$1,0))="",NA(),INDEX(Aux_puntos!$A$2:$OJ$901,35,MATCH($B$2&"|xK",Aux_puntos!$1:$1,0))),NA()) | AD39: =IFERROR(IF(INDEX(Aux_puntos!$A$2:$OJ$901,35,MATCH($B$2&"|yK",Aux_puntos!$1:$1,0))="",NA(),INDEX(Aux_puntos!$A$2:$OJ$901,35,MATCH($B$2&"|yK",Aux_puntos!$1:$1,0))),NA()) | AE39: =IFERROR(IF(INDEX(Aux_puntos!$A$2:$OJ$901,35,MATCH($B$2&"|xC",Aux_puntos!$1:$1,0))="",NA(),INDEX(Aux_puntos!$A$2:$OJ$901,35,MATCH($B$2&"|xC",Aux_puntos!$1:$1,0))),NA()) | AF39: =IFERROR(IF(INDEX(Aux_puntos!$A$2:$OJ$901,35,MATCH($B$2&"|yC",Aux_puntos!$1:$1,0))="",NA(),INDEX(Aux_puntos!$A$2:$OJ$901,35,MATCH($B$2&"|yC",Aux_puntos!$1:$1,0))),NA()) | AG39: =IFERROR(IF(INDEX(Aux_puntos!$A$2:$OJ$901,35,MATCH($B$2&"|xI",Aux_puntos!$1:$1,0))="",NA(),INDEX(Aux_puntos!$A$2:$OJ$901,35,MATCH($B$2&"|xI",Aux_puntos!$1:$1,0))),NA()) | AH39: =IFERROR(IF(INDEX(Aux_puntos!$A$2:$OJ$901,35,MATCH($B$2&"|yI",Aux_puntos!$1:$1,0))="",NA(),INDEX(Aux_puntos!$A$2:$OJ$901,35,MATCH($B$2&"|yI",Aux_puntos!$1:$1,0))),NA()) | AI39: =IFERROR(IF(INDEX(Aux_puntos!$A$2:$OJ$901,35,MATCH($B$2&"|xN",Aux_puntos!$1:$1,0))="",NA(),INDEX(Aux_puntos!$A$2:$OJ$901,35,MATCH($B$2&"|xN",Aux_puntos!$1:$1,0))),NA()) | AJ39: =IFERROR(IF(INDEX(Aux_puntos!$A$2:$OJ$901,35,MATCH($B$2&"|yN",Aux_puntos!$1:$1,0))="",NA(),INDEX(Aux_puntos!$A$2:$OJ$901,35,MATCH($B$2&"|yN",Aux_puntos!$1:$1,0))),NA())
AC40: =IFERROR(IF(INDEX(Aux_puntos!$A$2:$OJ$901,36,MATCH($B$2&"|xK",Aux_puntos!$1:$1,0))="",NA(),INDEX(Aux_puntos!$A$2:$OJ$901,36,MATCH($B$2&"|xK",Aux_puntos!$1:$1,0))),NA()) | AD40: =IFERROR(IF(INDEX(Aux_puntos!$A$2:$OJ$901,36,MATCH($B$2&"|yK",Aux_puntos!$1:$1,0))="",NA(),INDEX(Aux_puntos!$A$2:$OJ$901,36,MATCH($B$2&"|yK",Aux_puntos!$1:$1,0))),NA()) | AE40: =IFERROR(IF(INDEX(Aux_puntos!$A$2:$OJ$901,36,MATCH($B$2&"|xC",Aux_puntos!$1:$1,0))="",NA(),INDEX(Aux_puntos!$A$2:$OJ$901,36,MATCH($B$2&"|xC",Aux_puntos!$1:$1,0))),NA()) | AF40: =IFERROR(IF(INDEX(Aux_puntos!$A$2:$OJ$901,36,MATCH($B$2&"|yC",Aux_puntos!$1:$1,0))="",NA(),INDEX(Aux_puntos!$A$2:$OJ$901,36,MATCH($B$2&"|yC",Aux_puntos!$1:$1,0))),NA()) | AG40: =IFERROR(IF(INDEX(Aux_puntos!$A$2:$OJ$901,36,MATCH($B$2&"|xI",Aux_puntos!$1:$1,0))="",NA(),INDEX(Aux_puntos!$A$2:$OJ$901,36,MATCH($B$2&"|xI",Aux_puntos!$1:$1,0))),NA()) | AH40: =IFERROR(IF(INDEX(Aux_puntos!$A$2:$OJ$901,36,MATCH($B$2&"|yI",Aux_puntos!$1:$1,0))="",NA(),INDEX(Aux_puntos!$A$2:$OJ$901,36,MATCH($B$2&"|yI",Aux_puntos!$1:$1,0))),NA()) | AI40: =IFERROR(IF(INDEX(Aux_puntos!$A$2:$OJ$901,36,MATCH($B$2&"|xN",Aux_puntos!$1:$1,0))="",NA(),INDEX(Aux_puntos!$A$2:$OJ$901,36,MATCH($B$2&"|xN",Aux_puntos!$1:$1,0))),NA()) | AJ40: =IFERROR(IF(INDEX(Aux_puntos!$A$2:$OJ$901,36,MATCH($B$2&"|yN",Aux_puntos!$1:$1,0))="",NA(),INDEX(Aux_puntos!$A$2:$OJ$901,36,MATCH($B$2&"|yN",Aux_puntos!$1:$1,0))),NA())
AC41: =IFERROR(IF(INDEX(Aux_puntos!$A$2:$OJ$901,37,MATCH($B$2&"|xK",Aux_puntos!$1:$1,0))="",NA(),INDEX(Aux_puntos!$A$2:$OJ$901,37,MATCH($B$2&"|xK",Aux_puntos!$1:$1,0))),NA()) | AD41: =IFERROR(IF(INDEX(Aux_puntos!$A$2:$OJ$901,37,MATCH($B$2&"|yK",Aux_puntos!$1:$1,0))="",NA(),INDEX(Aux_puntos!$A$2:$OJ$901,37,MATCH($B$2&"|yK",Aux_puntos!$1:$1,0))),NA()) | AE41: =IFERROR(IF(INDEX(Aux_puntos!$A$2:$OJ$901,37,MATCH($B$2&"|xC",Aux_puntos!$1:$1,0))="",NA(),INDEX(Aux_puntos!$A$2:$OJ$901,37,MATCH($B$2&"|xC",Aux_puntos!$1:$1,0))),NA()) | AF41: =IFERROR(IF(INDEX(Aux_puntos!$A$2:$OJ$901,37,MATCH($B$2&"|yC",Aux_puntos!$1:$1,0))="",NA(),INDEX(Aux_puntos!$A$2:$OJ$901,37,MATCH($B$2&"|yC",Aux_puntos!$1:$1,0))),NA()) | AG41: =IFERROR(IF(INDEX(Aux_puntos!$A$2:$OJ$901,37,MATCH($B$2&"|xI",Aux_puntos!$1:$1,0))="",NA(),INDEX(Aux_puntos!$A$2:$OJ$901,37,MATCH($B$2&"|xI",Aux_puntos!$1:$1,0))),NA()) | AH41: =IFERROR(IF(INDEX(Aux_puntos!$A$2:$OJ$901,37,MATCH($B$2&"|yI",Aux_puntos!$1:$1,0))="",NA(),INDEX(Aux_puntos!$A$2:$OJ$901,37,MATCH($B$2&"|yI",Aux_puntos!$1:$1,0))),NA()) | AI41: =IFERROR(IF(INDEX(Aux_puntos!$A$2:$OJ$901,37,MATCH($B$2&"|xN",Aux_puntos!$1:$1,0))="",NA(),INDEX(Aux_puntos!$A$2:$OJ$901,37,MATCH($B$2&"|xN",Aux_puntos!$1:$1,0))),NA()) | AJ41: =IFERROR(IF(INDEX(Aux_puntos!$A$2:$OJ$901,37,MATCH($B$2&"|yN",Aux_puntos!$1:$1,0))="",NA(),INDEX(Aux_puntos!$A$2:$OJ$901,37,MATCH($B$2&"|yN",Aux_puntos!$1:$1,0))),NA())
AC42: =IFERROR(IF(INDEX(Aux_puntos!$A$2:$OJ$901,38,MATCH($B$2&"|xK",Aux_puntos!$1:$1,0))="",NA(),INDEX(Aux_puntos!$A$2:$OJ$901,38,MATCH($B$2&"|xK",Aux_puntos!$1:$1,0))),NA()) | AD42: =IFERROR(IF(INDEX(Aux_puntos!$A$2:$OJ$901,38,MATCH($B$2&"|yK",Aux_puntos!$1:$1,0))="",NA(),INDEX(Aux_puntos!$A$2:$OJ$901,38,MATCH($B$2&"|yK",Aux_puntos!$1:$1,0))),NA()) | AE42: =IFERROR(IF(INDEX(Aux_puntos!$A$2:$OJ$901,38,MATCH($B$2&"|xC",Aux_puntos!$1:$1,0))="",NA(),INDEX(Aux_puntos!$A$2:$OJ$901,38,MATCH($B$2&"|xC",Aux_puntos!$1:$1,0))),NA()) | AF42: =IFERROR(IF(INDEX(Aux_puntos!$A$2:$OJ$901,38,MATCH($B$2&"|yC",Aux_puntos!$1:$1,0))="",NA(),INDEX(Aux_puntos!$A$2:$OJ$901,38,MATCH($B$2&"|yC",Aux_puntos!$1:$1,0))),NA()) | AG42: =IFERROR(IF(INDEX(Aux_puntos!$A$2:$OJ$901,38,MATCH($B$2&"|xI",Aux_puntos!$1:$1,0))="",NA(),INDEX(Aux_puntos!$A$2:$OJ$901,38,MATCH($B$2&"|xI",Aux_puntos!$1:$1,0))),NA()) | AH42: =IFERROR(IF(INDEX(Aux_puntos!$A$2:$OJ$901,38,MATCH($B$2&"|yI",Aux_puntos!$1:$1,0))="",NA(),INDEX(Aux_puntos!$A$2:$OJ$901,38,MATCH($B$2&"|yI",Aux_puntos!$1:$1,0))),NA()) | AI42: =IFERROR(IF(INDEX(Aux_puntos!$A$2:$OJ$901,38,MATCH($B$2&"|xN",Aux_puntos!$1:$1,0))="",NA(),INDEX(Aux_puntos!$A$2:$OJ$901,38,MATCH($B$2&"|xN",Aux_puntos!$1:$1,0))),NA()) | AJ42: =IFERROR(IF(INDEX(Aux_puntos!$A$2:$OJ$901,38,MATCH($B$2&"|yN",Aux_puntos!$1:$1,0))="",NA(),INDEX(Aux_puntos!$A$2:$OJ$901,38,MATCH($B$2&"|yN",Aux_puntos!$1:$1,0))),NA())
AC43: =IFERROR(IF(INDEX(Aux_puntos!$A$2:$OJ$901,39,MATCH($B$2&"|xK",Aux_puntos!$1:$1,0))="",NA(),INDEX(Aux_puntos!$A$2:$OJ$901,39,MATCH($B$2&"|xK",Aux_puntos!$1:$1,0))),NA()) | AD43: =IFERROR(IF(INDEX(Aux_puntos!$A$2:$OJ$901,39,MATCH($B$2&"|yK",Aux_puntos!$1:$1,0))="",NA(),INDEX(Aux_puntos!$A$2:$OJ$901,39,MATCH($B$2&"|yK",Aux_puntos!$1:$1,0))),NA()) | AE43: =IFERROR(IF(INDEX(Aux_puntos!$A$2:$OJ$901,39,MATCH($B$2&"|xC",Aux_puntos!$1:$1,0))="",NA(),INDEX(Aux_puntos!$A$2:$OJ$901,39,MATCH($B$2&"|xC",Aux_puntos!$1:$1,0))),NA()) | AF43: =IFERROR(IF(INDEX(Aux_puntos!$A$2:$OJ$901,39,MATCH($B$2&"|yC",Aux_puntos!$1:$1,0))="",NA(),INDEX(Aux_puntos!$A$2:$OJ$901,39,MATCH($B$2&"|yC",Aux_puntos!$1:$1,0))),NA()) | AG43: =IFERROR(IF(INDEX(Aux_puntos!$A$2:$OJ$901,39,MATCH($B$2&"|xI",Aux_puntos!$1:$1,0))="",NA(),INDEX(Aux_puntos!$A$2:$OJ$901,39,MATCH($B$2&"|xI",Aux_puntos!$1:$1,0))),NA()) | AH43: =IFERROR(IF(INDEX(Aux_puntos!$A$2:$OJ$901,39,MATCH($B$2&"|yI",Aux_puntos!$1:$1,0))="",NA(),INDEX(Aux_puntos!$A$2:$OJ$901,39,MATCH($B$2&"|yI",Aux_puntos!$1:$1,0))),NA()) | AI43: =IFERROR(IF(INDEX(Aux_puntos!$A$2:$OJ$901,39,MATCH($B$2&"|xN",Aux_puntos!$1:$1,0))="",NA(),INDEX(Aux_puntos!$A$2:$OJ$901,39,MATCH($B$2&"|xN",Aux_puntos!$1:$1,0))),NA()) | AJ43: =IFERROR(IF(INDEX(Aux_puntos!$A$2:$OJ$901,39,MATCH($B$2&"|yN",Aux_puntos!$1:$1,0))="",NA(),INDEX(Aux_puntos!$A$2:$OJ$901,39,MATCH($B$2&"|yN",Aux_puntos!$1:$1,0))),NA())
AC44: =IFERROR(IF(INDEX(Aux_puntos!$A$2:$OJ$901,40,MATCH($B$2&"|xK",Aux_puntos!$1:$1,0))="",NA(),INDEX(Aux_puntos!$A$2:$OJ$901,40,MATCH($B$2&"|xK",Aux_puntos!$1:$1,0))),NA()) | AD44: =IFERROR(IF(INDEX(Aux_puntos!$A$2:$OJ$901,40,MATCH($B$2&"|yK",Aux_puntos!$1:$1,0))="",NA(),INDEX(Aux_puntos!$A$2:$OJ$901,40,MATCH($B$2&"|yK",Aux_puntos!$1:$1,0))),NA()) | AE44: =IFERROR(IF(INDEX(Aux_puntos!$A$2:$OJ$901,40,MATCH($B$2&"|xC",Aux_puntos!$1:$1,0))="",NA(),INDEX(Aux_puntos!$A$2:$OJ$901,40,MATCH($B$2&"|xC",Aux_puntos!$1:$1,0))),NA()) | AF44: =IFERROR(IF(INDEX(Aux_puntos!$A$2:$OJ$901,40,MATCH($B$2&"|yC",Aux_puntos!$1:$1,0))="",NA(),INDEX(Aux_puntos!$A$2:$OJ$901,40,MATCH($B$2&"|yC",Aux_puntos!$1:$1,0))),NA()) | AG44: =IFERROR(IF(INDEX(Aux_puntos!$A$2:$OJ$901,40,MATCH($B$2&"|xI",Aux_puntos!$1:$1,0))="",NA(),INDEX(Aux_puntos!$A$2:$OJ$901,40,MATCH($B$2&"|xI",Aux_puntos!$1:$1,0))),NA()) | AH44: =IFERROR(IF(INDEX(Aux_puntos!$A$2:$OJ$901,40,MATCH($B$2&"|yI",Aux_puntos!$1:$1,0))="",NA(),INDEX(Aux_puntos!$A$2:$OJ$901,40,MATCH($B$2&"|yI",Aux_puntos!$1:$1,0))),NA()) | AI44: =IFERROR(IF(INDEX(Aux_puntos!$A$2:$OJ$901,40,MATCH($B$2&"|xN",Aux_puntos!$1:$1,0))="",NA(),INDEX(Aux_puntos!$A$2:$OJ$901,40,MATCH($B$2&"|xN",Aux_puntos!$1:$1,0))),NA()) | AJ44: =IFERROR(IF(INDEX(Aux_puntos!$A$2:$OJ$901,40,MATCH($B$2&"|yN",Aux_puntos!$1:$1,0))="",NA(),INDEX(Aux_puntos!$A$2:$OJ$901,40,MATCH($B$2&"|yN",Aux_puntos!$1:$1,0))),NA())
AC45: =IFERROR(IF(INDEX(Aux_puntos!$A$2:$OJ$901,41,MATCH($B$2&"|xK",Aux_puntos!$1:$1,0))="",NA(),INDEX(Aux_puntos!$A$2:$OJ$901,41,MATCH($B$2&"|xK",Aux_puntos!$1:$1,0))),NA()) | AD45: =IFERROR(IF(INDEX(Aux_puntos!$A$2:$OJ$901,41,MATCH($B$2&"|yK",Aux_puntos!$1:$1,0))="",NA(),INDEX(Aux_puntos!$A$2:$OJ$901,41,MATCH($B$2&"|yK",Aux_puntos!$1:$1,0))),NA()) | AE45: =IFERROR(IF(INDEX(Aux_puntos!$A$2:$OJ$901,41,MATCH($B$2&"|xC",Aux_puntos!$1:$1,0))="",NA(),INDEX(Aux_puntos!$A$2:$OJ$901,41,MATCH($B$2&"|xC",Aux_puntos!$1:$1,0))),NA()) | AF45: =IFERROR(IF(INDEX(Aux_puntos!$A$2:$OJ$901,41,MATCH($B$2&"|yC",Aux_puntos!$1:$1,0))="",NA(),INDEX(Aux_puntos!$A$2:$OJ$901,41,MATCH($B$2&"|yC",Aux_puntos!$1:$1,0))),NA()) | AG45: =IFERROR(IF(INDEX(Aux_puntos!$A$2:$OJ$901,41,MATCH($B$2&"|xI",Aux_puntos!$1:$1,0))="",NA(),INDEX(Aux_puntos!$A$2:$OJ$901,41,MATCH($B$2&"|xI",Aux_puntos!$1:$1,0))),NA()) | AH45: =IFERROR(IF(INDEX(Aux_puntos!$A$2:$OJ$901,41,MATCH($B$2&"|yI",Aux_puntos!$1:$1,0))="",NA(),INDEX(Aux_puntos!$A$2:$OJ$901,41,MATCH($B$2&"|yI",Aux_puntos!$1:$1,0))),NA()) | AI45: =IFERROR(IF(INDEX(Aux_puntos!$A$2:$OJ$901,41,MATCH($B$2&"|xN",Aux_puntos!$1:$1,0))="",NA(),INDEX(Aux_puntos!$A$2:$OJ$901,41,MATCH($B$2&"|xN",Aux_puntos!$1:$1,0))),NA()) | AJ45: =IFERROR(IF(INDEX(Aux_puntos!$A$2:$OJ$901,41,MATCH($B$2&"|yN",Aux_puntos!$1:$1,0))="",NA(),INDEX(Aux_puntos!$A$2:$OJ$901,41,MATCH($B$2&"|yN",Aux_puntos!$1:$1,0))),NA())
AC46: =IFERROR(IF(INDEX(Aux_puntos!$A$2:$OJ$901,42,MATCH($B$2&"|xK",Aux_puntos!$1:$1,0))="",NA(),INDEX(Aux_puntos!$A$2:$OJ$901,42,MATCH($B$2&"|xK",Aux_puntos!$1:$1,0))),NA()) | AD46: =IFERROR(IF(INDEX(Aux_puntos!$A$2:$OJ$901,42,MATCH($B$2&"|yK",Aux_puntos!$1:$1,0))="",NA(),INDEX(Aux_puntos!$A$2:$OJ$901,42,MATCH($B$2&"|yK",Aux_puntos!$1:$1,0))),NA()) | AE46: =IFERROR(IF(INDEX(Aux_puntos!$A$2:$OJ$901,42,MATCH($B$2&"|xC",Aux_puntos!$1:$1,0))="",NA(),INDEX(Aux_puntos!$A$2:$OJ$901,42,MATCH($B$2&"|xC",Aux_puntos!$1:$1,0))),NA()) | AF46: =IFERROR(IF(INDEX(Aux_puntos!$A$2:$OJ$901,42,MATCH($B$2&"|yC",Aux_puntos!$1:$1,0))="",NA(),INDEX(Aux_puntos!$A$2:$OJ$901,42,MATCH($B$2&"|yC",Aux_puntos!$1:$1,0))),NA()) | AG46: =IFERROR(IF(INDEX(Aux_puntos!$A$2:$OJ$901,42,MATCH($B$2&"|xI",Aux_puntos!$1:$1,0))="",NA(),INDEX(Aux_puntos!$A$2:$OJ$901,42,MATCH($B$2&"|xI",Aux_puntos!$1:$1,0))),NA()) | AH46: =IFERROR(IF(INDEX(Aux_puntos!$A$2:$OJ$901,42,MATCH($B$2&"|yI",Aux_puntos!$1:$1,0))="",NA(),INDEX(Aux_puntos!$A$2:$OJ$901,42,MATCH($B$2&"|yI",Aux_puntos!$1:$1,0))),NA()) | AI46: =IFERROR(IF(INDEX(Aux_puntos!$A$2:$OJ$901,42,MATCH($B$2&"|xN",Aux_puntos!$1:$1,0))="",NA(),INDEX(Aux_puntos!$A$2:$OJ$901,42,MATCH($B$2&"|xN",Aux_puntos!$1:$1,0))),NA()) | AJ46: =IFERROR(IF(INDEX(Aux_puntos!$A$2:$OJ$901,42,MATCH($B$2&"|yN",Aux_puntos!$1:$1,0))="",NA(),INDEX(Aux_puntos!$A$2:$OJ$901,42,MATCH($B$2&"|yN",Aux_puntos!$1:$1,0))),NA())
AC47: =IFERROR(IF(INDEX(Aux_puntos!$A$2:$OJ$901,43,MATCH($B$2&"|xK",Aux_puntos!$1:$1,0))="",NA(),INDEX(Aux_puntos!$A$2:$OJ$901,43,MATCH($B$2&"|xK",Aux_puntos!$1:$1,0))),NA()) | AD47: =IFERROR(IF(INDEX(Aux_puntos!$A$2:$OJ$901,43,MATCH($B$2&"|yK",Aux_puntos!$1:$1,0))="",NA(),INDEX(Aux_puntos!$A$2:$OJ$901,43,MATCH($B$2&"|yK",Aux_puntos!$1:$1,0))),NA()) | AE47: =IFERROR(IF(INDEX(Aux_puntos!$A$2:$OJ$901,43,MATCH($B$2&"|xC",Aux_puntos!$1:$1,0))="",NA(),INDEX(Aux_puntos!$A$2:$OJ$901,43,MATCH($B$2&"|xC",Aux_puntos!$1:$1,0))),NA()) | AF47: =IFERROR(IF(INDEX(Aux_puntos!$A$2:$OJ$901,43,MATCH($B$2&"|yC",Aux_puntos!$1:$1,0))="",NA(),INDEX(Aux_puntos!$A$2:$OJ$901,43,MATCH($B$2&"|yC",Aux_puntos!$1:$1,0))),NA()) | AG47: =IFERROR(IF(INDEX(Aux_puntos!$A$2:$OJ$901,43,MATCH($B$2&"|xI",Aux_puntos!$1:$1,0))="",NA(),INDEX(Aux_puntos!$A$2:$OJ$901,43,MATCH($B$2&"|xI",Aux_puntos!$1:$1,0))),NA()) | AH47: =IFERROR(IF(INDEX(Aux_puntos!$A$2:$OJ$901,43,MATCH($B$2&"|yI",Aux_puntos!$1:$1,0))="",NA(),INDEX(Aux_puntos!$A$2:$OJ$901,43,MATCH($B$2&"|yI",Aux_puntos!$1:$1,0))),NA()) | AI47: =IFERROR(IF(INDEX(Aux_puntos!$A$2:$OJ$901,43,MATCH($B$2&"|xN",Aux_puntos!$1:$1,0))="",NA(),INDEX(Aux_puntos!$A$2:$OJ$901,43,MATCH($B$2&"|xN",Aux_puntos!$1:$1,0))),NA()) | AJ47: =IFERROR(IF(INDEX(Aux_puntos!$A$2:$OJ$901,43,MATCH($B$2&"|yN",Aux_puntos!$1:$1,0))="",NA(),INDEX(Aux_puntos!$A$2:$OJ$901,43,MATCH($B$2&"|yN",Aux_puntos!$1:$1,0))),NA())
AC48: =IFERROR(IF(INDEX(Aux_puntos!$A$2:$OJ$901,44,MATCH($B$2&"|xK",Aux_puntos!$1:$1,0))="",NA(),INDEX(Aux_puntos!$A$2:$OJ$901,44,MATCH($B$2&"|xK",Aux_puntos!$1:$1,0))),NA()) | AD48: =IFERROR(IF(INDEX(Aux_puntos!$A$2:$OJ$901,44,MATCH($B$2&"|yK",Aux_puntos!$1:$1,0))="",NA(),INDEX(Aux_puntos!$A$2:$OJ$901,44,MATCH($B$2&"|yK",Aux_puntos!$1:$1,0))),NA()) | AE48: =IFERROR(IF(INDEX(Aux_puntos!$A$2:$OJ$901,44,MATCH($B$2&"|xC",Aux_puntos!$1:$1,0))="",NA(),INDEX(Aux_puntos!$A$2:$OJ$901,44,MATCH($B$2&"|xC",Aux_puntos!$1:$1,0))),NA()) | AF48: =IFERROR(IF(INDEX(Aux_puntos!$A$2:$OJ$901,44,MATCH($B$2&"|yC",Aux_puntos!$1:$1,0))="",NA(),INDEX(Aux_puntos!$A$2:$OJ$901,44,MATCH($B$2&"|yC",Aux_puntos!$1:$1,0))),NA()) | AG48: =IFERROR(IF(INDEX(Aux_puntos!$A$2:$OJ$901,44,MATCH($B$2&"|xI",Aux_puntos!$1:$1,0))="",NA(),INDEX(Aux_puntos!$A$2:$OJ$901,44,MATCH($B$2&"|xI",Aux_puntos!$1:$1,0))),NA()) | AH48: =IFERROR(IF(INDEX(Aux_puntos!$A$2:$OJ$901,44,MATCH($B$2&"|yI",Aux_puntos!$1:$1,0))="",NA(),INDEX(Aux_puntos!$A$2:$OJ$901,44,MATCH($B$2&"|yI",Aux_puntos!$1:$1,0))),NA()) | AI48: =IFERROR(IF(INDEX(Aux_puntos!$A$2:$OJ$901,44,MATCH($B$2&"|xN",Aux_puntos!$1:$1,0))="",NA(),INDEX(Aux_puntos!$A$2:$OJ$901,44,MATCH($B$2&"|xN",Aux_puntos!$1:$1,0))),NA()) | AJ48: =IFERROR(IF(INDEX(Aux_puntos!$A$2:$OJ$901,44,MATCH($B$2&"|yN",Aux_puntos!$1:$1,0))="",NA(),INDEX(Aux_puntos!$A$2:$OJ$901,44,MATCH($B$2&"|yN",Aux_puntos!$1:$1,0))),NA())
AC49: =IFERROR(IF(INDEX(Aux_puntos!$A$2:$OJ$901,45,MATCH($B$2&"|xK",Aux_puntos!$1:$1,0))="",NA(),INDEX(Aux_puntos!$A$2:$OJ$901,45,MATCH($B$2&"|xK",Aux_puntos!$1:$1,0))),NA()) | AD49: =IFERROR(IF(INDEX(Aux_puntos!$A$2:$OJ$901,45,MATCH($B$2&"|yK",Aux_puntos!$1:$1,0))="",NA(),INDEX(Aux_puntos!$A$2:$OJ$901,45,MATCH($B$2&"|yK",Aux_puntos!$1:$1,0))),NA()) | AE49: =IFERROR(IF(INDEX(Aux_puntos!$A$2:$OJ$901,45,MATCH($B$2&"|xC",Aux_puntos!$1:$1,0))="",NA(),INDEX(Aux_puntos!$A$2:$OJ$901,45,MATCH($B$2&"|xC",Aux_puntos!$1:$1,0))),NA()) | AF49: =IFERROR(IF(INDEX(Aux_puntos!$A$2:$OJ$901,45,MATCH($B$2&"|yC",Aux_puntos!$1:$1,0))="",NA(),INDEX(Aux_puntos!$A$2:$OJ$901,45,MATCH($B$2&"|yC",Aux_puntos!$1:$1,0))),NA()) | AG49: =IFERROR(IF(INDEX(Aux_puntos!$A$2:$OJ$901,45,MATCH($B$2&"|xI",Aux_puntos!$1:$1,0))="",NA(),INDEX(Aux_puntos!$A$2:$OJ$901,45,MATCH($B$2&"|xI",Aux_puntos!$1:$1,0))),NA()) | AH49: =IFERROR(IF(INDEX(Aux_puntos!$A$2:$OJ$901,45,MATCH($B$2&"|yI",Aux_puntos!$1:$1,0))="",NA(),INDEX(Aux_puntos!$A$2:$OJ$901,45,MATCH($B$2&"|yI",Aux_puntos!$1:$1,0))),NA()) | AI49: =IFERROR(IF(INDEX(Aux_puntos!$A$2:$OJ$901,45,MATCH($B$2&"|xN",Aux_puntos!$1:$1,0))="",NA(),INDEX(Aux_puntos!$A$2:$OJ$901,45,MATCH($B$2&"|xN",Aux_puntos!$1:$1,0))),NA()) | AJ49: =IFERROR(IF(INDEX(Aux_puntos!$A$2:$OJ$901,45,MATCH($B$2&"|yN",Aux_puntos!$1:$1,0))="",NA(),INDEX(Aux_puntos!$A$2:$OJ$901,45,MATCH($B$2&"|yN",Aux_puntos!$1:$1,0))),NA())
AC50: =IFERROR(IF(INDEX(Aux_puntos!$A$2:$OJ$901,46,MATCH($B$2&"|xK",Aux_puntos!$1:$1,0))="",NA(),INDEX(Aux_puntos!$A$2:$OJ$901,46,MATCH($B$2&"|xK",Aux_puntos!$1:$1,0))),NA()) | AD50: =IFERROR(IF(INDEX(Aux_puntos!$A$2:$OJ$901,46,MATCH($B$2&"|yK",Aux_puntos!$1:$1,0))="",NA(),INDEX(Aux_puntos!$A$2:$OJ$901,46,MATCH($B$2&"|yK",Aux_puntos!$1:$1,0))),NA()) | AE50: =IFERROR(IF(INDEX(Aux_puntos!$A$2:$OJ$901,46,MATCH($B$2&"|xC",Aux_puntos!$1:$1,0))="",NA(),INDEX(Aux_puntos!$A$2:$OJ$901,46,MATCH($B$2&"|xC",Aux_puntos!$1:$1,0))),NA()) | AF50: =IFERROR(IF(INDEX(Aux_puntos!$A$2:$OJ$901,46,MATCH($B$2&"|yC",Aux_puntos!$1:$1,0))="",NA(),INDEX(Aux_puntos!$A$2:$OJ$901,46,MATCH($B$2&"|yC",Aux_puntos!$1:$1,0))),NA()) | AG50: =IFERROR(IF(INDEX(Aux_puntos!$A$2:$OJ$901,46,MATCH($B$2&"|xI",Aux_puntos!$1:$1,0))="",NA(),INDEX(Aux_puntos!$A$2:$OJ$901,46,MATCH($B$2&"|xI",Aux_puntos!$1:$1,0))),NA()) | AH50: =IFERROR(IF(INDEX(Aux_puntos!$A$2:$OJ$901,46,MATCH($B$2&"|yI",Aux_puntos!$1:$1,0))="",NA(),INDEX(Aux_puntos!$A$2:$OJ$901,46,MATCH($B$2&"|yI",Aux_puntos!$1:$1,0))),NA()) | AI50: =IFERROR(IF(INDEX(Aux_puntos!$A$2:$OJ$901,46,MATCH($B$2&"|xN",Aux_puntos!$1:$1,0))="",NA(),INDEX(Aux_puntos!$A$2:$OJ$901,46,MATCH($B$2&"|xN",Aux_puntos!$1:$1,0))),NA()) | AJ50: =IFERROR(IF(INDEX(Aux_puntos!$A$2:$OJ$901,46,MATCH($B$2&"|yN",Aux_puntos!$1:$1,0))="",NA(),INDEX(Aux_puntos!$A$2:$OJ$901,46,MATCH($B$2&"|yN",Aux_puntos!$1:$1,0))),NA())
AC51: =IFERROR(IF(INDEX(Aux_puntos!$A$2:$OJ$901,47,MATCH($B$2&"|xK",Aux_puntos!$1:$1,0))="",NA(),INDEX(Aux_puntos!$A$2:$OJ$901,47,MATCH($B$2&"|xK",Aux_puntos!$1:$1,0))),NA()) | AD51: =IFERROR(IF(INDEX(Aux_puntos!$A$2:$OJ$901,47,MATCH($B$2&"|yK",Aux_puntos!$1:$1,0))="",NA(),INDEX(Aux_puntos!$A$2:$OJ$901,47,MATCH($B$2&"|yK",Aux_puntos!$1:$1,0))),NA()) | AE51: =IFERROR(IF(INDEX(Aux_puntos!$A$2:$OJ$901,47,MATCH($B$2&"|xC",Aux_puntos!$1:$1,0))="",NA(),INDEX(Aux_puntos!$A$2:$OJ$901,47,MATCH($B$2&"|xC",Aux_puntos!$1:$1,0))),NA()) | AF51: =IFERROR(IF(INDEX(Aux_puntos!$A$2:$OJ$901,47,MATCH($B$2&"|yC",Aux_puntos!$1:$1,0))="",NA(),INDEX(Aux_puntos!$A$2:$OJ$901,47,MATCH($B$2&"|yC",Aux_puntos!$1:$1,0))),NA()) | AG51: =IFERROR(IF(INDEX(Aux_puntos!$A$2:$OJ$901,47,MATCH($B$2&"|xI",Aux_puntos!$1:$1,0))="",NA(),INDEX(Aux_puntos!$A$2:$OJ$901,47,MATCH($B$2&"|xI",Aux_puntos!$1:$1,0))),NA()) | AH51: =IFERROR(IF(INDEX(Aux_puntos!$A$2:$OJ$901,47,MATCH($B$2&"|yI",Aux_puntos!$1:$1,0))="",NA(),INDEX(Aux_puntos!$A$2:$OJ$901,47,MATCH($B$2&"|yI",Aux_puntos!$1:$1,0))),NA()) | AI51: =IFERROR(IF(INDEX(Aux_puntos!$A$2:$OJ$901,47,MATCH($B$2&"|xN",Aux_puntos!$1:$1,0))="",NA(),INDEX(Aux_puntos!$A$2:$OJ$901,47,MATCH($B$2&"|xN",Aux_puntos!$1:$1,0))),NA()) | AJ51: =IFERROR(IF(INDEX(Aux_puntos!$A$2:$OJ$901,47,MATCH($B$2&"|yN",Aux_puntos!$1:$1,0))="",NA(),INDEX(Aux_puntos!$A$2:$OJ$901,47,MATCH($B$2&"|yN",Aux_puntos!$1:$1,0))),NA())
AC52: =IFERROR(IF(INDEX(Aux_puntos!$A$2:$OJ$901,48,MATCH($B$2&"|xK",Aux_puntos!$1:$1,0))="",NA(),INDEX(Aux_puntos!$A$2:$OJ$901,48,MATCH($B$2&"|xK",Aux_puntos!$1:$1,0))),NA()) | AD52: =IFERROR(IF(INDEX(Aux_puntos!$A$2:$OJ$901,48,MATCH($B$2&"|yK",Aux_puntos!$1:$1,0))="",NA(),INDEX(Aux_puntos!$A$2:$OJ$901,48,MATCH($B$2&"|yK",Aux_puntos!$1:$1,0))),NA()) | AE52: =IFERROR(IF(INDEX(Aux_puntos!$A$2:$OJ$901,48,MATCH($B$2&"|xC",Aux_puntos!$1:$1,0))="",NA(),INDEX(Aux_puntos!$A$2:$OJ$901,48,MATCH($B$2&"|xC",Aux_puntos!$1:$1,0))),NA()) | AF52: =IFERROR(IF(INDEX(Aux_puntos!$A$2:$OJ$901,48,MATCH($B$2&"|yC",Aux_puntos!$1:$1,0))="",NA(),INDEX(Aux_puntos!$A$2:$OJ$901,48,MATCH($B$2&"|yC",Aux_puntos!$1:$1,0))),NA()) | AG52: =IFERROR(IF(INDEX(Aux_puntos!$A$2:$OJ$901,48,MATCH($B$2&"|xI",Aux_puntos!$1:$1,0))="",NA(),INDEX(Aux_puntos!$A$2:$OJ$901,48,MATCH($B$2&"|xI",Aux_puntos!$1:$1,0))),NA()) | AH52: =IFERROR(IF(INDEX(Aux_puntos!$A$2:$OJ$901,48,MATCH($B$2&"|yI",Aux_puntos!$1:$1,0))="",NA(),INDEX(Aux_puntos!$A$2:$OJ$901,48,MATCH($B$2&"|yI",Aux_puntos!$1:$1,0))),NA()) | AI52: =IFERROR(IF(INDEX(Aux_puntos!$A$2:$OJ$901,48,MATCH($B$2&"|xN",Aux_puntos!$1:$1,0))="",NA(),INDEX(Aux_puntos!$A$2:$OJ$901,48,MATCH($B$2&"|xN",Aux_puntos!$1:$1,0))),NA()) | AJ52: =IFERROR(IF(INDEX(Aux_puntos!$A$2:$OJ$901,48,MATCH($B$2&"|yN",Aux_puntos!$1:$1,0))="",NA(),INDEX(Aux_puntos!$A$2:$OJ$901,48,MATCH($B$2&"|yN",Aux_puntos!$1:$1,0))),NA())
AC53: =IFERROR(IF(INDEX(Aux_puntos!$A$2:$OJ$901,49,MATCH($B$2&"|xK",Aux_puntos!$1:$1,0))="",NA(),INDEX(Aux_puntos!$A$2:$OJ$901,49,MATCH($B$2&"|xK",Aux_puntos!$1:$1,0))),NA()) | AD53: =IFERROR(IF(INDEX(Aux_puntos!$A$2:$OJ$901,49,MATCH($B$2&"|yK",Aux_puntos!$1:$1,0))="",NA(),INDEX(Aux_puntos!$A$2:$OJ$901,49,MATCH($B$2&"|yK",Aux_puntos!$1:$1,0))),NA()) | AE53: =IFERROR(IF(INDEX(Aux_puntos!$A$2:$OJ$901,49,MATCH($B$2&"|xC",Aux_puntos!$1:$1,0))="",NA(),INDEX(Aux_puntos!$A$2:$OJ$901,49,MATCH($B$2&"|xC",Aux_puntos!$1:$1,0))),NA()) | AF53: =IFERROR(IF(INDEX(Aux_puntos!$A$2:$OJ$901,49,MATCH($B$2&"|yC",Aux_puntos!$1:$1,0))="",NA(),INDEX(Aux_puntos!$A$2:$OJ$901,49,MATCH($B$2&"|yC",Aux_puntos!$1:$1,0))),NA()) | AG53: =IFERROR(IF(INDEX(Aux_puntos!$A$2:$OJ$901,49,MATCH($B$2&"|xI",Aux_puntos!$1:$1,0))="",NA(),INDEX(Aux_puntos!$A$2:$OJ$901,49,MATCH($B$2&"|xI",Aux_puntos!$1:$1,0))),NA()) | AH53: =IFERROR(IF(INDEX(Aux_puntos!$A$2:$OJ$901,49,MATCH($B$2&"|yI",Aux_puntos!$1:$1,0))="",NA(),INDEX(Aux_puntos!$A$2:$OJ$901,49,MATCH($B$2&"|yI",Aux_puntos!$1:$1,0))),NA()) | AI53: =IFERROR(IF(INDEX(Aux_puntos!$A$2:$OJ$901,49,MATCH($B$2&"|xN",Aux_puntos!$1:$1,0))="",NA(),INDEX(Aux_puntos!$A$2:$OJ$901,49,MATCH($B$2&"|xN",Aux_puntos!$1:$1,0))),NA()) | AJ53: =IFERROR(IF(INDEX(Aux_puntos!$A$2:$OJ$901,49,MATCH($B$2&"|yN",Aux_puntos!$1:$1,0))="",NA(),INDEX(Aux_puntos!$A$2:$OJ$901,49,MATCH($B$2&"|yN",Aux_puntos!$1:$1,0))),NA())
AC54: =IFERROR(IF(INDEX(Aux_puntos!$A$2:$OJ$901,50,MATCH($B$2&"|xK",Aux_puntos!$1:$1,0))="",NA(),INDEX(Aux_puntos!$A$2:$OJ$901,50,MATCH($B$2&"|xK",Aux_puntos!$1:$1,0))),NA()) | AD54: =IFERROR(IF(INDEX(Aux_puntos!$A$2:$OJ$901,50,MATCH($B$2&"|yK",Aux_puntos!$1:$1,0))="",NA(),INDEX(Aux_puntos!$A$2:$OJ$901,50,MATCH($B$2&"|yK",Aux_puntos!$1:$1,0))),NA()) | AE54: =IFERROR(IF(INDEX(Aux_puntos!$A$2:$OJ$901,50,MATCH($B$2&"|xC",Aux_puntos!$1:$1,0))="",NA(),INDEX(Aux_puntos!$A$2:$OJ$901,50,MATCH($B$2&"|xC",Aux_puntos!$1:$1,0))),NA()) | AF54: =IFERROR(IF(INDEX(Aux_puntos!$A$2:$OJ$901,50,MATCH($B$2&"|yC",Aux_puntos!$1:$1,0))="",NA(),INDEX(Aux_puntos!$A$2:$OJ$901,50,MATCH($B$2&"|yC",Aux_puntos!$1:$1,0))),NA()) | AG54: =IFERROR(IF(INDEX(Aux_puntos!$A$2:$OJ$901,50,MATCH($B$2&"|xI",Aux_puntos!$1:$1,0))="",NA(),INDEX(Aux_puntos!$A$2:$OJ$901,50,MATCH($B$2&"|xI",Aux_puntos!$1:$1,0))),NA()) | AH54: =IFERROR(IF(INDEX(Aux_puntos!$A$2:$OJ$901,50,MATCH($B$2&"|yI",Aux_puntos!$1:$1,0))="",NA(),INDEX(Aux_puntos!$A$2:$OJ$901,50,MATCH($B$2&"|yI",Aux_puntos!$1:$1,0))),NA()) | AI54: =IFERROR(IF(INDEX(Aux_puntos!$A$2:$OJ$901,50,MATCH($B$2&"|xN",Aux_puntos!$1:$1,0))="",NA(),INDEX(Aux_puntos!$A$2:$OJ$901,50,MATCH($B$2&"|xN",Aux_puntos!$1:$1,0))),NA()) | AJ54: =IFERROR(IF(INDEX(Aux_puntos!$A$2:$OJ$901,50,MATCH($B$2&"|yN",Aux_puntos!$1:$1,0))="",NA(),INDEX(Aux_puntos!$A$2:$OJ$901,50,MATCH($B$2&"|yN",Aux_puntos!$1:$1,0))),NA())
AC55: =IFERROR(IF(INDEX(Aux_puntos!$A$2:$OJ$901,51,MATCH($B$2&"|xK",Aux_puntos!$1:$1,0))="",NA(),INDEX(Aux_puntos!$A$2:$OJ$901,51,MATCH($B$2&"|xK",Aux_puntos!$1:$1,0))),NA()) | AD55: =IFERROR(IF(INDEX(Aux_puntos!$A$2:$OJ$901,51,MATCH($B$2&"|yK",Aux_puntos!$1:$1,0))="",NA(),INDEX(Aux_puntos!$A$2:$OJ$901,51,MATCH($B$2&"|yK",Aux_puntos!$1:$1,0))),NA()) | AE55: =IFERROR(IF(INDEX(Aux_puntos!$A$2:$OJ$901,51,MATCH($B$2&"|xC",Aux_puntos!$1:$1,0))="",NA(),INDEX(Aux_puntos!$A$2:$OJ$901,51,MATCH($B$2&"|xC",Aux_puntos!$1:$1,0))),NA()) | AF55: =IFERROR(IF(INDEX(Aux_puntos!$A$2:$OJ$901,51,MATCH($B$2&"|yC",Aux_puntos!$1:$1,0))="",NA(),INDEX(Aux_puntos!$A$2:$OJ$901,51,MATCH($B$2&"|yC",Aux_puntos!$1:$1,0))),NA()) | AG55: =IFERROR(IF(INDEX(Aux_puntos!$A$2:$OJ$901,51,MATCH($B$2&"|xI",Aux_puntos!$1:$1,0))="",NA(),INDEX(Aux_puntos!$A$2:$OJ$901,51,MATCH($B$2&"|xI",Aux_puntos!$1:$1,0))),NA()) | AH55: =IFERROR(IF(INDEX(Aux_puntos!$A$2:$OJ$901,51,MATCH($B$2&"|yI",Aux_puntos!$1:$1,0))="",NA(),INDEX(Aux_puntos!$A$2:$OJ$901,51,MATCH($B$2&"|yI",Aux_puntos!$1:$1,0))),NA()) | AI55: =IFERROR(IF(INDEX(Aux_puntos!$A$2:$OJ$901,51,MATCH($B$2&"|xN",Aux_puntos!$1:$1,0))="",NA(),INDEX(Aux_puntos!$A$2:$OJ$901,51,MATCH($B$2&"|xN",Aux_puntos!$1:$1,0))),NA()) | AJ55: =IFERROR(IF(INDEX(Aux_puntos!$A$2:$OJ$901,51,MATCH($B$2&"|yN",Aux_puntos!$1:$1,0))="",NA(),INDEX(Aux_puntos!$A$2:$OJ$901,51,MATCH($B$2&"|yN",Aux_puntos!$1:$1,0))),NA())
AC56: =IFERROR(IF(INDEX(Aux_puntos!$A$2:$OJ$901,52,MATCH($B$2&"|xK",Aux_puntos!$1:$1,0))="",NA(),INDEX(Aux_puntos!$A$2:$OJ$901,52,MATCH($B$2&"|xK",Aux_puntos!$1:$1,0))),NA()) | AD56: =IFERROR(IF(INDEX(Aux_puntos!$A$2:$OJ$901,52,MATCH($B$2&"|yK",Aux_puntos!$1:$1,0))="",NA(),INDEX(Aux_puntos!$A$2:$OJ$901,52,MATCH($B$2&"|yK",Aux_puntos!$1:$1,0))),NA()) | AE56: =IFERROR(IF(INDEX(Aux_puntos!$A$2:$OJ$901,52,MATCH($B$2&"|xC",Aux_puntos!$1:$1,0))="",NA(),INDEX(Aux_puntos!$A$2:$OJ$901,52,MATCH($B$2&"|xC",Aux_puntos!$1:$1,0))),NA()) | AF56: =IFERROR(IF(INDEX(Aux_puntos!$A$2:$OJ$901,52,MATCH($B$2&"|yC",Aux_puntos!$1:$1,0))="",NA(),INDEX(Aux_puntos!$A$2:$OJ$901,52,MATCH($B$2&"|yC",Aux_puntos!$1:$1,0))),NA()) | AG56: =IFERROR(IF(INDEX(Aux_puntos!$A$2:$OJ$901,52,MATCH($B$2&"|xI",Aux_puntos!$1:$1,0))="",NA(),INDEX(Aux_puntos!$A$2:$OJ$901,52,MATCH($B$2&"|xI",Aux_puntos!$1:$1,0))),NA()) | AH56: =IFERROR(IF(INDEX(Aux_puntos!$A$2:$OJ$901,52,MATCH($B$2&"|yI",Aux_puntos!$1:$1,0))="",NA(),INDEX(Aux_puntos!$A$2:$OJ$901,52,MATCH($B$2&"|yI",Aux_puntos!$1:$1,0))),NA()) | AI56: =IFERROR(IF(INDEX(Aux_puntos!$A$2:$OJ$901,52,MATCH($B$2&"|xN",Aux_puntos!$1:$1,0))="",NA(),INDEX(Aux_puntos!$A$2:$OJ$901,52,MATCH($B$2&"|xN",Aux_puntos!$1:$1,0))),NA()) | AJ56: =IFERROR(IF(INDEX(Aux_puntos!$A$2:$OJ$901,52,MATCH($B$2&"|yN",Aux_puntos!$1:$1,0))="",NA(),INDEX(Aux_puntos!$A$2:$OJ$901,52,MATCH($B$2&"|yN",Aux_puntos!$1:$1,0))),NA())
AC57: =IFERROR(IF(INDEX(Aux_puntos!$A$2:$OJ$901,53,MATCH($B$2&"|xK",Aux_puntos!$1:$1,0))="",NA(),INDEX(Aux_puntos!$A$2:$OJ$901,53,MATCH($B$2&"|xK",Aux_puntos!$1:$1,0))),NA()) | AD57: =IFERROR(IF(INDEX(Aux_puntos!$A$2:$OJ$901,53,MATCH($B$2&"|yK",Aux_puntos!$1:$1,0))="",NA(),INDEX(Aux_puntos!$A$2:$OJ$901,53,MATCH($B$2&"|yK",Aux_puntos!$1:$1,0))),NA()) | AE57: =IFERROR(IF(INDEX(Aux_puntos!$A$2:$OJ$901,53,MATCH($B$2&"|xC",Aux_puntos!$1:$1,0))="",NA(),INDEX(Aux_puntos!$A$2:$OJ$901,53,MATCH($B$2&"|xC",Aux_puntos!$1:$1,0))),NA()) | AF57: =IFERROR(IF(INDEX(Aux_puntos!$A$2:$OJ$901,53,MATCH($B$2&"|yC",Aux_puntos!$1:$1,0))="",NA(),INDEX(Aux_puntos!$A$2:$OJ$901,53,MATCH($B$2&"|yC",Aux_puntos!$1:$1,0))),NA()) | AG57: =IFERROR(IF(INDEX(Aux_puntos!$A$2:$OJ$901,53,MATCH($B$2&"|xI",Aux_puntos!$1:$1,0))="",NA(),INDEX(Aux_puntos!$A$2:$OJ$901,53,MATCH($B$2&"|xI",Aux_puntos!$1:$1,0))),NA()) | AH57: =IFERROR(IF(INDEX(Aux_puntos!$A$2:$OJ$901,53,MATCH($B$2&"|yI",Aux_puntos!$1:$1,0))="",NA(),INDEX(Aux_puntos!$A$2:$OJ$901,53,MATCH($B$2&"|yI",Aux_puntos!$1:$1,0))),NA()) | AI57: =IFERROR(IF(INDEX(Aux_puntos!$A$2:$OJ$901,53,MATCH($B$2&"|xN",Aux_puntos!$1:$1,0))="",NA(),INDEX(Aux_puntos!$A$2:$OJ$901,53,MATCH($B$2&"|xN",Aux_puntos!$1:$1,0))),NA()) | AJ57: =IFERROR(IF(INDEX(Aux_puntos!$A$2:$OJ$901,53,MATCH($B$2&"|yN",Aux_puntos!$1:$1,0))="",NA(),INDEX(Aux_puntos!$A$2:$OJ$901,53,MATCH($B$2&"|yN",Aux_puntos!$1:$1,0))),NA())
AC58: =IFERROR(IF(INDEX(Aux_puntos!$A$2:$OJ$901,54,MATCH($B$2&"|xK",Aux_puntos!$1:$1,0))="",NA(),INDEX(Aux_puntos!$A$2:$OJ$901,54,MATCH($B$2&"|xK",Aux_puntos!$1:$1,0))),NA()) | AD58: =IFERROR(IF(INDEX(Aux_puntos!$A$2:$OJ$901,54,MATCH($B$2&"|yK",Aux_puntos!$1:$1,0))="",NA(),INDEX(Aux_puntos!$A$2:$OJ$901,54,MATCH($B$2&"|yK",Aux_puntos!$1:$1,0))),NA()) | AE58: =IFERROR(IF(INDEX(Aux_puntos!$A$2:$OJ$901,54,MATCH($B$2&"|xC",Aux_puntos!$1:$1,0))="",NA(),INDEX(Aux_puntos!$A$2:$OJ$901,54,MATCH($B$2&"|xC",Aux_puntos!$1:$1,0))),NA()) | AF58: =IFERROR(IF(INDEX(Aux_puntos!$A$2:$OJ$901,54,MATCH($B$2&"|yC",Aux_puntos!$1:$1,0))="",NA(),INDEX(Aux_puntos!$A$2:$OJ$901,54,MATCH($B$2&"|yC",Aux_puntos!$1:$1,0))),NA()) | AG58: =IFERROR(IF(INDEX(Aux_puntos!$A$2:$OJ$901,54,MATCH($B$2&"|xI",Aux_puntos!$1:$1,0))="",NA(),INDEX(Aux_puntos!$A$2:$OJ$901,54,MATCH($B$2&"|xI",Aux_puntos!$1:$1,0))),NA()) | AH58: =IFERROR(IF(INDEX(Aux_puntos!$A$2:$OJ$901,54,MATCH($B$2&"|yI",Aux_puntos!$1:$1,0))="",NA(),INDEX(Aux_puntos!$A$2:$OJ$901,54,MATCH($B$2&"|yI",Aux_puntos!$1:$1,0))),NA()) | AI58: =IFERROR(IF(INDEX(Aux_puntos!$A$2:$OJ$901,54,MATCH($B$2&"|xN",Aux_puntos!$1:$1,0))="",NA(),INDEX(Aux_puntos!$A$2:$OJ$901,54,MATCH($B$2&"|xN",Aux_puntos!$1:$1,0))),NA()) | AJ58: =IFERROR(IF(INDEX(Aux_puntos!$A$2:$OJ$901,54,MATCH($B$2&"|yN",Aux_puntos!$1:$1,0))="",NA(),INDEX(Aux_puntos!$A$2:$OJ$901,54,MATCH($B$2&"|yN",Aux_puntos!$1:$1,0))),NA())
AC59: =IFERROR(IF(INDEX(Aux_puntos!$A$2:$OJ$901,55,MATCH($B$2&"|xK",Aux_puntos!$1:$1,0))="",NA(),INDEX(Aux_puntos!$A$2:$OJ$901,55,MATCH($B$2&"|xK",Aux_puntos!$1:$1,0))),NA()) | AD59: =IFERROR(IF(INDEX(Aux_puntos!$A$2:$OJ$901,55,MATCH($B$2&"|yK",Aux_puntos!$1:$1,0))="",NA(),INDEX(Aux_puntos!$A$2:$OJ$901,55,MATCH($B$2&"|yK",Aux_puntos!$1:$1,0))),NA()) | AE59: =IFERROR(IF(INDEX(Aux_puntos!$A$2:$OJ$901,55,MATCH($B$2&"|xC",Aux_puntos!$1:$1,0))="",NA(),INDEX(Aux_puntos!$A$2:$OJ$901,55,MATCH($B$2&"|xC",Aux_puntos!$1:$1,0))),NA()) | AF59: =IFERROR(IF(INDEX(Aux_puntos!$A$2:$OJ$901,55,MATCH($B$2&"|yC",Aux_puntos!$1:$1,0))="",NA(),INDEX(Aux_puntos!$A$2:$OJ$901,55,MATCH($B$2&"|yC",Aux_puntos!$1:$1,0))),NA()) | AG59: =IFERROR(IF(INDEX(Aux_puntos!$A$2:$OJ$901,55,MATCH($B$2&"|xI",Aux_puntos!$1:$1,0))="",NA(),INDEX(Aux_puntos!$A$2:$OJ$901,55,MATCH($B$2&"|xI",Aux_puntos!$1:$1,0))),NA()) | AH59: =IFERROR(IF(INDEX(Aux_puntos!$A$2:$OJ$901,55,MATCH($B$2&"|yI",Aux_puntos!$1:$1,0))="",NA(),INDEX(Aux_puntos!$A$2:$OJ$901,55,MATCH($B$2&"|yI",Aux_puntos!$1:$1,0))),NA()) | AI59: =IFERROR(IF(INDEX(Aux_puntos!$A$2:$OJ$901,55,MATCH($B$2&"|xN",Aux_puntos!$1:$1,0))="",NA(),INDEX(Aux_puntos!$A$2:$OJ$901,55,MATCH($B$2&"|xN",Aux_puntos!$1:$1,0))),NA()) | AJ59: =IFERROR(IF(INDEX(Aux_puntos!$A$2:$OJ$901,55,MATCH($B$2&"|yN",Aux_puntos!$1:$1,0))="",NA(),INDEX(Aux_puntos!$A$2:$OJ$901,55,MATCH($B$2&"|yN",Aux_puntos!$1:$1,0))),NA())
AC60: =IFERROR(IF(INDEX(Aux_puntos!$A$2:$OJ$901,56,MATCH($B$2&"|xK",Aux_puntos!$1:$1,0))="",NA(),INDEX(Aux_puntos!$A$2:$OJ$901,56,MATCH($B$2&"|xK",Aux_puntos!$1:$1,0))),NA()) | AD60: =IFERROR(IF(INDEX(Aux_puntos!$A$2:$OJ$901,56,MATCH($B$2&"|yK",Aux_puntos!$1:$1,0))="",NA(),INDEX(Aux_puntos!$A$2:$OJ$901,56,MATCH($B$2&"|yK",Aux_puntos!$1:$1,0))),NA()) | AE60: =IFERROR(IF(INDEX(Aux_puntos!$A$2:$OJ$901,56,MATCH($B$2&"|xC",Aux_puntos!$1:$1,0))="",NA(),INDEX(Aux_puntos!$A$2:$OJ$901,56,MATCH($B$2&"|xC",Aux_puntos!$1:$1,0))),NA()) | AF60: =IFERROR(IF(INDEX(Aux_puntos!$A$2:$OJ$901,56,MATCH($B$2&"|yC",Aux_puntos!$1:$1,0))="",NA(),INDEX(Aux_puntos!$A$2:$OJ$901,56,MATCH($B$2&"|yC",Aux_puntos!$1:$1,0))),NA()) | AG60: =IFERROR(IF(INDEX(Aux_puntos!$A$2:$OJ$901,56,MATCH($B$2&"|xI",Aux_puntos!$1:$1,0))="",NA(),INDEX(Aux_puntos!$A$2:$OJ$901,56,MATCH($B$2&"|xI",Aux_puntos!$1:$1,0))),NA()) | AH60: =IFERROR(IF(INDEX(Aux_puntos!$A$2:$OJ$901,56,MATCH($B$2&"|yI",Aux_puntos!$1:$1,0))="",NA(),INDEX(Aux_puntos!$A$2:$OJ$901,56,MATCH($B$2&"|yI",Aux_puntos!$1:$1,0))),NA()) | AI60: =IFERROR(IF(INDEX(Aux_puntos!$A$2:$OJ$901,56,MATCH($B$2&"|xN",Aux_puntos!$1:$1,0))="",NA(),INDEX(Aux_puntos!$A$2:$OJ$901,56,MATCH($B$2&"|xN",Aux_puntos!$1:$1,0))),NA()) | AJ60: =IFERROR(IF(INDEX(Aux_puntos!$A$2:$OJ$901,56,MATCH($B$2&"|yN",Aux_puntos!$1:$1,0))="",NA(),INDEX(Aux_puntos!$A$2:$OJ$901,56,MATCH($B$2&"|yN",Aux_puntos!$1:$1,0))),NA())
AC61: =IFERROR(IF(INDEX(Aux_puntos!$A$2:$OJ$901,57,MATCH($B$2&"|xK",Aux_puntos!$1:$1,0))="",NA(),INDEX(Aux_puntos!$A$2:$OJ$901,57,MATCH($B$2&"|xK",Aux_puntos!$1:$1,0))),NA()) | AD61: =IFERROR(IF(INDEX(Aux_puntos!$A$2:$OJ$901,57,MATCH($B$2&"|yK",Aux_puntos!$1:$1,0))="",NA(),INDEX(Aux_puntos!$A$2:$OJ$901,57,MATCH($B$2&"|yK",Aux_puntos!$1:$1,0))),NA()) | AE61: =IFERROR(IF(INDEX(Aux_puntos!$A$2:$OJ$901,57,MATCH($B$2&"|xC",Aux_puntos!$1:$1,0))="",NA(),INDEX(Aux_puntos!$A$2:$OJ$901,57,MATCH($B$2&"|xC",Aux_puntos!$1:$1,0))),NA()) | AF61: =IFERROR(IF(INDEX(Aux_puntos!$A$2:$OJ$901,57,MATCH($B$2&"|yC",Aux_puntos!$1:$1,0))="",NA(),INDEX(Aux_puntos!$A$2:$OJ$901,57,MATCH($B$2&"|yC",Aux_puntos!$1:$1,0))),NA()) | AG61: =IFERROR(IF(INDEX(Aux_puntos!$A$2:$OJ$901,57,MATCH($B$2&"|xI",Aux_puntos!$1:$1,0))="",NA(),INDEX(Aux_puntos!$A$2:$OJ$901,57,MATCH($B$2&"|xI",Aux_puntos!$1:$1,0))),NA()) | AH61: =IFERROR(IF(INDEX(Aux_puntos!$A$2:$OJ$901,57,MATCH($B$2&"|yI",Aux_puntos!$1:$1,0))="",NA(),INDEX(Aux_puntos!$A$2:$OJ$901,57,MATCH($B$2&"|yI",Aux_puntos!$1:$1,0))),NA()) | AI61: =IFERROR(IF(INDEX(Aux_puntos!$A$2:$OJ$901,57,MATCH($B$2&"|xN",Aux_puntos!$1:$1,0))="",NA(),INDEX(Aux_puntos!$A$2:$OJ$901,57,MATCH($B$2&"|xN",Aux_puntos!$1:$1,0))),NA()) | AJ61: =IFERROR(IF(INDEX(Aux_puntos!$A$2:$OJ$901,57,MATCH($B$2&"|yN",Aux_puntos!$1:$1,0))="",NA(),INDEX(Aux_puntos!$A$2:$OJ$901,57,MATCH($B$2&"|yN",Aux_puntos!$1:$1,0))),NA())
AC62: =IFERROR(IF(INDEX(Aux_puntos!$A$2:$OJ$901,58,MATCH($B$2&"|xK",Aux_puntos!$1:$1,0))="",NA(),INDEX(Aux_puntos!$A$2:$OJ$901,58,MATCH($B$2&"|xK",Aux_puntos!$1:$1,0))),NA()) | AD62: =IFERROR(IF(INDEX(Aux_puntos!$A$2:$OJ$901,58,MATCH($B$2&"|yK",Aux_puntos!$1:$1,0))="",NA(),INDEX(Aux_puntos!$A$2:$OJ$901,58,MATCH($B$2&"|yK",Aux_puntos!$1:$1,0))),NA()) | AE62: =IFERROR(IF(INDEX(Aux_puntos!$A$2:$OJ$901,58,MATCH($B$2&"|xC",Aux_puntos!$1:$1,0))="",NA(),INDEX(Aux_puntos!$A$2:$OJ$901,58,MATCH($B$2&"|xC",Aux_puntos!$1:$1,0))),NA()) | AF62: =IFERROR(IF(INDEX(Aux_puntos!$A$2:$OJ$901,58,MATCH($B$2&"|yC",Aux_puntos!$1:$1,0))="",NA(),INDEX(Aux_puntos!$A$2:$OJ$901,58,MATCH($B$2&"|yC",Aux_puntos!$1:$1,0))),NA()) | AG62: =IFERROR(IF(INDEX(Aux_puntos!$A$2:$OJ$901,58,MATCH($B$2&"|xI",Aux_puntos!$1:$1,0))="",NA(),INDEX(Aux_puntos!$A$2:$OJ$901,58,MATCH($B$2&"|xI",Aux_puntos!$1:$1,0))),NA()) | AH62: =IFERROR(IF(INDEX(Aux_puntos!$A$2:$OJ$901,58,MATCH($B$2&"|yI",Aux_puntos!$1:$1,0))="",NA(),INDEX(Aux_puntos!$A$2:$OJ$901,58,MATCH($B$2&"|yI",Aux_puntos!$1:$1,0))),NA()) | AI62: =IFERROR(IF(INDEX(Aux_puntos!$A$2:$OJ$901,58,MATCH($B$2&"|xN",Aux_puntos!$1:$1,0))="",NA(),INDEX(Aux_puntos!$A$2:$OJ$901,58,MATCH($B$2&"|xN",Aux_puntos!$1:$1,0))),NA()) | AJ62: =IFERROR(IF(INDEX(Aux_puntos!$A$2:$OJ$901,58,MATCH($B$2&"|yN",Aux_puntos!$1:$1,0))="",NA(),INDEX(Aux_puntos!$A$2:$OJ$901,58,MATCH($B$2&"|yN",Aux_puntos!$1:$1,0))),NA())
AC63: =IFERROR(IF(INDEX(Aux_puntos!$A$2:$OJ$901,59,MATCH($B$2&"|xK",Aux_puntos!$1:$1,0))="",NA(),INDEX(Aux_puntos!$A$2:$OJ$901,59,MATCH($B$2&"|xK",Aux_puntos!$1:$1,0))),NA()) | AD63: =IFERROR(IF(INDEX(Aux_puntos!$A$2:$OJ$901,59,MATCH($B$2&"|yK",Aux_puntos!$1:$1,0))="",NA(),INDEX(Aux_puntos!$A$2:$OJ$901,59,MATCH($B$2&"|yK",Aux_puntos!$1:$1,0))),NA()) | AE63: =IFERROR(IF(INDEX(Aux_puntos!$A$2:$OJ$901,59,MATCH($B$2&"|xC",Aux_puntos!$1:$1,0))="",NA(),INDEX(Aux_puntos!$A$2:$OJ$901,59,MATCH($B$2&"|xC",Aux_puntos!$1:$1,0))),NA()) | AF63: =IFERROR(IF(INDEX(Aux_puntos!$A$2:$OJ$901,59,MATCH($B$2&"|yC",Aux_puntos!$1:$1,0))="",NA(),INDEX(Aux_puntos!$A$2:$OJ$901,59,MATCH($B$2&"|yC",Aux_puntos!$1:$1,0))),NA()) | AG63: =IFERROR(IF(INDEX(Aux_puntos!$A$2:$OJ$901,59,MATCH($B$2&"|xI",Aux_puntos!$1:$1,0))="",NA(),INDEX(Aux_puntos!$A$2:$OJ$901,59,MATCH($B$2&"|xI",Aux_puntos!$1:$1,0))),NA()) | AH63: =IFERROR(IF(INDEX(Aux_puntos!$A$2:$OJ$901,59,MATCH($B$2&"|yI",Aux_puntos!$1:$1,0))="",NA(),INDEX(Aux_puntos!$A$2:$OJ$901,59,MATCH($B$2&"|yI",Aux_puntos!$1:$1,0))),NA()) | AI63: =IFERROR(IF(INDEX(Aux_puntos!$A$2:$OJ$901,59,MATCH($B$2&"|xN",Aux_puntos!$1:$1,0))="",NA(),INDEX(Aux_puntos!$A$2:$OJ$901,59,MATCH($B$2&"|xN",Aux_puntos!$1:$1,0))),NA()) | AJ63: =IFERROR(IF(INDEX(Aux_puntos!$A$2:$OJ$901,59,MATCH($B$2&"|yN",Aux_puntos!$1:$1,0))="",NA(),INDEX(Aux_puntos!$A$2:$OJ$901,59,MATCH($B$2&"|yN",Aux_puntos!$1:$1,0))),NA())
AC64: =IFERROR(IF(INDEX(Aux_puntos!$A$2:$OJ$901,60,MATCH($B$2&"|xK",Aux_puntos!$1:$1,0))="",NA(),INDEX(Aux_puntos!$A$2:$OJ$901,60,MATCH($B$2&"|xK",Aux_puntos!$1:$1,0))),NA()) | AD64: =IFERROR(IF(INDEX(Aux_puntos!$A$2:$OJ$901,60,MATCH($B$2&"|yK",Aux_puntos!$1:$1,0))="",NA(),INDEX(Aux_puntos!$A$2:$OJ$901,60,MATCH($B$2&"|yK",Aux_puntos!$1:$1,0))),NA()) | AE64: =IFERROR(IF(INDEX(Aux_puntos!$A$2:$OJ$901,60,MATCH($B$2&"|xC",Aux_puntos!$1:$1,0))="",NA(),INDEX(Aux_puntos!$A$2:$OJ$901,60,MATCH($B$2&"|xC",Aux_puntos!$1:$1,0))),NA()) | AF64: =IFERROR(IF(INDEX(Aux_puntos!$A$2:$OJ$901,60,MATCH($B$2&"|yC",Aux_puntos!$1:$1,0))="",NA(),INDEX(Aux_puntos!$A$2:$OJ$901,60,MATCH($B$2&"|yC",Aux_puntos!$1:$1,0))),NA()) | AG64: =IFERROR(IF(INDEX(Aux_puntos!$A$2:$OJ$901,60,MATCH($B$2&"|xI",Aux_puntos!$1:$1,0))="",NA(),INDEX(Aux_puntos!$A$2:$OJ$901,60,MATCH($B$2&"|xI",Aux_puntos!$1:$1,0))),NA()) | AH64: =IFERROR(IF(INDEX(Aux_puntos!$A$2:$OJ$901,60,MATCH($B$2&"|yI",Aux_puntos!$1:$1,0))="",NA(),INDEX(Aux_puntos!$A$2:$OJ$901,60,MATCH($B$2&"|yI",Aux_puntos!$1:$1,0))),NA()) | AI64: =IFERROR(IF(INDEX(Aux_puntos!$A$2:$OJ$901,60,MATCH($B$2&"|xN",Aux_puntos!$1:$1,0))="",NA(),INDEX(Aux_puntos!$A$2:$OJ$901,60,MATCH($B$2&"|xN",Aux_puntos!$1:$1,0))),NA()) | AJ64: =IFERROR(IF(INDEX(Aux_puntos!$A$2:$OJ$901,60,MATCH($B$2&"|yN",Aux_puntos!$1:$1,0))="",NA(),INDEX(Aux_puntos!$A$2:$OJ$901,60,MATCH($B$2&"|yN",Aux_puntos!$1:$1,0))),NA())
AC65: =IFERROR(IF(INDEX(Aux_puntos!$A$2:$OJ$901,61,MATCH($B$2&"|xK",Aux_puntos!$1:$1,0))="",NA(),INDEX(Aux_puntos!$A$2:$OJ$901,61,MATCH($B$2&"|xK",Aux_puntos!$1:$1,0))),NA()) | AD65: =IFERROR(IF(INDEX(Aux_puntos!$A$2:$OJ$901,61,MATCH($B$2&"|yK",Aux_puntos!$1:$1,0))="",NA(),INDEX(Aux_puntos!$A$2:$OJ$901,61,MATCH($B$2&"|yK",Aux_puntos!$1:$1,0))),NA()) | AE65: =IFERROR(IF(INDEX(Aux_puntos!$A$2:$OJ$901,61,MATCH($B$2&"|xC",Aux_puntos!$1:$1,0))="",NA(),INDEX(Aux_puntos!$A$2:$OJ$901,61,MATCH($B$2&"|xC",Aux_puntos!$1:$1,0))),NA()) | AF65: =IFERROR(IF(INDEX(Aux_puntos!$A$2:$OJ$901,61,MATCH($B$2&"|yC",Aux_puntos!$1:$1,0))="",NA(),INDEX(Aux_puntos!$A$2:$OJ$901,61,MATCH($B$2&"|yC",Aux_puntos!$1:$1,0))),NA()) | AG65: =IFERROR(IF(INDEX(Aux_puntos!$A$2:$OJ$901,61,MATCH($B$2&"|xI",Aux_puntos!$1:$1,0))="",NA(),INDEX(Aux_puntos!$A$2:$OJ$901,61,MATCH($B$2&"|xI",Aux_puntos!$1:$1,0))),NA()) | AH65: =IFERROR(IF(INDEX(Aux_puntos!$A$2:$OJ$901,61,MATCH($B$2&"|yI",Aux_puntos!$1:$1,0))="",NA(),INDEX(Aux_puntos!$A$2:$OJ$901,61,MATCH($B$2&"|yI",Aux_puntos!$1:$1,0))),NA()) | AI65: =IFERROR(IF(INDEX(Aux_puntos!$A$2:$OJ$901,61,MATCH($B$2&"|xN",Aux_puntos!$1:$1,0))="",NA(),INDEX(Aux_puntos!$A$2:$OJ$901,61,MATCH($B$2&"|xN",Aux_puntos!$1:$1,0))),NA()) | AJ65: =IFERROR(IF(INDEX(Aux_puntos!$A$2:$OJ$901,61,MATCH($B$2&"|yN",Aux_puntos!$1:$1,0))="",NA(),INDEX(Aux_puntos!$A$2:$OJ$901,61,MATCH($B$2&"|yN",Aux_puntos!$1:$1,0))),NA())
AC66: =IFERROR(IF(INDEX(Aux_puntos!$A$2:$OJ$901,62,MATCH($B$2&"|xK",Aux_puntos!$1:$1,0))="",NA(),INDEX(Aux_puntos!$A$2:$OJ$901,62,MATCH($B$2&"|xK",Aux_puntos!$1:$1,0))),NA()) | AD66: =IFERROR(IF(INDEX(Aux_puntos!$A$2:$OJ$901,62,MATCH($B$2&"|yK",Aux_puntos!$1:$1,0))="",NA(),INDEX(Aux_puntos!$A$2:$OJ$901,62,MATCH($B$2&"|yK",Aux_puntos!$1:$1,0))),NA()) | AE66: =IFERROR(IF(INDEX(Aux_puntos!$A$2:$OJ$901,62,MATCH($B$2&"|xC",Aux_puntos!$1:$1,0))="",NA(),INDEX(Aux_puntos!$A$2:$OJ$901,62,MATCH($B$2&"|xC",Aux_puntos!$1:$1,0))),NA()) | AF66: =IFERROR(IF(INDEX(Aux_puntos!$A$2:$OJ$901,62,MATCH($B$2&"|yC",Aux_puntos!$1:$1,0))="",NA(),INDEX(Aux_puntos!$A$2:$OJ$901,62,MATCH($B$2&"|yC",Aux_puntos!$1:$1,0))),NA()) | AG66: =IFERROR(IF(INDEX(Aux_puntos!$A$2:$OJ$901,62,MATCH($B$2&"|xI",Aux_puntos!$1:$1,0))="",NA(),INDEX(Aux_puntos!$A$2:$OJ$901,62,MATCH($B$2&"|xI",Aux_puntos!$1:$1,0))),NA()) | AH66: =IFERROR(IF(INDEX(Aux_puntos!$A$2:$OJ$901,62,MATCH($B$2&"|yI",Aux_puntos!$1:$1,0))="",NA(),INDEX(Aux_puntos!$A$2:$OJ$901,62,MATCH($B$2&"|yI",Aux_puntos!$1:$1,0))),NA()) | AI66: =IFERROR(IF(INDEX(Aux_puntos!$A$2:$OJ$901,62,MATCH($B$2&"|xN",Aux_puntos!$1:$1,0))="",NA(),INDEX(Aux_puntos!$A$2:$OJ$901,62,MATCH($B$2&"|xN",Aux_puntos!$1:$1,0))),NA()) | AJ66: =IFERROR(IF(INDEX(Aux_puntos!$A$2:$OJ$901,62,MATCH($B$2&"|yN",Aux_puntos!$1:$1,0))="",NA(),INDEX(Aux_puntos!$A$2:$OJ$901,62,MATCH($B$2&"|yN",Aux_puntos!$1:$1,0))),NA())
AC67: =IFERROR(IF(INDEX(Aux_puntos!$A$2:$OJ$901,63,MATCH($B$2&"|xK",Aux_puntos!$1:$1,0))="",NA(),INDEX(Aux_puntos!$A$2:$OJ$901,63,MATCH($B$2&"|xK",Aux_puntos!$1:$1,0))),NA()) | AD67: =IFERROR(IF(INDEX(Aux_puntos!$A$2:$OJ$901,63,MATCH($B$2&"|yK",Aux_puntos!$1:$1,0))="",NA(),INDEX(Aux_puntos!$A$2:$OJ$901,63,MATCH($B$2&"|yK",Aux_puntos!$1:$1,0))),NA()) | AE67: =IFERROR(IF(INDEX(Aux_puntos!$A$2:$OJ$901,63,MATCH($B$2&"|xC",Aux_puntos!$1:$1,0))="",NA(),INDEX(Aux_puntos!$A$2:$OJ$901,63,MATCH($B$2&"|xC",Aux_puntos!$1:$1,0))),NA()) | AF67: =IFERROR(IF(INDEX(Aux_puntos!$A$2:$OJ$901,63,MATCH($B$2&"|yC",Aux_puntos!$1:$1,0))="",NA(),INDEX(Aux_puntos!$A$2:$OJ$901,63,MATCH($B$2&"|yC",Aux_puntos!$1:$1,0))),NA()) | AG67: =IFERROR(IF(INDEX(Aux_puntos!$A$2:$OJ$901,63,MATCH($B$2&"|xI",Aux_puntos!$1:$1,0))="",NA(),INDEX(Aux_puntos!$A$2:$OJ$901,63,MATCH($B$2&"|xI",Aux_puntos!$1:$1,0))),NA()) | AH67: =IFERROR(IF(INDEX(Aux_puntos!$A$2:$OJ$901,63,MATCH($B$2&"|yI",Aux_puntos!$1:$1,0))="",NA(),INDEX(Aux_puntos!$A$2:$OJ$901,63,MATCH($B$2&"|yI",Aux_puntos!$1:$1,0))),NA()) | AI67: =IFERROR(IF(INDEX(Aux_puntos!$A$2:$OJ$901,63,MATCH($B$2&"|xN",Aux_puntos!$1:$1,0))="",NA(),INDEX(Aux_puntos!$A$2:$OJ$901,63,MATCH($B$2&"|xN",Aux_puntos!$1:$1,0))),NA()) | AJ67: =IFERROR(IF(INDEX(Aux_puntos!$A$2:$OJ$901,63,MATCH($B$2&"|yN",Aux_puntos!$1:$1,0))="",NA(),INDEX(Aux_puntos!$A$2:$OJ$901,63,MATCH($B$2&"|yN",Aux_puntos!$1:$1,0))),NA())
AC68: =IFERROR(IF(INDEX(Aux_puntos!$A$2:$OJ$901,64,MATCH($B$2&"|xK",Aux_puntos!$1:$1,0))="",NA(),INDEX(Aux_puntos!$A$2:$OJ$901,64,MATCH($B$2&"|xK",Aux_puntos!$1:$1,0))),NA()) | AD68: =IFERROR(IF(INDEX(Aux_puntos!$A$2:$OJ$901,64,MATCH($B$2&"|yK",Aux_puntos!$1:$1,0))="",NA(),INDEX(Aux_puntos!$A$2:$OJ$901,64,MATCH($B$2&"|yK",Aux_puntos!$1:$1,0))),NA()) | AE68: =IFERROR(IF(INDEX(Aux_puntos!$A$2:$OJ$901,64,MATCH($B$2&"|xC",Aux_puntos!$1:$1,0))="",NA(),INDEX(Aux_puntos!$A$2:$OJ$901,64,MATCH($B$2&"|xC",Aux_puntos!$1:$1,0))),NA()) | AF68: =IFERROR(IF(INDEX(Aux_puntos!$A$2:$OJ$901,64,MATCH($B$2&"|yC",Aux_puntos!$1:$1,0))="",NA(),INDEX(Aux_puntos!$A$2:$OJ$901,64,MATCH($B$2&"|yC",Aux_puntos!$1:$1,0))),NA()) | AG68: =IFERROR(IF(INDEX(Aux_puntos!$A$2:$OJ$901,64,MATCH($B$2&"|xI",Aux_puntos!$1:$1,0))="",NA(),INDEX(Aux_puntos!$A$2:$OJ$901,64,MATCH($B$2&"|xI",Aux_puntos!$1:$1,0))),NA()) | AH68: =IFERROR(IF(INDEX(Aux_puntos!$A$2:$OJ$901,64,MATCH($B$2&"|yI",Aux_puntos!$1:$1,0))="",NA(),INDEX(Aux_puntos!$A$2:$OJ$901,64,MATCH($B$2&"|yI",Aux_puntos!$1:$1,0))),NA()) | AI68: =IFERROR(IF(INDEX(Aux_puntos!$A$2:$OJ$901,64,MATCH($B$2&"|xN",Aux_puntos!$1:$1,0))="",NA(),INDEX(Aux_puntos!$A$2:$OJ$901,64,MATCH($B$2&"|xN",Aux_puntos!$1:$1,0))),NA()) | AJ68: =IFERROR(IF(INDEX(Aux_puntos!$A$2:$OJ$901,64,MATCH($B$2&"|yN",Aux_puntos!$1:$1,0))="",NA(),INDEX(Aux_puntos!$A$2:$OJ$901,64,MATCH($B$2&"|yN",Aux_puntos!$1:$1,0))),NA())
AC69: =IFERROR(IF(INDEX(Aux_puntos!$A$2:$OJ$901,65,MATCH($B$2&"|xK",Aux_puntos!$1:$1,0))="",NA(),INDEX(Aux_puntos!$A$2:$OJ$901,65,MATCH($B$2&"|xK",Aux_puntos!$1:$1,0))),NA()) | AD69: =IFERROR(IF(INDEX(Aux_puntos!$A$2:$OJ$901,65,MATCH($B$2&"|yK",Aux_puntos!$1:$1,0))="",NA(),INDEX(Aux_puntos!$A$2:$OJ$901,65,MATCH($B$2&"|yK",Aux_puntos!$1:$1,0))),NA()) | AE69: =IFERROR(IF(INDEX(Aux_puntos!$A$2:$OJ$901,65,MATCH($B$2&"|xC",Aux_puntos!$1:$1,0))="",NA(),INDEX(Aux_puntos!$A$2:$OJ$901,65,MATCH($B$2&"|xC",Aux_puntos!$1:$1,0))),NA()) | AF69: =IFERROR(IF(INDEX(Aux_puntos!$A$2:$OJ$901,65,MATCH($B$2&"|yC",Aux_puntos!$1:$1,0))="",NA(),INDEX(Aux_puntos!$A$2:$OJ$901,65,MATCH($B$2&"|yC",Aux_puntos!$1:$1,0))),NA()) | AG69: =IFERROR(IF(INDEX(Aux_puntos!$A$2:$OJ$901,65,MATCH($B$2&"|xI",Aux_puntos!$1:$1,0))="",NA(),INDEX(Aux_puntos!$A$2:$OJ$901,65,MATCH($B$2&"|xI",Aux_puntos!$1:$1,0))),NA()) | AH69: =IFERROR(IF(INDEX(Aux_puntos!$A$2:$OJ$901,65,MATCH($B$2&"|yI",Aux_puntos!$1:$1,0))="",NA(),INDEX(Aux_puntos!$A$2:$OJ$901,65,MATCH($B$2&"|yI",Aux_puntos!$1:$1,0))),NA()) | AI69: =IFERROR(IF(INDEX(Aux_puntos!$A$2:$OJ$901,65,MATCH($B$2&"|xN",Aux_puntos!$1:$1,0))="",NA(),INDEX(Aux_puntos!$A$2:$OJ$901,65,MATCH($B$2&"|xN",Aux_puntos!$1:$1,0))),NA()) | AJ69: =IFERROR(IF(INDEX(Aux_puntos!$A$2:$OJ$901,65,MATCH($B$2&"|yN",Aux_puntos!$1:$1,0))="",NA(),INDEX(Aux_puntos!$A$2:$OJ$901,65,MATCH($B$2&"|yN",Aux_puntos!$1:$1,0))),NA())
AC70: =IFERROR(IF(INDEX(Aux_puntos!$A$2:$OJ$901,66,MATCH($B$2&"|xK",Aux_puntos!$1:$1,0))="",NA(),INDEX(Aux_puntos!$A$2:$OJ$901,66,MATCH($B$2&"|xK",Aux_puntos!$1:$1,0))),NA()) | AD70: =IFERROR(IF(INDEX(Aux_puntos!$A$2:$OJ$901,66,MATCH($B$2&"|yK",Aux_puntos!$1:$1,0))="",NA(),INDEX(Aux_puntos!$A$2:$OJ$901,66,MATCH($B$2&"|yK",Aux_puntos!$1:$1,0))),NA()) | AE70: =IFERROR(IF(INDEX(Aux_puntos!$A$2:$OJ$901,66,MATCH($B$2&"|xC",Aux_puntos!$1:$1,0))="",NA(),INDEX(Aux_puntos!$A$2:$OJ$901,66,MATCH($B$2&"|xC",Aux_puntos!$1:$1,0))),NA()) | AF70: =IFERROR(IF(INDEX(Aux_puntos!$A$2:$OJ$901,66,MATCH($B$2&"|yC",Aux_puntos!$1:$1,0))="",NA(),INDEX(Aux_puntos!$A$2:$OJ$901,66,MATCH($B$2&"|yC",Aux_puntos!$1:$1,0))),NA()) | AG70: =IFERROR(IF(INDEX(Aux_puntos!$A$2:$OJ$901,66,MATCH($B$2&"|xI",Aux_puntos!$1:$1,0))="",NA(),INDEX(Aux_puntos!$A$2:$OJ$901,66,MATCH($B$2&"|xI",Aux_puntos!$1:$1,0))),NA()) | AH70: =IFERROR(IF(INDEX(Aux_puntos!$A$2:$OJ$901,66,MATCH($B$2&"|yI",Aux_puntos!$1:$1,0))="",NA(),INDEX(Aux_puntos!$A$2:$OJ$901,66,MATCH($B$2&"|yI",Aux_puntos!$1:$1,0))),NA()) | AI70: =IFERROR(IF(INDEX(Aux_puntos!$A$2:$OJ$901,66,MATCH($B$2&"|xN",Aux_puntos!$1:$1,0))="",NA(),INDEX(Aux_puntos!$A$2:$OJ$901,66,MATCH($B$2&"|xN",Aux_puntos!$1:$1,0))),NA()) | AJ70: =IFERROR(IF(INDEX(Aux_puntos!$A$2:$OJ$901,66,MATCH($B$2&"|yN",Aux_puntos!$1:$1,0))="",NA(),INDEX(Aux_puntos!$A$2:$OJ$901,66,MATCH($B$2&"|yN",Aux_puntos!$1:$1,0))),NA())
AC71: =IFERROR(IF(INDEX(Aux_puntos!$A$2:$OJ$901,67,MATCH($B$2&"|xK",Aux_puntos!$1:$1,0))="",NA(),INDEX(Aux_puntos!$A$2:$OJ$901,67,MATCH($B$2&"|xK",Aux_puntos!$1:$1,0))),NA()) | AD71: =IFERROR(IF(INDEX(Aux_puntos!$A$2:$OJ$901,67,MATCH($B$2&"|yK",Aux_puntos!$1:$1,0))="",NA(),INDEX(Aux_puntos!$A$2:$OJ$901,67,MATCH($B$2&"|yK",Aux_puntos!$1:$1,0))),NA()) | AE71: =IFERROR(IF(INDEX(Aux_puntos!$A$2:$OJ$901,67,MATCH($B$2&"|xC",Aux_puntos!$1:$1,0))="",NA(),INDEX(Aux_puntos!$A$2:$OJ$901,67,MATCH($B$2&"|xC",Aux_puntos!$1:$1,0))),NA()) | AF71: =IFERROR(IF(INDEX(Aux_puntos!$A$2:$OJ$901,67,MATCH($B$2&"|yC",Aux_puntos!$1:$1,0))="",NA(),INDEX(Aux_puntos!$A$2:$OJ$901,67,MATCH($B$2&"|yC",Aux_puntos!$1:$1,0))),NA()) | AG71: =IFERROR(IF(INDEX(Aux_puntos!$A$2:$OJ$901,67,MATCH($B$2&"|xI",Aux_puntos!$1:$1,0))="",NA(),INDEX(Aux_puntos!$A$2:$OJ$901,67,MATCH($B$2&"|xI",Aux_puntos!$1:$1,0))),NA()) | AH71: =IFERROR(IF(INDEX(Aux_puntos!$A$2:$OJ$901,67,MATCH($B$2&"|yI",Aux_puntos!$1:$1,0))="",NA(),INDEX(Aux_puntos!$A$2:$OJ$901,67,MATCH($B$2&"|yI",Aux_puntos!$1:$1,0))),NA()) | AI71: =IFERROR(IF(INDEX(Aux_puntos!$A$2:$OJ$901,67,MATCH($B$2&"|xN",Aux_puntos!$1:$1,0))="",NA(),INDEX(Aux_puntos!$A$2:$OJ$901,67,MATCH($B$2&"|xN",Aux_puntos!$1:$1,0))),NA()) | AJ71: =IFERROR(IF(INDEX(Aux_puntos!$A$2:$OJ$901,67,MATCH($B$2&"|yN",Aux_puntos!$1:$1,0))="",NA(),INDEX(Aux_puntos!$A$2:$OJ$901,67,MATCH($B$2&"|yN",Aux_puntos!$1:$1,0))),NA())
AC72: =IFERROR(IF(INDEX(Aux_puntos!$A$2:$OJ$901,68,MATCH($B$2&"|xK",Aux_puntos!$1:$1,0))="",NA(),INDEX(Aux_puntos!$A$2:$OJ$901,68,MATCH($B$2&"|xK",Aux_puntos!$1:$1,0))),NA()) | AD72: =IFERROR(IF(INDEX(Aux_puntos!$A$2:$OJ$901,68,MATCH($B$2&"|yK",Aux_puntos!$1:$1,0))="",NA(),INDEX(Aux_puntos!$A$2:$OJ$901,68,MATCH($B$2&"|yK",Aux_puntos!$1:$1,0))),NA()) | AE72: =IFERROR(IF(INDEX(Aux_puntos!$A$2:$OJ$901,68,MATCH($B$2&"|xC",Aux_puntos!$1:$1,0))="",NA(),INDEX(Aux_puntos!$A$2:$OJ$901,68,MATCH($B$2&"|xC",Aux_puntos!$1:$1,0))),NA()) | AF72: =IFERROR(IF(INDEX(Aux_puntos!$A$2:$OJ$901,68,MATCH($B$2&"|yC",Aux_puntos!$1:$1,0))="",NA(),INDEX(Aux_puntos!$A$2:$OJ$901,68,MATCH($B$2&"|yC",Aux_puntos!$1:$1,0))),NA()) | AG72: =IFERROR(IF(INDEX(Aux_puntos!$A$2:$OJ$901,68,MATCH($B$2&"|xI",Aux_puntos!$1:$1,0))="",NA(),INDEX(Aux_puntos!$A$2:$OJ$901,68,MATCH($B$2&"|xI",Aux_puntos!$1:$1,0))),NA()) | AH72: =IFERROR(IF(INDEX(Aux_puntos!$A$2:$OJ$901,68,MATCH($B$2&"|yI",Aux_puntos!$1:$1,0))="",NA(),INDEX(Aux_puntos!$A$2:$OJ$901,68,MATCH($B$2&"|yI",Aux_puntos!$1:$1,0))),NA()) | AI72: =IFERROR(IF(INDEX(Aux_puntos!$A$2:$OJ$901,68,MATCH($B$2&"|xN",Aux_puntos!$1:$1,0))="",NA(),INDEX(Aux_puntos!$A$2:$OJ$901,68,MATCH($B$2&"|xN",Aux_puntos!$1:$1,0))),NA()) | AJ72: =IFERROR(IF(INDEX(Aux_puntos!$A$2:$OJ$901,68,MATCH($B$2&"|yN",Aux_puntos!$1:$1,0))="",NA(),INDEX(Aux_puntos!$A$2:$OJ$901,68,MATCH($B$2&"|yN",Aux_puntos!$1:$1,0))),NA())
AC73: =IFERROR(IF(INDEX(Aux_puntos!$A$2:$OJ$901,69,MATCH($B$2&"|xK",Aux_puntos!$1:$1,0))="",NA(),INDEX(Aux_puntos!$A$2:$OJ$901,69,MATCH($B$2&"|xK",Aux_puntos!$1:$1,0))),NA()) | AD73: =IFERROR(IF(INDEX(Aux_puntos!$A$2:$OJ$901,69,MATCH($B$2&"|yK",Aux_puntos!$1:$1,0))="",NA(),INDEX(Aux_puntos!$A$2:$OJ$901,69,MATCH($B$2&"|yK",Aux_puntos!$1:$1,0))),NA()) | AE73: =IFERROR(IF(INDEX(Aux_puntos!$A$2:$OJ$901,69,MATCH($B$2&"|xC",Aux_puntos!$1:$1,0))="",NA(),INDEX(Aux_puntos!$A$2:$OJ$901,69,MATCH($B$2&"|xC",Aux_puntos!$1:$1,0))),NA()) | AF73: =IFERROR(IF(INDEX(Aux_puntos!$A$2:$OJ$901,69,MATCH($B$2&"|yC",Aux_puntos!$1:$1,0))="",NA(),INDEX(Aux_puntos!$A$2:$OJ$901,69,MATCH($B$2&"|yC",Aux_puntos!$1:$1,0))),NA()) | AG73: =IFERROR(IF(INDEX(Aux_puntos!$A$2:$OJ$901,69,MATCH($B$2&"|xI",Aux_puntos!$1:$1,0))="",NA(),INDEX(Aux_puntos!$A$2:$OJ$901,69,MATCH($B$2&"|xI",Aux_puntos!$1:$1,0))),NA()) | AH73: =IFERROR(IF(INDEX(Aux_puntos!$A$2:$OJ$901,69,MATCH($B$2&"|yI",Aux_puntos!$1:$1,0))="",NA(),INDEX(Aux_puntos!$A$2:$OJ$901,69,MATCH($B$2&"|yI",Aux_puntos!$1:$1,0))),NA()) | AI73: =IFERROR(IF(INDEX(Aux_puntos!$A$2:$OJ$901,69,MATCH($B$2&"|xN",Aux_puntos!$1:$1,0))="",NA(),INDEX(Aux_puntos!$A$2:$OJ$901,69,MATCH($B$2&"|xN",Aux_puntos!$1:$1,0))),NA()) | AJ73: =IFERROR(IF(INDEX(Aux_puntos!$A$2:$OJ$901,69,MATCH($B$2&"|yN",Aux_puntos!$1:$1,0))="",NA(),INDEX(Aux_puntos!$A$2:$OJ$901,69,MATCH($B$2&"|yN",Aux_puntos!$1:$1,0))),NA())
AC74: =IFERROR(IF(INDEX(Aux_puntos!$A$2:$OJ$901,70,MATCH($B$2&"|xK",Aux_puntos!$1:$1,0))="",NA(),INDEX(Aux_puntos!$A$2:$OJ$901,70,MATCH($B$2&"|xK",Aux_puntos!$1:$1,0))),NA()) | AD74: =IFERROR(IF(INDEX(Aux_puntos!$A$2:$OJ$901,70,MATCH($B$2&"|yK",Aux_puntos!$1:$1,0))="",NA(),INDEX(Aux_puntos!$A$2:$OJ$901,70,MATCH($B$2&"|yK",Aux_puntos!$1:$1,0))),NA()) | AE74: =IFERROR(IF(INDEX(Aux_puntos!$A$2:$OJ$901,70,MATCH($B$2&"|xC",Aux_puntos!$1:$1,0))="",NA(),INDEX(Aux_puntos!$A$2:$OJ$901,70,MATCH($B$2&"|xC",Aux_puntos!$1:$1,0))),NA()) | AF74: =IFERROR(IF(INDEX(Aux_puntos!$A$2:$OJ$901,70,MATCH($B$2&"|yC",Aux_puntos!$1:$1,0))="",NA(),INDEX(Aux_puntos!$A$2:$OJ$901,70,MATCH($B$2&"|yC",Aux_puntos!$1:$1,0))),NA()) | AG74: =IFERROR(IF(INDEX(Aux_puntos!$A$2:$OJ$901,70,MATCH($B$2&"|xI",Aux_puntos!$1:$1,0))="",NA(),INDEX(Aux_puntos!$A$2:$OJ$901,70,MATCH($B$2&"|xI",Aux_puntos!$1:$1,0))),NA()) | AH74: =IFERROR(IF(INDEX(Aux_puntos!$A$2:$OJ$901,70,MATCH($B$2&"|yI",Aux_puntos!$1:$1,0))="",NA(),INDEX(Aux_puntos!$A$2:$OJ$901,70,MATCH($B$2&"|yI",Aux_puntos!$1:$1,0))),NA()) | AI74: =IFERROR(IF(INDEX(Aux_puntos!$A$2:$OJ$901,70,MATCH($B$2&"|xN",Aux_puntos!$1:$1,0))="",NA(),INDEX(Aux_puntos!$A$2:$OJ$901,70,MATCH($B$2&"|xN",Aux_puntos!$1:$1,0))),NA()) | AJ74: =IFERROR(IF(INDEX(Aux_puntos!$A$2:$OJ$901,70,MATCH($B$2&"|yN",Aux_puntos!$1:$1,0))="",NA(),INDEX(Aux_puntos!$A$2:$OJ$901,70,MATCH($B$2&"|yN",Aux_puntos!$1:$1,0))),NA())
AC75: =IFERROR(IF(INDEX(Aux_puntos!$A$2:$OJ$901,71,MATCH($B$2&"|xK",Aux_puntos!$1:$1,0))="",NA(),INDEX(Aux_puntos!$A$2:$OJ$901,71,MATCH($B$2&"|xK",Aux_puntos!$1:$1,0))),NA()) | AD75: =IFERROR(IF(INDEX(Aux_puntos!$A$2:$OJ$901,71,MATCH($B$2&"|yK",Aux_puntos!$1:$1,0))="",NA(),INDEX(Aux_puntos!$A$2:$OJ$901,71,MATCH($B$2&"|yK",Aux_puntos!$1:$1,0))),NA()) | AE75: =IFERROR(IF(INDEX(Aux_puntos!$A$2:$OJ$901,71,MATCH($B$2&"|xC",Aux_puntos!$1:$1,0))="",NA(),INDEX(Aux_puntos!$A$2:$OJ$901,71,MATCH($B$2&"|xC",Aux_puntos!$1:$1,0))),NA()) | AF75: =IFERROR(IF(INDEX(Aux_puntos!$A$2:$OJ$901,71,MATCH($B$2&"|yC",Aux_puntos!$1:$1,0))="",NA(),INDEX(Aux_puntos!$A$2:$OJ$901,71,MATCH($B$2&"|yC",Aux_puntos!$1:$1,0))),NA()) | AG75: =IFERROR(IF(INDEX(Aux_puntos!$A$2:$OJ$901,71,MATCH($B$2&"|xI",Aux_puntos!$1:$1,0))="",NA(),INDEX(Aux_puntos!$A$2:$OJ$901,71,MATCH($B$2&"|xI",Aux_puntos!$1:$1,0))),NA()) | AH75: =IFERROR(IF(INDEX(Aux_puntos!$A$2:$OJ$901,71,MATCH($B$2&"|yI",Aux_puntos!$1:$1,0))="",NA(),INDEX(Aux_puntos!$A$2:$OJ$901,71,MATCH($B$2&"|yI",Aux_puntos!$1:$1,0))),NA()) | AI75: =IFERROR(IF(INDEX(Aux_puntos!$A$2:$OJ$901,71,MATCH($B$2&"|xN",Aux_puntos!$1:$1,0))="",NA(),INDEX(Aux_puntos!$A$2:$OJ$901,71,MATCH($B$2&"|xN",Aux_puntos!$1:$1,0))),NA()) | AJ75: =IFERROR(IF(INDEX(Aux_puntos!$A$2:$OJ$901,71,MATCH($B$2&"|yN",Aux_puntos!$1:$1,0))="",NA(),INDEX(Aux_puntos!$A$2:$OJ$901,71,MATCH($B$2&"|yN",Aux_puntos!$1:$1,0))),NA())
AC76: =IFERROR(IF(INDEX(Aux_puntos!$A$2:$OJ$901,72,MATCH($B$2&"|xK",Aux_puntos!$1:$1,0))="",NA(),INDEX(Aux_puntos!$A$2:$OJ$901,72,MATCH($B$2&"|xK",Aux_puntos!$1:$1,0))),NA()) | AD76: =IFERROR(IF(INDEX(Aux_puntos!$A$2:$OJ$901,72,MATCH($B$2&"|yK",Aux_puntos!$1:$1,0))="",NA(),INDEX(Aux_puntos!$A$2:$OJ$901,72,MATCH($B$2&"|yK",Aux_puntos!$1:$1,0))),NA()) | AE76: =IFERROR(IF(INDEX(Aux_puntos!$A$2:$OJ$901,72,MATCH($B$2&"|xC",Aux_puntos!$1:$1,0))="",NA(),INDEX(Aux_puntos!$A$2:$OJ$901,72,MATCH($B$2&"|xC",Aux_puntos!$1:$1,0))),NA()) | AF76: =IFERROR(IF(INDEX(Aux_puntos!$A$2:$OJ$901,72,MATCH($B$2&"|yC",Aux_puntos!$1:$1,0))="",NA(),INDEX(Aux_puntos!$A$2:$OJ$901,72,MATCH($B$2&"|yC",Aux_puntos!$1:$1,0))),NA()) | AG76: =IFERROR(IF(INDEX(Aux_puntos!$A$2:$OJ$901,72,MATCH($B$2&"|xI",Aux_puntos!$1:$1,0))="",NA(),INDEX(Aux_puntos!$A$2:$OJ$901,72,MATCH($B$2&"|xI",Aux_puntos!$1:$1,0))),NA()) | AH76: =IFERROR(IF(INDEX(Aux_puntos!$A$2:$OJ$901,72,MATCH($B$2&"|yI",Aux_puntos!$1:$1,0))="",NA(),INDEX(Aux_puntos!$A$2:$OJ$901,72,MATCH($B$2&"|yI",Aux_puntos!$1:$1,0))),NA()) | AI76: =IFERROR(IF(INDEX(Aux_puntos!$A$2:$OJ$901,72,MATCH($B$2&"|xN",Aux_puntos!$1:$1,0))="",NA(),INDEX(Aux_puntos!$A$2:$OJ$901,72,MATCH($B$2&"|xN",Aux_puntos!$1:$1,0))),NA()) | AJ76: =IFERROR(IF(INDEX(Aux_puntos!$A$2:$OJ$901,72,MATCH($B$2&"|yN",Aux_puntos!$1:$1,0))="",NA(),INDEX(Aux_puntos!$A$2:$OJ$901,72,MATCH($B$2&"|yN",Aux_puntos!$1:$1,0))),NA())
AC77: =IFERROR(IF(INDEX(Aux_puntos!$A$2:$OJ$901,73,MATCH($B$2&"|xK",Aux_puntos!$1:$1,0))="",NA(),INDEX(Aux_puntos!$A$2:$OJ$901,73,MATCH($B$2&"|xK",Aux_puntos!$1:$1,0))),NA()) | AD77: =IFERROR(IF(INDEX(Aux_puntos!$A$2:$OJ$901,73,MATCH($B$2&"|yK",Aux_puntos!$1:$1,0))="",NA(),INDEX(Aux_puntos!$A$2:$OJ$901,73,MATCH($B$2&"|yK",Aux_puntos!$1:$1,0))),NA()) | AE77: =IFERROR(IF(INDEX(Aux_puntos!$A$2:$OJ$901,73,MATCH($B$2&"|xC",Aux_puntos!$1:$1,0))="",NA(),INDEX(Aux_puntos!$A$2:$OJ$901,73,MATCH($B$2&"|xC",Aux_puntos!$1:$1,0))),NA()) | AF77: =IFERROR(IF(INDEX(Aux_puntos!$A$2:$OJ$901,73,MATCH($B$2&"|yC",Aux_puntos!$1:$1,0))="",NA(),INDEX(Aux_puntos!$A$2:$OJ$901,73,MATCH($B$2&"|yC",Aux_puntos!$1:$1,0))),NA()) | AG77: =IFERROR(IF(INDEX(Aux_puntos!$A$2:$OJ$901,73,MATCH($B$2&"|xI",Aux_puntos!$1:$1,0))="",NA(),INDEX(Aux_puntos!$A$2:$OJ$901,73,MATCH($B$2&"|xI",Aux_puntos!$1:$1,0))),NA()) | AH77: =IFERROR(IF(INDEX(Aux_puntos!$A$2:$OJ$901,73,MATCH($B$2&"|yI",Aux_puntos!$1:$1,0))="",NA(),INDEX(Aux_puntos!$A$2:$OJ$901,73,MATCH($B$2&"|yI",Aux_puntos!$1:$1,0))),NA()) | AI77: =IFERROR(IF(INDEX(Aux_puntos!$A$2:$OJ$901,73,MATCH($B$2&"|xN",Aux_puntos!$1:$1,0))="",NA(),INDEX(Aux_puntos!$A$2:$OJ$901,73,MATCH($B$2&"|xN",Aux_puntos!$1:$1,0))),NA()) | AJ77: =IFERROR(IF(INDEX(Aux_puntos!$A$2:$OJ$901,73,MATCH($B$2&"|yN",Aux_puntos!$1:$1,0))="",NA(),INDEX(Aux_puntos!$A$2:$OJ$901,73,MATCH($B$2&"|yN",Aux_puntos!$1:$1,0))),NA())
AC78: =IFERROR(IF(INDEX(Aux_puntos!$A$2:$OJ$901,74,MATCH($B$2&"|xK",Aux_puntos!$1:$1,0))="",NA(),INDEX(Aux_puntos!$A$2:$OJ$901,74,MATCH($B$2&"|xK",Aux_puntos!$1:$1,0))),NA()) | AD78: =IFERROR(IF(INDEX(Aux_puntos!$A$2:$OJ$901,74,MATCH($B$2&"|yK",Aux_puntos!$1:$1,0))="",NA(),INDEX(Aux_puntos!$A$2:$OJ$901,74,MATCH($B$2&"|yK",Aux_puntos!$1:$1,0))),NA()) | AE78: =IFERROR(IF(INDEX(Aux_puntos!$A$2:$OJ$901,74,MATCH($B$2&"|xC",Aux_puntos!$1:$1,0))="",NA(),INDEX(Aux_puntos!$A$2:$OJ$901,74,MATCH($B$2&"|xC",Aux_puntos!$1:$1,0))),NA()) | AF78: =IFERROR(IF(INDEX(Aux_puntos!$A$2:$OJ$901,74,MATCH($B$2&"|yC",Aux_puntos!$1:$1,0))="",NA(),INDEX(Aux_puntos!$A$2:$OJ$901,74,MATCH($B$2&"|yC",Aux_puntos!$1:$1,0))),NA()) | AG78: =IFERROR(IF(INDEX(Aux_puntos!$A$2:$OJ$901,74,MATCH($B$2&"|xI",Aux_puntos!$1:$1,0))="",NA(),INDEX(Aux_puntos!$A$2:$OJ$901,74,MATCH($B$2&"|xI",Aux_puntos!$1:$1,0))),NA()) | AH78: =IFERROR(IF(INDEX(Aux_puntos!$A$2:$OJ$901,74,MATCH($B$2&"|yI",Aux_puntos!$1:$1,0))="",NA(),INDEX(Aux_puntos!$A$2:$OJ$901,74,MATCH($B$2&"|yI",Aux_puntos!$1:$1,0))),NA()) | AI78: =IFERROR(IF(INDEX(Aux_puntos!$A$2:$OJ$901,74,MATCH($B$2&"|xN",Aux_puntos!$1:$1,0))="",NA(),INDEX(Aux_puntos!$A$2:$OJ$901,74,MATCH($B$2&"|xN",Aux_puntos!$1:$1,0))),NA()) | AJ78: =IFERROR(IF(INDEX(Aux_puntos!$A$2:$OJ$901,74,MATCH($B$2&"|yN",Aux_puntos!$1:$1,0))="",NA(),INDEX(Aux_puntos!$A$2:$OJ$901,74,MATCH($B$2&"|yN",Aux_puntos!$1:$1,0))),NA())
AC79: =IFERROR(IF(INDEX(Aux_puntos!$A$2:$OJ$901,75,MATCH($B$2&"|xK",Aux_puntos!$1:$1,0))="",NA(),INDEX(Aux_puntos!$A$2:$OJ$901,75,MATCH($B$2&"|xK",Aux_puntos!$1:$1,0))),NA()) | AD79: =IFERROR(IF(INDEX(Aux_puntos!$A$2:$OJ$901,75,MATCH($B$2&"|yK",Aux_puntos!$1:$1,0))="",NA(),INDEX(Aux_puntos!$A$2:$OJ$901,75,MATCH($B$2&"|yK",Aux_puntos!$1:$1,0))),NA()) | AE79: =IFERROR(IF(INDEX(Aux_puntos!$A$2:$OJ$901,75,MATCH($B$2&"|xC",Aux_puntos!$1:$1,0))="",NA(),INDEX(Aux_puntos!$A$2:$OJ$901,75,MATCH($B$2&"|xC",Aux_puntos!$1:$1,0))),NA()) | AF79: =IFERROR(IF(INDEX(Aux_puntos!$A$2:$OJ$901,75,MATCH($B$2&"|yC",Aux_puntos!$1:$1,0))="",NA(),INDEX(Aux_puntos!$A$2:$OJ$901,75,MATCH($B$2&"|yC",Aux_puntos!$1:$1,0))),NA()) | AG79: =IFERROR(IF(INDEX(Aux_puntos!$A$2:$OJ$901,75,MATCH($B$2&"|xI",Aux_puntos!$1:$1,0))="",NA(),INDEX(Aux_puntos!$A$2:$OJ$901,75,MATCH($B$2&"|xI",Aux_puntos!$1:$1,0))),NA()) | AH79: =IFERROR(IF(INDEX(Aux_puntos!$A$2:$OJ$901,75,MATCH($B$2&"|yI",Aux_puntos!$1:$1,0))="",NA(),INDEX(Aux_puntos!$A$2:$OJ$901,75,MATCH($B$2&"|yI",Aux_puntos!$1:$1,0))),NA()) | AI79: =IFERROR(IF(INDEX(Aux_puntos!$A$2:$OJ$901,75,MATCH($B$2&"|xN",Aux_puntos!$1:$1,0))="",NA(),INDEX(Aux_puntos!$A$2:$OJ$901,75,MATCH($B$2&"|xN",Aux_puntos!$1:$1,0))),NA()) | AJ79: =IFERROR(IF(INDEX(Aux_puntos!$A$2:$OJ$901,75,MATCH($B$2&"|yN",Aux_puntos!$1:$1,0))="",NA(),INDEX(Aux_puntos!$A$2:$OJ$901,75,MATCH($B$2&"|yN",Aux_puntos!$1:$1,0))),NA())
AC80: =IFERROR(IF(INDEX(Aux_puntos!$A$2:$OJ$901,76,MATCH($B$2&"|xK",Aux_puntos!$1:$1,0))="",NA(),INDEX(Aux_puntos!$A$2:$OJ$901,76,MATCH($B$2&"|xK",Aux_puntos!$1:$1,0))),NA()) | AD80: =IFERROR(IF(INDEX(Aux_puntos!$A$2:$OJ$901,76,MATCH($B$2&"|yK",Aux_puntos!$1:$1,0))="",NA(),INDEX(Aux_puntos!$A$2:$OJ$901,76,MATCH($B$2&"|yK",Aux_puntos!$1:$1,0))),NA()) | AE80: =IFERROR(IF(INDEX(Aux_puntos!$A$2:$OJ$901,76,MATCH($B$2&"|xC",Aux_puntos!$1:$1,0))="",NA(),INDEX(Aux_puntos!$A$2:$OJ$901,76,MATCH($B$2&"|xC",Aux_puntos!$1:$1,0))),NA()) | AF80: =IFERROR(IF(INDEX(Aux_puntos!$A$2:$OJ$901,76,MATCH($B$2&"|yC",Aux_puntos!$1:$1,0))="",NA(),INDEX(Aux_puntos!$A$2:$OJ$901,76,MATCH($B$2&"|yC",Aux_puntos!$1:$1,0))),NA()) | AG80: =IFERROR(IF(INDEX(Aux_puntos!$A$2:$OJ$901,76,MATCH($B$2&"|xI",Aux_puntos!$1:$1,0))="",NA(),INDEX(Aux_puntos!$A$2:$OJ$901,76,MATCH($B$2&"|xI",Aux_puntos!$1:$1,0))),NA()) | AH80: =IFERROR(IF(INDEX(Aux_puntos!$A$2:$OJ$901,76,MATCH($B$2&"|yI",Aux_puntos!$1:$1,0))="",NA(),INDEX(Aux_puntos!$A$2:$OJ$901,76,MATCH($B$2&"|yI",Aux_puntos!$1:$1,0))),NA()) | AI80: =IFERROR(IF(INDEX(Aux_puntos!$A$2:$OJ$901,76,MATCH($B$2&"|xN",Aux_puntos!$1:$1,0))="",NA(),INDEX(Aux_puntos!$A$2:$OJ$901,76,MATCH($B$2&"|xN",Aux_puntos!$1:$1,0))),NA()) | AJ80: =IFERROR(IF(INDEX(Aux_puntos!$A$2:$OJ$901,76,MATCH($B$2&"|yN",Aux_puntos!$1:$1,0))="",NA(),INDEX(Aux_puntos!$A$2:$OJ$901,76,MATCH($B$2&"|yN",Aux_puntos!$1:$1,0))),NA())
AC81: =IFERROR(IF(INDEX(Aux_puntos!$A$2:$OJ$901,77,MATCH($B$2&"|xK",Aux_puntos!$1:$1,0))="",NA(),INDEX(Aux_puntos!$A$2:$OJ$901,77,MATCH($B$2&"|xK",Aux_puntos!$1:$1,0))),NA()) | AD81: =IFERROR(IF(INDEX(Aux_puntos!$A$2:$OJ$901,77,MATCH($B$2&"|yK",Aux_puntos!$1:$1,0))="",NA(),INDEX(Aux_puntos!$A$2:$OJ$901,77,MATCH($B$2&"|yK",Aux_puntos!$1:$1,0))),NA()) | AE81: =IFERROR(IF(INDEX(Aux_puntos!$A$2:$OJ$901,77,MATCH($B$2&"|xC",Aux_puntos!$1:$1,0))="",NA(),INDEX(Aux_puntos!$A$2:$OJ$901,77,MATCH($B$2&"|xC",Aux_puntos!$1:$1,0))),NA()) | AF81: =IFERROR(IF(INDEX(Aux_puntos!$A$2:$OJ$901,77,MATCH($B$2&"|yC",Aux_puntos!$1:$1,0))="",NA(),INDEX(Aux_puntos!$A$2:$OJ$901,77,MATCH($B$2&"|yC",Aux_puntos!$1:$1,0))),NA()) | AG81: =IFERROR(IF(INDEX(Aux_puntos!$A$2:$OJ$901,77,MATCH($B$2&"|xI",Aux_puntos!$1:$1,0))="",NA(),INDEX(Aux_puntos!$A$2:$OJ$901,77,MATCH($B$2&"|xI",Aux_puntos!$1:$1,0))),NA()) | AH81: =IFERROR(IF(INDEX(Aux_puntos!$A$2:$OJ$901,77,MATCH($B$2&"|yI",Aux_puntos!$1:$1,0))="",NA(),INDEX(Aux_puntos!$A$2:$OJ$901,77,MATCH($B$2&"|yI",Aux_puntos!$1:$1,0))),NA()) | AI81: =IFERROR(IF(INDEX(Aux_puntos!$A$2:$OJ$901,77,MATCH($B$2&"|xN",Aux_puntos!$1:$1,0))="",NA(),INDEX(Aux_puntos!$A$2:$OJ$901,77,MATCH($B$2&"|xN",Aux_puntos!$1:$1,0))),NA()) | AJ81: =IFERROR(IF(INDEX(Aux_puntos!$A$2:$OJ$901,77,MATCH($B$2&"|yN",Aux_puntos!$1:$1,0))="",NA(),INDEX(Aux_puntos!$A$2:$OJ$901,77,MATCH($B$2&"|yN",Aux_puntos!$1:$1,0))),NA())
AC82: =IFERROR(IF(INDEX(Aux_puntos!$A$2:$OJ$901,78,MATCH($B$2&"|xK",Aux_puntos!$1:$1,0))="",NA(),INDEX(Aux_puntos!$A$2:$OJ$901,78,MATCH($B$2&"|xK",Aux_puntos!$1:$1,0))),NA()) | AD82: =IFERROR(IF(INDEX(Aux_puntos!$A$2:$OJ$901,78,MATCH($B$2&"|yK",Aux_puntos!$1:$1,0))="",NA(),INDEX(Aux_puntos!$A$2:$OJ$901,78,MATCH($B$2&"|yK",Aux_puntos!$1:$1,0))),NA()) | AE82: =IFERROR(IF(INDEX(Aux_puntos!$A$2:$OJ$901,78,MATCH($B$2&"|xC",Aux_puntos!$1:$1,0))="",NA(),INDEX(Aux_puntos!$A$2:$OJ$901,78,MATCH($B$2&"|xC",Aux_puntos!$1:$1,0))),NA()) | AF82: =IFERROR(IF(INDEX(Aux_puntos!$A$2:$OJ$901,78,MATCH($B$2&"|yC",Aux_puntos!$1:$1,0))="",NA(),INDEX(Aux_puntos!$A$2:$OJ$901,78,MATCH($B$2&"|yC",Aux_puntos!$1:$1,0))),NA()) | AG82: =IFERROR(IF(INDEX(Aux_puntos!$A$2:$OJ$901,78,MATCH($B$2&"|xI",Aux_puntos!$1:$1,0))="",NA(),INDEX(Aux_puntos!$A$2:$OJ$901,78,MATCH($B$2&"|xI",Aux_puntos!$1:$1,0))),NA()) | AH82: =IFERROR(IF(INDEX(Aux_puntos!$A$2:$OJ$901,78,MATCH($B$2&"|yI",Aux_puntos!$1:$1,0))="",NA(),INDEX(Aux_puntos!$A$2:$OJ$901,78,MATCH($B$2&"|yI",Aux_puntos!$1:$1,0))),NA()) | AI82: =IFERROR(IF(INDEX(Aux_puntos!$A$2:$OJ$901,78,MATCH($B$2&"|xN",Aux_puntos!$1:$1,0))="",NA(),INDEX(Aux_puntos!$A$2:$OJ$901,78,MATCH($B$2&"|xN",Aux_puntos!$1:$1,0))),NA()) | AJ82: =IFERROR(IF(INDEX(Aux_puntos!$A$2:$OJ$901,78,MATCH($B$2&"|yN",Aux_puntos!$1:$1,0))="",NA(),INDEX(Aux_puntos!$A$2:$OJ$901,78,MATCH($B$2&"|yN",Aux_puntos!$1:$1,0))),NA())
AC83: =IFERROR(IF(INDEX(Aux_puntos!$A$2:$OJ$901,79,MATCH($B$2&"|xK",Aux_puntos!$1:$1,0))="",NA(),INDEX(Aux_puntos!$A$2:$OJ$901,79,MATCH($B$2&"|xK",Aux_puntos!$1:$1,0))),NA()) | AD83: =IFERROR(IF(INDEX(Aux_puntos!$A$2:$OJ$901,79,MATCH($B$2&"|yK",Aux_puntos!$1:$1,0))="",NA(),INDEX(Aux_puntos!$A$2:$OJ$901,79,MATCH($B$2&"|yK",Aux_puntos!$1:$1,0))),NA()) | AE83: =IFERROR(IF(INDEX(Aux_puntos!$A$2:$OJ$901,79,MATCH($B$2&"|xC",Aux_puntos!$1:$1,0))="",NA(),INDEX(Aux_puntos!$A$2:$OJ$901,79,MATCH($B$2&"|xC",Aux_puntos!$1:$1,0))),NA()) | AF83: =IFERROR(IF(INDEX(Aux_puntos!$A$2:$OJ$901,79,MATCH($B$2&"|yC",Aux_puntos!$1:$1,0))="",NA(),INDEX(Aux_puntos!$A$2:$OJ$901,79,MATCH($B$2&"|yC",Aux_puntos!$1:$1,0))),NA()) | AG83: =IFERROR(IF(INDEX(Aux_puntos!$A$2:$OJ$901,79,MATCH($B$2&"|xI",Aux_puntos!$1:$1,0))="",NA(),INDEX(Aux_puntos!$A$2:$OJ$901,79,MATCH($B$2&"|xI",Aux_puntos!$1:$1,0))),NA()) | AH83: =IFERROR(IF(INDEX(Aux_puntos!$A$2:$OJ$901,79,MATCH($B$2&"|yI",Aux_puntos!$1:$1,0))="",NA(),INDEX(Aux_puntos!$A$2:$OJ$901,79,MATCH($B$2&"|yI",Aux_puntos!$1:$1,0))),NA()) | AI83: =IFERROR(IF(INDEX(Aux_puntos!$A$2:$OJ$901,79,MATCH($B$2&"|xN",Aux_puntos!$1:$1,0))="",NA(),INDEX(Aux_puntos!$A$2:$OJ$901,79,MATCH($B$2&"|xN",Aux_puntos!$1:$1,0))),NA()) | AJ83: =IFERROR(IF(INDEX(Aux_puntos!$A$2:$OJ$901,79,MATCH($B$2&"|yN",Aux_puntos!$1:$1,0))="",NA(),INDEX(Aux_puntos!$A$2:$OJ$901,79,MATCH($B$2&"|yN",Aux_puntos!$1:$1,0))),NA())
AC84: =IFERROR(IF(INDEX(Aux_puntos!$A$2:$OJ$901,80,MATCH($B$2&"|xK",Aux_puntos!$1:$1,0))="",NA(),INDEX(Aux_puntos!$A$2:$OJ$901,80,MATCH($B$2&"|xK",Aux_puntos!$1:$1,0))),NA()) | AD84: =IFERROR(IF(INDEX(Aux_puntos!$A$2:$OJ$901,80,MATCH($B$2&"|yK",Aux_puntos!$1:$1,0))="",NA(),INDEX(Aux_puntos!$A$2:$OJ$901,80,MATCH($B$2&"|yK",Aux_puntos!$1:$1,0))),NA()) | AE84: =IFERROR(IF(INDEX(Aux_puntos!$A$2:$OJ$901,80,MATCH($B$2&"|xC",Aux_puntos!$1:$1,0))="",NA(),INDEX(Aux_puntos!$A$2:$OJ$901,80,MATCH($B$2&"|xC",Aux_puntos!$1:$1,0))),NA()) | AF84: =IFERROR(IF(INDEX(Aux_puntos!$A$2:$OJ$901,80,MATCH($B$2&"|yC",Aux_puntos!$1:$1,0))="",NA(),INDEX(Aux_puntos!$A$2:$OJ$901,80,MATCH($B$2&"|yC",Aux_puntos!$1:$1,0))),NA()) | AG84: =IFERROR(IF(INDEX(Aux_puntos!$A$2:$OJ$901,80,MATCH($B$2&"|xI",Aux_puntos!$1:$1,0))="",NA(),INDEX(Aux_puntos!$A$2:$OJ$901,80,MATCH($B$2&"|xI",Aux_puntos!$1:$1,0))),NA()) | AH84: =IFERROR(IF(INDEX(Aux_puntos!$A$2:$OJ$901,80,MATCH($B$2&"|yI",Aux_puntos!$1:$1,0))="",NA(),INDEX(Aux_puntos!$A$2:$OJ$901,80,MATCH($B$2&"|yI",Aux_puntos!$1:$1,0))),NA()) | AI84: =IFERROR(IF(INDEX(Aux_puntos!$A$2:$OJ$901,80,MATCH($B$2&"|xN",Aux_puntos!$1:$1,0))="",NA(),INDEX(Aux_puntos!$A$2:$OJ$901,80,MATCH($B$2&"|xN",Aux_puntos!$1:$1,0))),NA()) | AJ84: =IFERROR(IF(INDEX(Aux_puntos!$A$2:$OJ$901,80,MATCH($B$2&"|yN",Aux_puntos!$1:$1,0))="",NA(),INDEX(Aux_puntos!$A$2:$OJ$901,80,MATCH($B$2&"|yN",Aux_puntos!$1:$1,0))),NA())
AC85: =IFERROR(IF(INDEX(Aux_puntos!$A$2:$OJ$901,81,MATCH($B$2&"|xK",Aux_puntos!$1:$1,0))="",NA(),INDEX(Aux_puntos!$A$2:$OJ$901,81,MATCH($B$2&"|xK",Aux_puntos!$1:$1,0))),NA()) | AD85: =IFERROR(IF(INDEX(Aux_puntos!$A$2:$OJ$901,81,MATCH($B$2&"|yK",Aux_puntos!$1:$1,0))="",NA(),INDEX(Aux_puntos!$A$2:$OJ$901,81,MATCH($B$2&"|yK",Aux_puntos!$1:$1,0))),NA()) | AE85: =IFERROR(IF(INDEX(Aux_puntos!$A$2:$OJ$901,81,MATCH($B$2&"|xC",Aux_puntos!$1:$1,0))="",NA(),INDEX(Aux_puntos!$A$2:$OJ$901,81,MATCH($B$2&"|xC",Aux_puntos!$1:$1,0))),NA()) | AF85: =IFERROR(IF(INDEX(Aux_puntos!$A$2:$OJ$901,81,MATCH($B$2&"|yC",Aux_puntos!$1:$1,0))="",NA(),INDEX(Aux_puntos!$A$2:$OJ$901,81,MATCH($B$2&"|yC",Aux_puntos!$1:$1,0))),NA()) | AG85: =IFERROR(IF(INDEX(Aux_puntos!$A$2:$OJ$901,81,MATCH($B$2&"|xI",Aux_puntos!$1:$1,0))="",NA(),INDEX(Aux_puntos!$A$2:$OJ$901,81,MATCH($B$2&"|xI",Aux_puntos!$1:$1,0))),NA()) | AH85: =IFERROR(IF(INDEX(Aux_puntos!$A$2:$OJ$901,81,MATCH($B$2&"|yI",Aux_puntos!$1:$1,0))="",NA(),INDEX(Aux_puntos!$A$2:$OJ$901,81,MATCH($B$2&"|yI",Aux_puntos!$1:$1,0))),NA()) | AI85: =IFERROR(IF(INDEX(Aux_puntos!$A$2:$OJ$901,81,MATCH($B$2&"|xN",Aux_puntos!$1:$1,0))="",NA(),INDEX(Aux_puntos!$A$2:$OJ$901,81,MATCH($B$2&"|xN",Aux_puntos!$1:$1,0))),NA()) | AJ85: =IFERROR(IF(INDEX(Aux_puntos!$A$2:$OJ$901,81,MATCH($B$2&"|yN",Aux_puntos!$1:$1,0))="",NA(),INDEX(Aux_puntos!$A$2:$OJ$901,81,MATCH($B$2&"|yN",Aux_puntos!$1:$1,0))),NA())
AC86: =IFERROR(IF(INDEX(Aux_puntos!$A$2:$OJ$901,82,MATCH($B$2&"|xK",Aux_puntos!$1:$1,0))="",NA(),INDEX(Aux_puntos!$A$2:$OJ$901,82,MATCH($B$2&"|xK",Aux_puntos!$1:$1,0))),NA()) | AD86: =IFERROR(IF(INDEX(Aux_puntos!$A$2:$OJ$901,82,MATCH($B$2&"|yK",Aux_puntos!$1:$1,0))="",NA(),INDEX(Aux_puntos!$A$2:$OJ$901,82,MATCH($B$2&"|yK",Aux_puntos!$1:$1,0))),NA()) | AE86: =IFERROR(IF(INDEX(Aux_puntos!$A$2:$OJ$901,82,MATCH($B$2&"|xC",Aux_puntos!$1:$1,0))="",NA(),INDEX(Aux_puntos!$A$2:$OJ$901,82,MATCH($B$2&"|xC",Aux_puntos!$1:$1,0))),NA()) | AF86: =IFERROR(IF(INDEX(Aux_puntos!$A$2:$OJ$901,82,MATCH($B$2&"|yC",Aux_puntos!$1:$1,0))="",NA(),INDEX(Aux_puntos!$A$2:$OJ$901,82,MATCH($B$2&"|yC",Aux_puntos!$1:$1,0))),NA()) | AG86: =IFERROR(IF(INDEX(Aux_puntos!$A$2:$OJ$901,82,MATCH($B$2&"|xI",Aux_puntos!$1:$1,0))="",NA(),INDEX(Aux_puntos!$A$2:$OJ$901,82,MATCH($B$2&"|xI",Aux_puntos!$1:$1,0))),NA()) | AH86: =IFERROR(IF(INDEX(Aux_puntos!$A$2:$OJ$901,82,MATCH($B$2&"|yI",Aux_puntos!$1:$1,0))="",NA(),INDEX(Aux_puntos!$A$2:$OJ$901,82,MATCH($B$2&"|yI",Aux_puntos!$1:$1,0))),NA()) | AI86: =IFERROR(IF(INDEX(Aux_puntos!$A$2:$OJ$901,82,MATCH($B$2&"|xN",Aux_puntos!$1:$1,0))="",NA(),INDEX(Aux_puntos!$A$2:$OJ$901,82,MATCH($B$2&"|xN",Aux_puntos!$1:$1,0))),NA()) | AJ86: =IFERROR(IF(INDEX(Aux_puntos!$A$2:$OJ$901,82,MATCH($B$2&"|yN",Aux_puntos!$1:$1,0))="",NA(),INDEX(Aux_puntos!$A$2:$OJ$901,82,MATCH($B$2&"|yN",Aux_puntos!$1:$1,0))),NA())
AC87: =IFERROR(IF(INDEX(Aux_puntos!$A$2:$OJ$901,83,MATCH($B$2&"|xK",Aux_puntos!$1:$1,0))="",NA(),INDEX(Aux_puntos!$A$2:$OJ$901,83,MATCH($B$2&"|xK",Aux_puntos!$1:$1,0))),NA()) | AD87: =IFERROR(IF(INDEX(Aux_puntos!$A$2:$OJ$901,83,MATCH($B$2&"|yK",Aux_puntos!$1:$1,0))="",NA(),INDEX(Aux_puntos!$A$2:$OJ$901,83,MATCH($B$2&"|yK",Aux_puntos!$1:$1,0))),NA()) | AE87: =IFERROR(IF(INDEX(Aux_puntos!$A$2:$OJ$901,83,MATCH($B$2&"|xC",Aux_puntos!$1:$1,0))="",NA(),INDEX(Aux_puntos!$A$2:$OJ$901,83,MATCH($B$2&"|xC",Aux_puntos!$1:$1,0))),NA()) | AF87: =IFERROR(IF(INDEX(Aux_puntos!$A$2:$OJ$901,83,MATCH($B$2&"|yC",Aux_puntos!$1:$1,0))="",NA(),INDEX(Aux_puntos!$A$2:$OJ$901,83,MATCH($B$2&"|yC",Aux_puntos!$1:$1,0))),NA()) | AG87: =IFERROR(IF(INDEX(Aux_puntos!$A$2:$OJ$901,83,MATCH($B$2&"|xI",Aux_puntos!$1:$1,0))="",NA(),INDEX(Aux_puntos!$A$2:$OJ$901,83,MATCH($B$2&"|xI",Aux_puntos!$1:$1,0))),NA()) | AH87: =IFERROR(IF(INDEX(Aux_puntos!$A$2:$OJ$901,83,MATCH($B$2&"|yI",Aux_puntos!$1:$1,0))="",NA(),INDEX(Aux_puntos!$A$2:$OJ$901,83,MATCH($B$2&"|yI",Aux_puntos!$1:$1,0))),NA()) | AI87: =IFERROR(IF(INDEX(Aux_puntos!$A$2:$OJ$901,83,MATCH($B$2&"|xN",Aux_puntos!$1:$1,0))="",NA(),INDEX(Aux_puntos!$A$2:$OJ$901,83,MATCH($B$2&"|xN",Aux_puntos!$1:$1,0))),NA()) | AJ87: =IFERROR(IF(INDEX(Aux_puntos!$A$2:$OJ$901,83,MATCH($B$2&"|yN",Aux_puntos!$1:$1,0))="",NA(),INDEX(Aux_puntos!$A$2:$OJ$901,83,MATCH($B$2&"|yN",Aux_puntos!$1:$1,0))),NA())
AC88: =IFERROR(IF(INDEX(Aux_puntos!$A$2:$OJ$901,84,MATCH($B$2&"|xK",Aux_puntos!$1:$1,0))="",NA(),INDEX(Aux_puntos!$A$2:$OJ$901,84,MATCH($B$2&"|xK",Aux_puntos!$1:$1,0))),NA()) | AD88: =IFERROR(IF(INDEX(Aux_puntos!$A$2:$OJ$901,84,MATCH($B$2&"|yK",Aux_puntos!$1:$1,0))="",NA(),INDEX(Aux_puntos!$A$2:$OJ$901,84,MATCH($B$2&"|yK",Aux_puntos!$1:$1,0))),NA()) | AE88: =IFERROR(IF(INDEX(Aux_puntos!$A$2:$OJ$901,84,MATCH($B$2&"|xC",Aux_puntos!$1:$1,0))="",NA(),INDEX(Aux_puntos!$A$2:$OJ$901,84,MATCH($B$2&"|xC",Aux_puntos!$1:$1,0))),NA()) | AF88: =IFERROR(IF(INDEX(Aux_puntos!$A$2:$OJ$901,84,MATCH($B$2&"|yC",Aux_puntos!$1:$1,0))="",NA(),INDEX(Aux_puntos!$A$2:$OJ$901,84,MATCH($B$2&"|yC",Aux_puntos!$1:$1,0))),NA()) | AG88: =IFERROR(IF(INDEX(Aux_puntos!$A$2:$OJ$901,84,MATCH($B$2&"|xI",Aux_puntos!$1:$1,0))="",NA(),INDEX(Aux_puntos!$A$2:$OJ$901,84,MATCH($B$2&"|xI",Aux_puntos!$1:$1,0))),NA()) | AH88: =IFERROR(IF(INDEX(Aux_puntos!$A$2:$OJ$901,84,MATCH($B$2&"|yI",Aux_puntos!$1:$1,0))="",NA(),INDEX(Aux_puntos!$A$2:$OJ$901,84,MATCH($B$2&"|yI",Aux_puntos!$1:$1,0))),NA()) | AI88: =IFERROR(IF(INDEX(Aux_puntos!$A$2:$OJ$901,84,MATCH($B$2&"|xN",Aux_puntos!$1:$1,0))="",NA(),INDEX(Aux_puntos!$A$2:$OJ$901,84,MATCH($B$2&"|xN",Aux_puntos!$1:$1,0))),NA()) | AJ88: =IFERROR(IF(INDEX(Aux_puntos!$A$2:$OJ$901,84,MATCH($B$2&"|yN",Aux_puntos!$1:$1,0))="",NA(),INDEX(Aux_puntos!$A$2:$OJ$901,84,MATCH($B$2&"|yN",Aux_puntos!$1:$1,0))),NA())
AC89: =IFERROR(IF(INDEX(Aux_puntos!$A$2:$OJ$901,85,MATCH($B$2&"|xK",Aux_puntos!$1:$1,0))="",NA(),INDEX(Aux_puntos!$A$2:$OJ$901,85,MATCH($B$2&"|xK",Aux_puntos!$1:$1,0))),NA()) | AD89: =IFERROR(IF(INDEX(Aux_puntos!$A$2:$OJ$901,85,MATCH($B$2&"|yK",Aux_puntos!$1:$1,0))="",NA(),INDEX(Aux_puntos!$A$2:$OJ$901,85,MATCH($B$2&"|yK",Aux_puntos!$1:$1,0))),NA()) | AE89: =IFERROR(IF(INDEX(Aux_puntos!$A$2:$OJ$901,85,MATCH($B$2&"|xC",Aux_puntos!$1:$1,0))="",NA(),INDEX(Aux_puntos!$A$2:$OJ$901,85,MATCH($B$2&"|xC",Aux_puntos!$1:$1,0))),NA()) | AF89: =IFERROR(IF(INDEX(Aux_puntos!$A$2:$OJ$901,85,MATCH($B$2&"|yC",Aux_puntos!$1:$1,0))="",NA(),INDEX(Aux_puntos!$A$2:$OJ$901,85,MATCH($B$2&"|yC",Aux_puntos!$1:$1,0))),NA()) | AG89: =IFERROR(IF(INDEX(Aux_puntos!$A$2:$OJ$901,85,MATCH($B$2&"|xI",Aux_puntos!$1:$1,0))="",NA(),INDEX(Aux_puntos!$A$2:$OJ$901,85,MATCH($B$2&"|xI",Aux_puntos!$1:$1,0))),NA()) | AH89: =IFERROR(IF(INDEX(Aux_puntos!$A$2:$OJ$901,85,MATCH($B$2&"|yI",Aux_puntos!$1:$1,0))="",NA(),INDEX(Aux_puntos!$A$2:$OJ$901,85,MATCH($B$2&"|yI",Aux_puntos!$1:$1,0))),NA()) | AI89: =IFERROR(IF(INDEX(Aux_puntos!$A$2:$OJ$901,85,MATCH($B$2&"|xN",Aux_puntos!$1:$1,0))="",NA(),INDEX(Aux_puntos!$A$2:$OJ$901,85,MATCH($B$2&"|xN",Aux_puntos!$1:$1,0))),NA()) | AJ89: =IFERROR(IF(INDEX(Aux_puntos!$A$2:$OJ$901,85,MATCH($B$2&"|yN",Aux_puntos!$1:$1,0))="",NA(),INDEX(Aux_puntos!$A$2:$OJ$901,85,MATCH($B$2&"|yN",Aux_puntos!$1:$1,0))),NA())
AC90: =IFERROR(IF(INDEX(Aux_puntos!$A$2:$OJ$901,86,MATCH($B$2&"|xK",Aux_puntos!$1:$1,0))="",NA(),INDEX(Aux_puntos!$A$2:$OJ$901,86,MATCH($B$2&"|xK",Aux_puntos!$1:$1,0))),NA()) | AD90: =IFERROR(IF(INDEX(Aux_puntos!$A$2:$OJ$901,86,MATCH($B$2&"|yK",Aux_puntos!$1:$1,0))="",NA(),INDEX(Aux_puntos!$A$2:$OJ$901,86,MATCH($B$2&"|yK",Aux_puntos!$1:$1,0))),NA()) | AE90: =IFERROR(IF(INDEX(Aux_puntos!$A$2:$OJ$901,86,MATCH($B$2&"|xC",Aux_puntos!$1:$1,0))="",NA(),INDEX(Aux_puntos!$A$2:$OJ$901,86,MATCH($B$2&"|xC",Aux_puntos!$1:$1,0))),NA()) | AF90: =IFERROR(IF(INDEX(Aux_puntos!$A$2:$OJ$901,86,MATCH($B$2&"|yC",Aux_puntos!$1:$1,0))="",NA(),INDEX(Aux_puntos!$A$2:$OJ$901,86,MATCH($B$2&"|yC",Aux_puntos!$1:$1,0))),NA()) | AG90: =IFERROR(IF(INDEX(Aux_puntos!$A$2:$OJ$901,86,MATCH($B$2&"|xI",Aux_puntos!$1:$1,0))="",NA(),INDEX(Aux_puntos!$A$2:$OJ$901,86,MATCH($B$2&"|xI",Aux_puntos!$1:$1,0))),NA()) | AH90: =IFERROR(IF(INDEX(Aux_puntos!$A$2:$OJ$901,86,MATCH($B$2&"|yI",Aux_puntos!$1:$1,0))="",NA(),INDEX(Aux_puntos!$A$2:$OJ$901,86,MATCH($B$2&"|yI",Aux_puntos!$1:$1,0))),NA()) | AI90: =IFERROR(IF(INDEX(Aux_puntos!$A$2:$OJ$901,86,MATCH($B$2&"|xN",Aux_puntos!$1:$1,0))="",NA(),INDEX(Aux_puntos!$A$2:$OJ$901,86,MATCH($B$2&"|xN",Aux_puntos!$1:$1,0))),NA()) | AJ90: =IFERROR(IF(INDEX(Aux_puntos!$A$2:$OJ$901,86,MATCH($B$2&"|yN",Aux_puntos!$1:$1,0))="",NA(),INDEX(Aux_puntos!$A$2:$OJ$901,86,MATCH($B$2&"|yN",Aux_puntos!$1:$1,0))),NA())
AC91: =IFERROR(IF(INDEX(Aux_puntos!$A$2:$OJ$901,87,MATCH($B$2&"|xK",Aux_puntos!$1:$1,0))="",NA(),INDEX(Aux_puntos!$A$2:$OJ$901,87,MATCH($B$2&"|xK",Aux_puntos!$1:$1,0))),NA()) | AD91: =IFERROR(IF(INDEX(Aux_puntos!$A$2:$OJ$901,87,MATCH($B$2&"|yK",Aux_puntos!$1:$1,0))="",NA(),INDEX(Aux_puntos!$A$2:$OJ$901,87,MATCH($B$2&"|yK",Aux_puntos!$1:$1,0))),NA()) | AE91: =IFERROR(IF(INDEX(Aux_puntos!$A$2:$OJ$901,87,MATCH($B$2&"|xC",Aux_puntos!$1:$1,0))="",NA(),INDEX(Aux_puntos!$A$2:$OJ$901,87,MATCH($B$2&"|xC",Aux_puntos!$1:$1,0))),NA()) | AF91: =IFERROR(IF(INDEX(Aux_puntos!$A$2:$OJ$901,87,MATCH($B$2&"|yC",Aux_puntos!$1:$1,0))="",NA(),INDEX(Aux_puntos!$A$2:$OJ$901,87,MATCH($B$2&"|yC",Aux_puntos!$1:$1,0))),NA()) | AG91: =IFERROR(IF(INDEX(Aux_puntos!$A$2:$OJ$901,87,MATCH($B$2&"|xI",Aux_puntos!$1:$1,0))="",NA(),INDEX(Aux_puntos!$A$2:$OJ$901,87,MATCH($B$2&"|xI",Aux_puntos!$1:$1,0))),NA()) | AH91: =IFERROR(IF(INDEX(Aux_puntos!$A$2:$OJ$901,87,MATCH($B$2&"|yI",Aux_puntos!$1:$1,0))="",NA(),INDEX(Aux_puntos!$A$2:$OJ$901,87,MATCH($B$2&"|yI",Aux_puntos!$1:$1,0))),NA()) | AI91: =IFERROR(IF(INDEX(Aux_puntos!$A$2:$OJ$901,87,MATCH($B$2&"|xN",Aux_puntos!$1:$1,0))="",NA(),INDEX(Aux_puntos!$A$2:$OJ$901,87,MATCH($B$2&"|xN",Aux_puntos!$1:$1,0))),NA()) | AJ91: =IFERROR(IF(INDEX(Aux_puntos!$A$2:$OJ$901,87,MATCH($B$2&"|yN",Aux_puntos!$1:$1,0))="",NA(),INDEX(Aux_puntos!$A$2:$OJ$901,87,MATCH($B$2&"|yN",Aux_puntos!$1:$1,0))),NA())
AC92: =IFERROR(IF(INDEX(Aux_puntos!$A$2:$OJ$901,88,MATCH($B$2&"|xK",Aux_puntos!$1:$1,0))="",NA(),INDEX(Aux_puntos!$A$2:$OJ$901,88,MATCH($B$2&"|xK",Aux_puntos!$1:$1,0))),NA()) | AD92: =IFERROR(IF(INDEX(Aux_puntos!$A$2:$OJ$901,88,MATCH($B$2&"|yK",Aux_puntos!$1:$1,0))="",NA(),INDEX(Aux_puntos!$A$2:$OJ$901,88,MATCH($B$2&"|yK",Aux_puntos!$1:$1,0))),NA()) | AE92: =IFERROR(IF(INDEX(Aux_puntos!$A$2:$OJ$901,88,MATCH($B$2&"|xC",Aux_puntos!$1:$1,0))="",NA(),INDEX(Aux_puntos!$A$2:$OJ$901,88,MATCH($B$2&"|xC",Aux_puntos!$1:$1,0))),NA()) | AF92: =IFERROR(IF(INDEX(Aux_puntos!$A$2:$OJ$901,88,MATCH($B$2&"|yC",Aux_puntos!$1:$1,0))="",NA(),INDEX(Aux_puntos!$A$2:$OJ$901,88,MATCH($B$2&"|yC",Aux_puntos!$1:$1,0))),NA()) | AG92: =IFERROR(IF(INDEX(Aux_puntos!$A$2:$OJ$901,88,MATCH($B$2&"|xI",Aux_puntos!$1:$1,0))="",NA(),INDEX(Aux_puntos!$A$2:$OJ$901,88,MATCH($B$2&"|xI",Aux_puntos!$1:$1,0))),NA()) | AH92: =IFERROR(IF(INDEX(Aux_puntos!$A$2:$OJ$901,88,MATCH($B$2&"|yI",Aux_puntos!$1:$1,0))="",NA(),INDEX(Aux_puntos!$A$2:$OJ$901,88,MATCH($B$2&"|yI",Aux_puntos!$1:$1,0))),NA()) | AI92: =IFERROR(IF(INDEX(Aux_puntos!$A$2:$OJ$901,88,MATCH($B$2&"|xN",Aux_puntos!$1:$1,0))="",NA(),INDEX(Aux_puntos!$A$2:$OJ$901,88,MATCH($B$2&"|xN",Aux_puntos!$1:$1,0))),NA()) | AJ92: =IFERROR(IF(INDEX(Aux_puntos!$A$2:$OJ$901,88,MATCH($B$2&"|yN",Aux_puntos!$1:$1,0))="",NA(),INDEX(Aux_puntos!$A$2:$OJ$901,88,MATCH($B$2&"|yN",Aux_puntos!$1:$1,0))),NA())
AC93: =IFERROR(IF(INDEX(Aux_puntos!$A$2:$OJ$901,89,MATCH($B$2&"|xK",Aux_puntos!$1:$1,0))="",NA(),INDEX(Aux_puntos!$A$2:$OJ$901,89,MATCH($B$2&"|xK",Aux_puntos!$1:$1,0))),NA()) | AD93: =IFERROR(IF(INDEX(Aux_puntos!$A$2:$OJ$901,89,MATCH($B$2&"|yK",Aux_puntos!$1:$1,0))="",NA(),INDEX(Aux_puntos!$A$2:$OJ$901,89,MATCH($B$2&"|yK",Aux_puntos!$1:$1,0))),NA()) | AE93: =IFERROR(IF(INDEX(Aux_puntos!$A$2:$OJ$901,89,MATCH($B$2&"|xC",Aux_puntos!$1:$1,0))="",NA(),INDEX(Aux_puntos!$A$2:$OJ$901,89,MATCH($B$2&"|xC",Aux_puntos!$1:$1,0))),NA()) | AF93: =IFERROR(IF(INDEX(Aux_puntos!$A$2:$OJ$901,89,MATCH($B$2&"|yC",Aux_puntos!$1:$1,0))="",NA(),INDEX(Aux_puntos!$A$2:$OJ$901,89,MATCH($B$2&"|yC",Aux_puntos!$1:$1,0))),NA()) | AG93: =IFERROR(IF(INDEX(Aux_puntos!$A$2:$OJ$901,89,MATCH($B$2&"|xI",Aux_puntos!$1:$1,0))="",NA(),INDEX(Aux_puntos!$A$2:$OJ$901,89,MATCH($B$2&"|xI",Aux_puntos!$1:$1,0))),NA()) | AH93: =IFERROR(IF(INDEX(Aux_puntos!$A$2:$OJ$901,89,MATCH($B$2&"|yI",Aux_puntos!$1:$1,0))="",NA(),INDEX(Aux_puntos!$A$2:$OJ$901,89,MATCH($B$2&"|yI",Aux_puntos!$1:$1,0))),NA()) | AI93: =IFERROR(IF(INDEX(Aux_puntos!$A$2:$OJ$901,89,MATCH($B$2&"|xN",Aux_puntos!$1:$1,0))="",NA(),INDEX(Aux_puntos!$A$2:$OJ$901,89,MATCH($B$2&"|xN",Aux_puntos!$1:$1,0))),NA()) | AJ93: =IFERROR(IF(INDEX(Aux_puntos!$A$2:$OJ$901,89,MATCH($B$2&"|yN",Aux_puntos!$1:$1,0))="",NA(),INDEX(Aux_puntos!$A$2:$OJ$901,89,MATCH($B$2&"|yN",Aux_puntos!$1:$1,0))),NA())
AC94: =IFERROR(IF(INDEX(Aux_puntos!$A$2:$OJ$901,90,MATCH($B$2&"|xK",Aux_puntos!$1:$1,0))="",NA(),INDEX(Aux_puntos!$A$2:$OJ$901,90,MATCH($B$2&"|xK",Aux_puntos!$1:$1,0))),NA()) | AD94: =IFERROR(IF(INDEX(Aux_puntos!$A$2:$OJ$901,90,MATCH($B$2&"|yK",Aux_puntos!$1:$1,0))="",NA(),INDEX(Aux_puntos!$A$2:$OJ$901,90,MATCH($B$2&"|yK",Aux_puntos!$1:$1,0))),NA()) | AE94: =IFERROR(IF(INDEX(Aux_puntos!$A$2:$OJ$901,90,MATCH($B$2&"|xC",Aux_puntos!$1:$1,0))="",NA(),INDEX(Aux_puntos!$A$2:$OJ$901,90,MATCH($B$2&"|xC",Aux_puntos!$1:$1,0))),NA()) | AF94: =IFERROR(IF(INDEX(Aux_puntos!$A$2:$OJ$901,90,MATCH($B$2&"|yC",Aux_puntos!$1:$1,0))="",NA(),INDEX(Aux_puntos!$A$2:$OJ$901,90,MATCH($B$2&"|yC",Aux_puntos!$1:$1,0))),NA()) | AG94: =IFERROR(IF(INDEX(Aux_puntos!$A$2:$OJ$901,90,MATCH($B$2&"|xI",Aux_puntos!$1:$1,0))="",NA(),INDEX(Aux_puntos!$A$2:$OJ$901,90,MATCH($B$2&"|xI",Aux_puntos!$1:$1,0))),NA()) | AH94: =IFERROR(IF(INDEX(Aux_puntos!$A$2:$OJ$901,90,MATCH($B$2&"|yI",Aux_puntos!$1:$1,0))="",NA(),INDEX(Aux_puntos!$A$2:$OJ$901,90,MATCH($B$2&"|yI",Aux_puntos!$1:$1,0))),NA()) | AI94: =IFERROR(IF(INDEX(Aux_puntos!$A$2:$OJ$901,90,MATCH($B$2&"|xN",Aux_puntos!$1:$1,0))="",NA(),INDEX(Aux_puntos!$A$2:$OJ$901,90,MATCH($B$2&"|xN",Aux_puntos!$1:$1,0))),NA()) | AJ94: =IFERROR(IF(INDEX(Aux_puntos!$A$2:$OJ$901,90,MATCH($B$2&"|yN",Aux_puntos!$1:$1,0))="",NA(),INDEX(Aux_puntos!$A$2:$OJ$901,90,MATCH($B$2&"|yN",Aux_puntos!$1:$1,0))),NA())
AC95: =IFERROR(IF(INDEX(Aux_puntos!$A$2:$OJ$901,91,MATCH($B$2&"|xK",Aux_puntos!$1:$1,0))="",NA(),INDEX(Aux_puntos!$A$2:$OJ$901,91,MATCH($B$2&"|xK",Aux_puntos!$1:$1,0))),NA()) | AD95: =IFERROR(IF(INDEX(Aux_puntos!$A$2:$OJ$901,91,MATCH($B$2&"|yK",Aux_puntos!$1:$1,0))="",NA(),INDEX(Aux_puntos!$A$2:$OJ$901,91,MATCH($B$2&"|yK",Aux_puntos!$1:$1,0))),NA()) | AE95: =IFERROR(IF(INDEX(Aux_puntos!$A$2:$OJ$901,91,MATCH($B$2&"|xC",Aux_puntos!$1:$1,0))="",NA(),INDEX(Aux_puntos!$A$2:$OJ$901,91,MATCH($B$2&"|xC",Aux_puntos!$1:$1,0))),NA()) | AF95: =IFERROR(IF(INDEX(Aux_puntos!$A$2:$OJ$901,91,MATCH($B$2&"|yC",Aux_puntos!$1:$1,0))="",NA(),INDEX(Aux_puntos!$A$2:$OJ$901,91,MATCH($B$2&"|yC",Aux_puntos!$1:$1,0))),NA()) | AG95: =IFERROR(IF(INDEX(Aux_puntos!$A$2:$OJ$901,91,MATCH($B$2&"|xI",Aux_puntos!$1:$1,0))="",NA(),INDEX(Aux_puntos!$A$2:$OJ$901,91,MATCH($B$2&"|xI",Aux_puntos!$1:$1,0))),NA()) | AH95: =IFERROR(IF(INDEX(Aux_puntos!$A$2:$OJ$901,91,MATCH($B$2&"|yI",Aux_puntos!$1:$1,0))="",NA(),INDEX(Aux_puntos!$A$2:$OJ$901,91,MATCH($B$2&"|yI",Aux_puntos!$1:$1,0))),NA()) | AI95: =IFERROR(IF(INDEX(Aux_puntos!$A$2:$OJ$901,91,MATCH($B$2&"|xN",Aux_puntos!$1:$1,0))="",NA(),INDEX(Aux_puntos!$A$2:$OJ$901,91,MATCH($B$2&"|xN",Aux_puntos!$1:$1,0))),NA()) | AJ95: =IFERROR(IF(INDEX(Aux_puntos!$A$2:$OJ$901,91,MATCH($B$2&"|yN",Aux_puntos!$1:$1,0))="",NA(),INDEX(Aux_puntos!$A$2:$OJ$901,91,MATCH($B$2&"|yN",Aux_puntos!$1:$1,0))),NA())
AC96: =IFERROR(IF(INDEX(Aux_puntos!$A$2:$OJ$901,92,MATCH($B$2&"|xK",Aux_puntos!$1:$1,0))="",NA(),INDEX(Aux_puntos!$A$2:$OJ$901,92,MATCH($B$2&"|xK",Aux_puntos!$1:$1,0))),NA()) | AD96: =IFERROR(IF(INDEX(Aux_puntos!$A$2:$OJ$901,92,MATCH($B$2&"|yK",Aux_puntos!$1:$1,0))="",NA(),INDEX(Aux_puntos!$A$2:$OJ$901,92,MATCH($B$2&"|yK",Aux_puntos!$1:$1,0))),NA()) | AE96: =IFERROR(IF(INDEX(Aux_puntos!$A$2:$OJ$901,92,MATCH($B$2&"|xC",Aux_puntos!$1:$1,0))="",NA(),INDEX(Aux_puntos!$A$2:$OJ$901,92,MATCH($B$2&"|xC",Aux_puntos!$1:$1,0))),NA()) | AF96: =IFERROR(IF(INDEX(Aux_puntos!$A$2:$OJ$901,92,MATCH($B$2&"|yC",Aux_puntos!$1:$1,0))="",NA(),INDEX(Aux_puntos!$A$2:$OJ$901,92,MATCH($B$2&"|yC",Aux_puntos!$1:$1,0))),NA()) | AG96: =IFERROR(IF(INDEX(Aux_puntos!$A$2:$OJ$901,92,MATCH($B$2&"|xI",Aux_puntos!$1:$1,0))="",NA(),INDEX(Aux_puntos!$A$2:$OJ$901,92,MATCH($B$2&"|xI",Aux_puntos!$1:$1,0))),NA()) | AH96: =IFERROR(IF(INDEX(Aux_puntos!$A$2:$OJ$901,92,MATCH($B$2&"|yI",Aux_puntos!$1:$1,0))="",NA(),INDEX(Aux_puntos!$A$2:$OJ$901,92,MATCH($B$2&"|yI",Aux_puntos!$1:$1,0))),NA()) | AI96: =IFERROR(IF(INDEX(Aux_puntos!$A$2:$OJ$901,92,MATCH($B$2&"|xN",Aux_puntos!$1:$1,0))="",NA(),INDEX(Aux_puntos!$A$2:$OJ$901,92,MATCH($B$2&"|xN",Aux_puntos!$1:$1,0))),NA()) | AJ96: =IFERROR(IF(INDEX(Aux_puntos!$A$2:$OJ$901,92,MATCH($B$2&"|yN",Aux_puntos!$1:$1,0))="",NA(),INDEX(Aux_puntos!$A$2:$OJ$901,92,MATCH($B$2&"|yN",Aux_puntos!$1:$1,0))),NA())
AC97: =IFERROR(IF(INDEX(Aux_puntos!$A$2:$OJ$901,93,MATCH($B$2&"|xK",Aux_puntos!$1:$1,0))="",NA(),INDEX(Aux_puntos!$A$2:$OJ$901,93,MATCH($B$2&"|xK",Aux_puntos!$1:$1,0))),NA()) | AD97: =IFERROR(IF(INDEX(Aux_puntos!$A$2:$OJ$901,93,MATCH($B$2&"|yK",Aux_puntos!$1:$1,0))="",NA(),INDEX(Aux_puntos!$A$2:$OJ$901,93,MATCH($B$2&"|yK",Aux_puntos!$1:$1,0))),NA()) | AE97: =IFERROR(IF(INDEX(Aux_puntos!$A$2:$OJ$901,93,MATCH($B$2&"|xC",Aux_puntos!$1:$1,0))="",NA(),INDEX(Aux_puntos!$A$2:$OJ$901,93,MATCH($B$2&"|xC",Aux_puntos!$1:$1,0))),NA()) | AF97: =IFERROR(IF(INDEX(Aux_puntos!$A$2:$OJ$901,93,MATCH($B$2&"|yC",Aux_puntos!$1:$1,0))="",NA(),INDEX(Aux_puntos!$A$2:$OJ$901,93,MATCH($B$2&"|yC",Aux_puntos!$1:$1,0))),NA()) | AG97: =IFERROR(IF(INDEX(Aux_puntos!$A$2:$OJ$901,93,MATCH($B$2&"|xI",Aux_puntos!$1:$1,0))="",NA(),INDEX(Aux_puntos!$A$2:$OJ$901,93,MATCH($B$2&"|xI",Aux_puntos!$1:$1,0))),NA()) | AH97: =IFERROR(IF(INDEX(Aux_puntos!$A$2:$OJ$901,93,MATCH($B$2&"|yI",Aux_puntos!$1:$1,0))="",NA(),INDEX(Aux_puntos!$A$2:$OJ$901,93,MATCH($B$2&"|yI",Aux_puntos!$1:$1,0))),NA()) | AI97: =IFERROR(IF(INDEX(Aux_puntos!$A$2:$OJ$901,93,MATCH($B$2&"|xN",Aux_puntos!$1:$1,0))="",NA(),INDEX(Aux_puntos!$A$2:$OJ$901,93,MATCH($B$2&"|xN",Aux_puntos!$1:$1,0))),NA()) | AJ97: =IFERROR(IF(INDEX(Aux_puntos!$A$2:$OJ$901,93,MATCH($B$2&"|yN",Aux_puntos!$1:$1,0))="",NA(),INDEX(Aux_puntos!$A$2:$OJ$901,93,MATCH($B$2&"|yN",Aux_puntos!$1:$1,0))),NA())
AC98: =IFERROR(IF(INDEX(Aux_puntos!$A$2:$OJ$901,94,MATCH($B$2&"|xK",Aux_puntos!$1:$1,0))="",NA(),INDEX(Aux_puntos!$A$2:$OJ$901,94,MATCH($B$2&"|xK",Aux_puntos!$1:$1,0))),NA()) | AD98: =IFERROR(IF(INDEX(Aux_puntos!$A$2:$OJ$901,94,MATCH($B$2&"|yK",Aux_puntos!$1:$1,0))="",NA(),INDEX(Aux_puntos!$A$2:$OJ$901,94,MATCH($B$2&"|yK",Aux_puntos!$1:$1,0))),NA()) | AE98: =IFERROR(IF(INDEX(Aux_puntos!$A$2:$OJ$901,94,MATCH($B$2&"|xC",Aux_puntos!$1:$1,0))="",NA(),INDEX(Aux_puntos!$A$2:$OJ$901,94,MATCH($B$2&"|xC",Aux_puntos!$1:$1,0))),NA()) | AF98: =IFERROR(IF(INDEX(Aux_puntos!$A$2:$OJ$901,94,MATCH($B$2&"|yC",Aux_puntos!$1:$1,0))="",NA(),INDEX(Aux_puntos!$A$2:$OJ$901,94,MATCH($B$2&"|yC",Aux_puntos!$1:$1,0))),NA()) | AG98: =IFERROR(IF(INDEX(Aux_puntos!$A$2:$OJ$901,94,MATCH($B$2&"|xI",Aux_puntos!$1:$1,0))="",NA(),INDEX(Aux_puntos!$A$2:$OJ$901,94,MATCH($B$2&"|xI",Aux_puntos!$1:$1,0))),NA()) | AH98: =IFERROR(IF(INDEX(Aux_puntos!$A$2:$OJ$901,94,MATCH($B$2&"|yI",Aux_puntos!$1:$1,0))="",NA(),INDEX(Aux_puntos!$A$2:$OJ$901,94,MATCH($B$2&"|yI",Aux_puntos!$1:$1,0))),NA()) | AI98: =IFERROR(IF(INDEX(Aux_puntos!$A$2:$OJ$901,94,MATCH($B$2&"|xN",Aux_puntos!$1:$1,0))="",NA(),INDEX(Aux_puntos!$A$2:$OJ$901,94,MATCH($B$2&"|xN",Aux_puntos!$1:$1,0))),NA()) | AJ98: =IFERROR(IF(INDEX(Aux_puntos!$A$2:$OJ$901,94,MATCH($B$2&"|yN",Aux_puntos!$1:$1,0))="",NA(),INDEX(Aux_puntos!$A$2:$OJ$901,94,MATCH($B$2&"|yN",Aux_puntos!$1:$1,0))),NA())
AC99: =IFERROR(IF(INDEX(Aux_puntos!$A$2:$OJ$901,95,MATCH($B$2&"|xK",Aux_puntos!$1:$1,0))="",NA(),INDEX(Aux_puntos!$A$2:$OJ$901,95,MATCH($B$2&"|xK",Aux_puntos!$1:$1,0))),NA()) | AD99: =IFERROR(IF(INDEX(Aux_puntos!$A$2:$OJ$901,95,MATCH($B$2&"|yK",Aux_puntos!$1:$1,0))="",NA(),INDEX(Aux_puntos!$A$2:$OJ$901,95,MATCH($B$2&"|yK",Aux_puntos!$1:$1,0))),NA()) | AE99: =IFERROR(IF(INDEX(Aux_puntos!$A$2:$OJ$901,95,MATCH($B$2&"|xC",Aux_puntos!$1:$1,0))="",NA(),INDEX(Aux_puntos!$A$2:$OJ$901,95,MATCH($B$2&"|xC",Aux_puntos!$1:$1,0))),NA()) | AF99: =IFERROR(IF(INDEX(Aux_puntos!$A$2:$OJ$901,95,MATCH($B$2&"|yC",Aux_puntos!$1:$1,0))="",NA(),INDEX(Aux_puntos!$A$2:$OJ$901,95,MATCH($B$2&"|yC",Aux_puntos!$1:$1,0))),NA()) | AG99: =IFERROR(IF(INDEX(Aux_puntos!$A$2:$OJ$901,95,MATCH($B$2&"|xI",Aux_puntos!$1:$1,0))="",NA(),INDEX(Aux_puntos!$A$2:$OJ$901,95,MATCH($B$2&"|xI",Aux_puntos!$1:$1,0))),NA()) | AH99: =IFERROR(IF(INDEX(Aux_puntos!$A$2:$OJ$901,95,MATCH($B$2&"|yI",Aux_puntos!$1:$1,0))="",NA(),INDEX(Aux_puntos!$A$2:$OJ$901,95,MATCH($B$2&"|yI",Aux_puntos!$1:$1,0))),NA()) | AI99: =IFERROR(IF(INDEX(Aux_puntos!$A$2:$OJ$901,95,MATCH($B$2&"|xN",Aux_puntos!$1:$1,0))="",NA(),INDEX(Aux_puntos!$A$2:$OJ$901,95,MATCH($B$2&"|xN",Aux_puntos!$1:$1,0))),NA()) | AJ99: =IFERROR(IF(INDEX(Aux_puntos!$A$2:$OJ$901,95,MATCH($B$2&"|yN",Aux_puntos!$1:$1,0))="",NA(),INDEX(Aux_puntos!$A$2:$OJ$901,95,MATCH($B$2&"|yN",Aux_puntos!$1:$1,0))),NA())
AC100: =IFERROR(IF(INDEX(Aux_puntos!$A$2:$OJ$901,96,MATCH($B$2&"|xK",Aux_puntos!$1:$1,0))="",NA(),INDEX(Aux_puntos!$A$2:$OJ$901,96,MATCH($B$2&"|xK",Aux_puntos!$1:$1,0))),NA()) | AD100: =IFERROR(IF(INDEX(Aux_puntos!$A$2:$OJ$901,96,MATCH($B$2&"|yK",Aux_puntos!$1:$1,0))="",NA(),INDEX(Aux_puntos!$A$2:$OJ$901,96,MATCH($B$2&"|yK",Aux_puntos!$1:$1,0))),NA()) | AE100: =IFERROR(IF(INDEX(Aux_puntos!$A$2:$OJ$901,96,MATCH($B$2&"|xC",Aux_puntos!$1:$1,0))="",NA(),INDEX(Aux_puntos!$A$2:$OJ$901,96,MATCH($B$2&"|xC",Aux_puntos!$1:$1,0))),NA()) | AF100: =IFERROR(IF(INDEX(Aux_puntos!$A$2:$OJ$901,96,MATCH($B$2&"|yC",Aux_puntos!$1:$1,0))="",NA(),INDEX(Aux_puntos!$A$2:$OJ$901,96,MATCH($B$2&"|yC",Aux_puntos!$1:$1,0))),NA()) | AG100: =IFERROR(IF(INDEX(Aux_puntos!$A$2:$OJ$901,96,MATCH($B$2&"|xI",Aux_puntos!$1:$1,0))="",NA(),INDEX(Aux_puntos!$A$2:$OJ$901,96,MATCH($B$2&"|xI",Aux_puntos!$1:$1,0))),NA()) | AH100: =IFERROR(IF(INDEX(Aux_puntos!$A$2:$OJ$901,96,MATCH($B$2&"|yI",Aux_puntos!$1:$1,0))="",NA(),INDEX(Aux_puntos!$A$2:$OJ$901,96,MATCH($B$2&"|yI",Aux_puntos!$1:$1,0))),NA()) | AI100: =IFERROR(IF(INDEX(Aux_puntos!$A$2:$OJ$901,96,MATCH($B$2&"|xN",Aux_puntos!$1:$1,0))="",NA(),INDEX(Aux_puntos!$A$2:$OJ$901,96,MATCH($B$2&"|xN",Aux_puntos!$1:$1,0))),NA()) | AJ100: =IFERROR(IF(INDEX(Aux_puntos!$A$2:$OJ$901,96,MATCH($B$2&"|yN",Aux_puntos!$1:$1,0))="",NA(),INDEX(Aux_puntos!$A$2:$OJ$901,96,MATCH($B$2&"|yN",Aux_puntos!$1:$1,0))),NA())
AC101: =IFERROR(IF(INDEX(Aux_puntos!$A$2:$OJ$901,97,MATCH($B$2&"|xK",Aux_puntos!$1:$1,0))="",NA(),INDEX(Aux_puntos!$A$2:$OJ$901,97,MATCH($B$2&"|xK",Aux_puntos!$1:$1,0))),NA()) | AD101: =IFERROR(IF(INDEX(Aux_puntos!$A$2:$OJ$901,97,MATCH($B$2&"|yK",Aux_puntos!$1:$1,0))="",NA(),INDEX(Aux_puntos!$A$2:$OJ$901,97,MATCH($B$2&"|yK",Aux_puntos!$1:$1,0))),NA()) | AE101: =IFERROR(IF(INDEX(Aux_puntos!$A$2:$OJ$901,97,MATCH($B$2&"|xC",Aux_puntos!$1:$1,0))="",NA(),INDEX(Aux_puntos!$A$2:$OJ$901,97,MATCH($B$2&"|xC",Aux_puntos!$1:$1,0))),NA()) | AF101: =IFERROR(IF(INDEX(Aux_puntos!$A$2:$OJ$901,97,MATCH($B$2&"|yC",Aux_puntos!$1:$1,0))="",NA(),INDEX(Aux_puntos!$A$2:$OJ$901,97,MATCH($B$2&"|yC",Aux_puntos!$1:$1,0))),NA()) | AG101: =IFERROR(IF(INDEX(Aux_puntos!$A$2:$OJ$901,97,MATCH($B$2&"|xI",Aux_puntos!$1:$1,0))="",NA(),INDEX(Aux_puntos!$A$2:$OJ$901,97,MATCH($B$2&"|xI",Aux_puntos!$1:$1,0))),NA()) | AH101: =IFERROR(IF(INDEX(Aux_puntos!$A$2:$OJ$901,97,MATCH($B$2&"|yI",Aux_puntos!$1:$1,0))="",NA(),INDEX(Aux_puntos!$A$2:$OJ$901,97,MATCH($B$2&"|yI",Aux_puntos!$1:$1,0))),NA()) | AI101: =IFERROR(IF(INDEX(Aux_puntos!$A$2:$OJ$901,97,MATCH($B$2&"|xN",Aux_puntos!$1:$1,0))="",NA(),INDEX(Aux_puntos!$A$2:$OJ$901,97,MATCH($B$2&"|xN",Aux_puntos!$1:$1,0))),NA()) | AJ101: =IFERROR(IF(INDEX(Aux_puntos!$A$2:$OJ$901,97,MATCH($B$2&"|yN",Aux_puntos!$1:$1,0))="",NA(),INDEX(Aux_puntos!$A$2:$OJ$901,97,MATCH($B$2&"|yN",Aux_puntos!$1:$1,0))),NA())
...

Sheet Indice
A1: Hoja | B1: Estudio | C1: Parte(s) | D1: Qué muestra
A2: Punto_profesor | B2: — | C2: — | D2: Datos del profesor y punto ancla A*
A3: S-1 Resumen por estudio | B3: S | C3: 1.1b, 1.1a, 1.1c, 1.1d, 2.1, 2.2a, 2.2b, 2.3a, 2.3b, 2.3c, 2.3d, 2.4a, 2.4b, 2.4c, 2.4d, 3.1, 3.2, 3.3, 4.1a, 4.1b, 4.1c, 4.1d, 4.1e, 4.2, 5.1a, 5.1b, 5.1c, 5.1d, 5.1e, 6.1a, 6.1b, 6.1c, 4.3 T_fuente, 4.3 eficiencias, 4.3 P_alta, 4.3 P_baja, 4.3 T_sumidero, 4.3 x_b, 4.3 x_b+T_fuente, 4.3 x_b+eficiencias, 4.3 x_b+P_alta, 4.3 x_b+P_baja, 4.3 x_b+T_sumidero, 4.3 x_b+P_alta+T_fuente, 4.3 x_b+P_alta+eficiencias, 4.3 x_b+P_alta+P_baja, 4.3 x_b+P_alta+T_sumidero, 4.3 x_b+P_alta+eficiencias+T_fuente, 4.3 x_b+P_alta+eficiencias+P_baja, 4.3 x_b+P_alta+eficiencias+T_sumidero, 6.2e, 6.1d, 6.2a, 6.2b, 6.2c, 6.2d | D3: Resumen por estudio
A4: S-2 Qué se movió en cada barrid | B4: S | C4: 1.1b, 1.1a, 1.1c, 1.1d, 2.1, 2.2a, 2.2b, 2.3a, 2.3b, 2.3c, 2.3d, 2.4a, 2.4b, 2.4c, 2.4d, 3.1, 3.2, 3.3, 4.1a, 4.1b, 4.1c, 4.1d, 4.1e, 4.2, 5.1a, 5.1b, 5.1c, 5.1d, 5.1e, 6.1a, 6.1b, 6.1c, 4.3 T_fuente, 4.3 eficiencias, 4.3 P_alta, 4.3 P_baja, 4.3 T_sumidero, 4.3 x_b, 4.3 x_b+T_fuente, 4.3 x_b+eficiencias, 4.3 x_b+P_alta, 4.3 x_b+P_baja, 4.3 x_b+T_sumidero, 4.3 x_b+P_alta+T_fuente, 4.3 x_b+P_alta+eficiencias, 4.3 x_b+P_alta+P_baja, 4.3 x_b+P_alta+T_sumidero, 4.3 x_b+P_alta+eficiencias+T_fuente, 4.3 x_b+P_alta+eficiencias+P_baja, 4.3 x_b+P_alta+eficiencias+T_sumidero, 6.2e, 6.1d, 6.2a, 6.2b, 6.2c, 6.2d | D4: Qué se movió en cada barrido
A5: S-3 Rangos KALINA comparados | B5: S | C5: nan | D5: Rangos KALINA comparados
A6: S-4 Datos del profesor conserva | B6: S | C6: nan | D6: Datos del profesor conservables
A7: S-5 Criterios que bloquean, por | B7: S | C7: nan | D7: Criterios que bloquean, por estudio
A8: 1.1-1 Condiciones qué quedó fij | B8: 1.1 | C8: 1.1b, 1.1a, 1.1c, 1.1d | D8: Condiciones: qué quedó fijo y qué se barrió
A9: 1.1-2 Corridas por parte y por | B9: 1.1 | C9: 1.1b, 1.1a, 1.1c, 1.1d | D9: Corridas por parte y por clase
A10: 1.1-3 Comparación antes y despu | B10: 1.1 | C10: 1.1b, 1.1a, 1.1c, 1.1d | D10: Comparación antes y después de la F1
A11: 2.1-1 Condiciones qué quedó fij | B11: 2.1 | C11: 2.1 | D11: Condiciones: qué quedó fijo y qué se barrió
A12: 2.1-2 Corridas por parte y por | B12: 2.1 | C12: 2.1 | D12: Corridas por parte y por clase
... A87: A.1 Anexo fuera de rango | B87: A.1 | C87: — | D87: Curiosidad: equipos fuera del rango realista

Sheet Punto_profesor
A1: Dato | B1: Unidad | C1: Punto del profesor (PP) | D1: Punto ancla A*
A2: P_alta | B2: kPa | C2: 3000 | D2: 3000
A3: P_baja | B3: kPa | C3: 400 | D3: 563.64
A4: x_b | B4: – | C4: 0.5 | D4: 0.5
A5: T_fuente | B5: K | C5: 623.15 | D5: 403
A6: T_sumidero | B6: K | C6: 300.03292 | D6: 300.03292
A7: η_t | B7: – | C7: 0.85 | D7: 0.85
A8: η_p | B8: – | C8: 0.75 | D8: 0.75
A9: ε_HRVG | B9: – | C9: 0.85 | D9: 0.85
A10: ε_reg | B10: – | C10: 0.75 | D10: 0.75
A11: ε_cond | B11: – | C11: 0.8 | D11: 0.8
A12: m_b | B12: kg/s | C12: 1 | D12: 1
A14: A* = PP con solo dos cambios (T_fuente y P_baja). Es KALINA, η = 8.48 %. PP no converge (M1).

Sheet S-1 Resumen por estudio
A1: Tabla S-1 · Resumen por estudio
A2: Síntesis de toda la campaña: cada fila es un estudio o una parte con sus propios datos fijos.
A4: Síntesis: cada fila es un estudio o una parte con sus propios datos fijos.
A5: Fuente: todos_los_puntos.csv
A7: Estudio | B7: Nombre | C7: Familia | D7: Partes | E7: Punto base | F7: Diseño | G7: Corridas | H7: Genuinas | I7: KALINA | J7: KALINA confiables | K7: Falsos convergidos | L7: Criterio que más bloquea
A8: 1.1 | B8: Repetir el caso del profesor | C8: R | D8: 1.1a, 1.1b, 1.1c, 1.1d | E8: PP | F8: una variable a la vez sobre PP | G8: 42 | H8: 0 | I8: 0 | J8: 0 | K8: 0 | L8: —
A9: 2.1 | B9: Un solo cambio | C9: F | D9: 2.1 | E9: PP | F9: malla 10 + bisección | G9: 132 | H9: 15 | I9: 0 | J9: 0 | K9: 21 | L9: O2 (15 de 15)
A10: 2.2 | B10: Dos cambios | C10: F | D10: 2.2a, 2.2b | E10: PP | F10: malla 2D + bisección | G10: 180 | H10: 165 | I10: 59 | J10: 48 | K10: 12 | L10: O2 (106 de 106)
A11: 2.3 | B11: Dos cambios con η y ε en 0.40–0.95 | C11: F | D11: 2.3a, 2.3b, 2.3c, 2.3d | E11: PP | F11: mallas + bisección | G11: 225 | H11: 154 | I11: 20 | J11: 1 | K11: 4 | L11: O2 (134 de 134)
A12: 2.4 | B12: Sumidero más frío | C12: F | D12: 2.4a, 2.4b, 2.4c, 2.4d | E12: 4 bases | F12: malla 2D + bisección | G12: 320 | H12: 269 | I12: 153 | J12: 119 | K12: 0 | L12: O2 (116 de 116)
A13: 3.1 | B13: Sensibilidad local alrededor de A* | C13: L | D13: 3.1 | E13: A* | F13: OAT 15 + A* ± 1 % | G13: 171 | H13: 148 | I13: 86 | J13: 86 | K13: 6 | L13: O2 (61 de 62)
A14: 3.2 | B14: Sensibilidad global (500 puntos) | C14: G | D14: 3.2 | E14: caja | F14: LHS | G14: 500 | H14: 452 | I14: 121 | J14: 83 | K14: 13 | L14: O2 (324 de 331)
A15: 3.3 | B15: P_baja alta (1500–2500 kPa) | C15: G | D15: 3.3 | E15: caja | F15: LHS | G15: 150 | H15: 120 | I15: 75 | J15: 45 | K15: 6 | L15: O2 (44 de 45)
A16: 4.1 | B16: Escenarios de conservación | C16: C | D16: 4.1a, 4.1b, 4.1c, 4.1d, 4.1e | E16: PP parcial | F16: LHS por escenario | G16: 600 | H16: 382 | I16: 20 | J16: 2 | K16: 12 | L16: O2 (362 de 362)
A17: 4.2 | B17: Mapa con las presiones del profesor | C17: C | D17: 4.2 | E17: PP con PA y PB | F17: malla 11×5×3 | G17: 165 | H17: 149 | I17: 104 | J17: 104 | K17: 15 | L17: O2 (30 de 45)
A18: 6.1 | B18: Verificación con el motor de referencia | C18: V | D18: 6.1a, 6.1b, 6.1c | E18: puntos clave | F18: puntos de control | G18: 167 | H18: 151 | I18: 142 | J18: 137 | K18: 0 | L18: O2 (9 de 9)
A19: 5.1 | B19: Búsqueda de la η máxima | C19: O | D19: 5.1a, 5.1b, 5.1c, 5.1d, 5.1e | E19: 5 arranques | F19: búsqueda por patrones | G19: 560 | H19: 549 | I19: 419 | J19: 331 | K19: 1 | L19: O2 (114 de 130)
... A21: 6.2 | B21: Planta real de Húsavík | C21: H | D21: 6.2a, 6.2b, 6.2c, 6.2d | E21: ancla de Húsavík | F21: recorrida + OFAT + malla | G21: 382 | H21: 347 | I21: 282 | J21: 268 | K21: 16 | L21: O2 (65 de 65)
A23: Notas: Filtro: todos los puntos (sin el anexo A.1). n = 14 filas en la tabla. † = fuera del rango confiable (IAPWS G4-01); ‡ = falso convergido. Fuente: todos_los_puntos.csv. Familias: R reproducibilidad, F factibilidad, L local, G global, C conservación, O optimización, V verificación, H Húsavík.
A26: Figura S-1 · Resultado de cada barrido: puntos por clase
A49: Estudios 1.1 a 6.2 (figura de síntesis: una barra por estudio), sin el anexo A.1.
A50: Datos fijos: no aplica (figura de síntesis).
A51: Filtro: todos los puntos menos los de A.1.
A52: n = 4560. Fuente: todos_los_puntos.csv.

Sheet S-2 Qué se movió en cada barrid
A1: Tabla S-2 · Qué se movió en cada barrido
A2: Síntesis de toda la campaña: cada fila es un estudio o una parte con sus propios datos fijos.
A4: Síntesis: cada fila es un estudio o una parte con sus propios datos fijos.
A5: Fuente: casos_x_variables.csv
A7: Parte | B7: Temperatura de la fuente, T_fuente [K] | C7: Temperatura del sumidero, T_sumidero [K] | D7: Presión de alta, P_alta [kPa] | E7: Presión de baja, P_baja [kPa] | F7: Fracción de amoníaco de la mezcla base, x_b [–] | G7: Flujo másico base, m_b [kg/s] | H7: Eficiencia isentrópica de la turbina, η_t [–] | I7: Eficiencia isentrópica de la bomba, η_p [–] | J7: Efectividad del generador de vapor, ε_HRVG [–] | K7: Efectividad del regenerador, ε_reg [–] | L7: Efectividad del condensador, ε_cond [–] | M7: Piso de O2 (T de diseño de la bomba) [K] | N7: motor
A8: 1.1b · solo P_alta | B8: fijo: profesor | C8: fijo: profesor | D8: barrido: 2000 – 4000 | E8: fijo: profesor | F8: fijo: profesor | G8: fijo: profesor | H8: fijo: profesor | I8: fijo: profesor | J8: fijo: profesor | K8: fijo: profesor | L8: fijo: profesor | N8: fijo: teqp
A9: 1.1a · punto del profesor | B9: fijo: profesor | C9: fijo: profesor | D9: fijo: profesor | E9: fijo: profesor | F9: fijo: profesor | G9: fijo: profesor | H9: fijo: profesor | I9: fijo: profesor | J9: fijo: profesor | K9: fijo: profesor | L9: fijo: profesor | N9: barrido: 2 valores
A10: 1.1c · solo x_b | B10: fijo: profesor | C10: fijo: profesor | D10: fijo: profesor | E10: fijo: profesor | F10: barrido: 0.4 – 0.7 | G10: fijo: profesor | H10: fijo: profesor | I10: fijo: profesor | J10: fijo: profesor | K10: fijo: profesor | L10: fijo: profesor | N10: fijo: teqp
A11: 1.1d · temperatura ambiente hora a hora | B11: fijo: profesor | C11: barrido: 297.95 – 303.55 | D11: fijo: profesor | E11: fijo: profesor | F11: fijo: profesor | G11: fijo: profesor | H11: fijo: profesor | I11: fijo: profesor | J11: fijo: profesor | K11: fijo: profesor | L11: fijo: profesor | N11: fijo: teqp
A12: 2.1 | B12: barrido: 340 – 623.15 | C12: barrido: 283.15 – 303.55 | D12: barrido: 1000 – 10000 | E12: barrido: 150 – 1500 | F12: barrido: 0.3 – 0.9 | G12: fijo: profesor | H12: barrido: 0.75 – 0.9 | I12: barrido: 0.65 – 0.85 | J12: barrido: 0.75 – 0.85 | K12: barrido: 0.75 – 0.85 | L12: barrido: 0.75 – 0.85 | N12: fijo: teqp
A13: 2.2a · conservar la fuente (ε_HRVG × P_baja) | B13: fijo: profesor | C13: fijo: profesor | D13: fijo: profesor | E13: barrido: 400 – 2000 | F13: fijo: profesor | G13: fijo: profesor | H13: fijo: profesor | I13: fijo: profesor | J13: barrido: 0.75 – 0.81 | K13: fijo: profesor | L13: fijo: profesor | N13: fijo: teqp
A14: 2.2b · bajar la fuente (T_fuente × P_baja) | B14: barrido: 380 – 560 | C14: fijo: profesor | D14: fijo: profesor | E14: barrido: 400 – 2000 | F14: fijo: profesor | G14: fijo: profesor | H14: fijo: profesor | I14: fijo: profesor | J14: fijo: profesor | K14: fijo: profesor | L14: fijo: profesor | N14: fijo: teqp
A15: 2.3a · un cambio | B15: fijo: profesor | C15: fijo: profesor | D15: fijo: profesor | E15: fijo: profesor | F15: fijo: profesor | G15: fijo: profesor | H15: barrido: 0.4 – 0.95 | I15: barrido: 0.4 – 0.95 | J15: barrido: 0.4 – 0.95 | K15: barrido: 0.4 – 0.95 | L15: barrido: 0.4 – 0.95 | N15: fijo: teqp
A16: 2.3b · ε_HRVG × ε_cond | B16: fijo: profesor | C16: fijo: profesor | D16: fijo: profesor | E16: fijo: profesor | F16: fijo: profesor | G16: fijo: profesor | H16: fijo: profesor | I16: fijo: profesor | J16: barrido: 0.4 – 0.8 | K16: fijo: profesor | L16: barrido: 0.4 – 0.95 | N16: fijo: teqp
A17: 2.3c · ε_HRVG × P_baja | B17: fijo: profesor | C17: fijo: profesor | D17: fijo: profesor | E17: barrido: 400 – 2000 | F17: fijo: profesor | G17: fijo: profesor | H17: fijo: profesor | I17: fijo: profesor | J17: barrido: 0.4 – 0.7 | K17: fijo: profesor | L17: fijo: profesor | N17: fijo: teqp
A18: 2.3d · T_fuente × ε_cond | B18: barrido: 403 – 560 | C18: fijo: profesor | D18: fijo: profesor | E18: fijo: profesor | F18: fijo: profesor | G18: fijo: profesor | H18: fijo: profesor | I18: fijo: profesor | J18: fijo: profesor | K18: fijo: profesor | L18: barrido: 0.85 – 0.95 | N18: fijo: teqp
A19: 2.4a · fuente a 403 K | B19: fijo: 403 | C19: barrido: 278.15 – 300.033 | D19: fijo: profesor | E19: barrido: 150 – 1500 | F19: fijo: profesor | G19: fijo: profesor | H19: fijo: profesor | I19: fijo: profesor | J19: fijo: profesor | K19: fijo: profesor | L19: fijo: profesor | M19: barrido: 278.15 – 300.033 | N19: fijo: teqp
A20: 2.4b · fuente a 420 K | B20: fijo: 420 | C20: barrido: 278.15 – 300.033 | D20: fijo: profesor | E20: barrido: 150 – 1500 | F20: fijo: profesor | G20: fijo: profesor | H20: fijo: profesor | I20: fijo: profesor | J20: fijo: profesor | K20: fijo: profesor | L20: fijo: profesor | M20: barrido: 278.15 – 300.033 | N20: fijo: teqp
A21: 2.4c · ε_HRVG = 0.40 (fuente del profesor) | B21: fijo: profesor | C21: barrido: 278.15 – 300.033 | D21: fijo: profesor | E21: barrido: 150 – 1500 | F21: fijo: profesor | G21: fijo: profesor | H21: fijo: profesor | I21: fijo: profesor | J21: fijo: 0.4 | K21: fijo: profesor | L21: fijo: profesor | M21: barrido: 278.15 – 300.033 | N21: fijo: teqp
A22: 2.4d · datos exactos del profesor | B22: fijo: profesor | C22: barrido: 278.15 – 300.033 | D22: fijo: profesor | E22: barrido: 150 – 1500 | F22: fijo: profesor | G22: fijo: profesor | H22: fijo: profesor | I22: fijo: profesor | J22: fijo: profesor | K22: fijo: profesor | L22: fijo: profesor | M22: barrido: 278.15 – 300.033 | N22: fijo: teqp
A23: 3.1 | B23: barrido: 340 – 623.15 | C23: barrido: 283.15 – 303.55 | D23: barrido: 1000 – 10000 | E23: barrido: 150 – 1500 | F23: barrido: 0.3 – 0.9 | G23: fijo: profesor | H23: barrido: 0.4 – 0.95 | I23: barrido: 0.4 – 0.95 | J23: barrido: 0.4 – 0.95 | K23: barrido: 0.4 – 0.95 | L23: barrido: 0.4 – 0.95 | N23: fijo: teqp
A24: 3.2 | B24: barrido: 380.23 – 499.941 | C24: barrido: 278.192 – 303.54 | D24: barrido: 2005.4 – 4991.23 | E24: barrido: 302.949 – 1498 | F24: barrido: 0.50017 – 0.849984 | G24: fijo: profesor | H24: barrido: 0.750411 – 0.919501 | I24: barrido: 0.6504 – 0.899194 | J24: barrido: 0.600039 – 0.949047 | K24: barrido: 0.600973 – 0.949965 | L24: barrido: 0.700136 – 0.949409 | M24: barrido: 278.192 – 303.54 | N24: fijo: teqp
A25: 3.2 | B25: barrido: 380.294 – 499.533 | C25: barrido: 278.183 – 303.47 | D25: barrido: 2009.95 – 4986.56 | E25: barrido: 304.741 – 1497.19 | F25: barrido: 0.500115 – 0.848795 | G25: fijo: profesor | H25: barrido: 0.750358 – 0.919688 | I25: barrido: 0.65092 – 0.898858 | J25: barrido: 0.600605 – 0.948339 | K25: barrido: 0.601672 – 0.949157 | L25: barrido: 0.700518 – 0.949213 | M25: barrido: 278.183 – 303.47 | N25: fijo: teqp
A26: 3.3 | B26: barrido: 380.746 – 499.827 | C26: barrido: 278.278 – 303.41 | D26: barrido: 2015.69 – 4995.76 | E26: barrido: 1501.26 – 2494.53 | F26: barrido: 0.502301 – 0.849527 | G26: fijo: profesor | H26: barrido: 0.751027 – 0.919188 | I26: barrido: 0.651194 – 0.89988 | J26: barrido: 0.600893 – 0.948455 | K26: barrido: 0.600382 – 0.947696 | L26: barrido: 0.700042 – 0.949665 | M26: barrido: 278.278 – 303.41 | N26: fijo: teqp
A27: 4.1a · conserva sus temperaturas | B27: fijo: profesor | C27: fijo: profesor | D27: barrido: 2000.11 – 4986.58 | E27: barrido: 202.14 – 1989.72 | F27: barrido: 0.501239 – 0.84895 | G27: fijo: profesor | H27: barrido: 0.400616 – 0.947454 | I27: barrido: 0.404302 – 0.94919 | J27: barrido: 0.40441 – 0.949187 | K27: barrido: 0.40384 – 0.947903 | L27: barrido: 0.400868 – 0.945788 | M27: fijo: profesor | N27: fijo: teqp
A28: 4.1b · conserva sus presiones | B28: barrido: 381.609 – 621.774 | C28: barrido: 278.262 – 303.479 | D28: fijo: profesor | E28: fijo: profesor | F28: barrido: 0.500843 – 0.847315 | G28: fijo: profesor | H28: barrido: 0.402676 – 0.948584 | I28: barrido: 0.401033 – 0.947097 | J28: barrido: 0.402168 – 0.947551 | K28: barrido: 0.402278 – 0.946602 | L28: barrido: 0.402092 – 0.947396 | M28: barrido: 278.262 – 303.479 | N28: fijo: teqp
A29: 4.1c · conserva sus presiones y su clima | B29: barrido: 380.234 – 622.401 | C29: fijo: profesor | D29: fijo: profesor | E29: fijo: profesor | F29: barrido: 0.500235 – 0.849316 | G29: fijo: profesor | H29: barrido: 0.40006 – 0.947691 | I29: barrido: 0.403602 – 0.945484 | J29: barrido: 0.400156 – 0.948884 | K29: barrido: 0.402159 – 0.948596 | L29: barrido: 0.404237 – 0.946851 | M29: fijo: profesor | N29: fijo: teqp
A30: 4.1d · conserva su P_alta y sus temperaturas | B30: fijo: profesor | C30: fijo: profesor | D30: fijo: profesor | E30: barrido: 211.417 – 1985.57 | F30: barrido: 0.502261 – 0.847941 | G30: fijo: profesor | H30: barrido: 0.403251 – 0.945781 | I30: barrido: 0.400375 – 0.946613 | J30: barrido: 0.40425 – 0.949578 | K30: barrido: 0.400942 – 0.946597 | L30: barrido: 0.402166 – 0.94675 | M30: fijo: profesor | N30: fijo: teqp
A31: 4.1e · conserva su fuente y su x_b | B31: fijo: profesor | C31: barrido: 278.281 – 303.358 | D31: barrido: 2023 – 4997.47 | E31: barrido: 206.126 – 1999.26 | F31: fijo: profesor | G31: fijo: profesor | H31: barrido: 0.403299 – 0.949946 | I31: barrido: 0.403485 – 0.947603 | J31: barrido: 0.404141 – 0.948736 | K31: barrido: 0.402646 – 0.94725 | L31: barrido: 0.401266 – 0.948251 | M31: barrido: 278.281 – 303.358 | N31: fijo: teqp
A32: 4.2 | B32: barrido: 385 – 410 | C32: barrido: 278.15 – 300.033 | D32: fijo: profesor | E32: fijo: profesor | F32: fijo: profesor | G32: fijo: profesor | H32: fijo: profesor | I32: fijo: profesor | J32: fijo: profesor | K32: fijo: profesor | L32: barrido: 0.85 – 0.95 | M32: barrido: 278.15 – 300.033 | N32: fijo: teqp
A33: 5.1a · libre, desde el mejor de 3.2 | B33: barrido: 424.097 – 448.097 | C33: barrido: 278.15 – 281.638 | D33: barrido: 3181.82 – 4681.82 | E33: barrido: 588.34 – 1028.34 | F33: barrido: 0.599749 – 0.704749 | G33: fijo: profesor | H33: barrido: 0.863483 – 0.95 | I33: barrido: 0.691081 – 0.801081 | J33: barrido: 0.622731 – 0.732731 | K33: barrido: 0.88653 – 0.95 | L33: barrido: 0.786826 – 0.896826 | M33: barrido: 278.15 – 281.638 | N33: fijo: teqp
A34: 5.1b · libre, desde el mejor de 2.4 | B34: barrido: 408 – 432 | C34: barrido: 278.15 – 280.69 | D34: barrido: 2700 – 3300 | E34: barrido: 300 – 613.75 | F34: barrido: 0.5 – 0.535 | G34: fijo: profesor | H34: barrido: 0.795 – 0.95 | I34: barrido: 0.695 – 0.805 | J34: barrido: 0.795 – 0.905 | K34: barrido: 0.695 – 0.95 | L34: barrido: 0.745 – 0.855 | M34: barrido: 278.15 – 280.69 | N34: fijo: teqp
A35: 5.1c · conserva sus temperaturas | B35: fijo: profesor | C35: fijo: profesor | D35: barrido: 3605.95 – 5000 | E35: barrido: 1139.56 – 1579.56 | F35: barrido: 0.794478 – 0.85 | G35: fijo: profesor | H35: barrido: 0.781056 – 0.95 | I35: barrido: 0.782534 – 0.892534 | J35: barrido: 0.441366 – 0.551366 | K35: barrido: 0.861678 – 0.95 | L35: barrido: 0.890788 – 0.95 | M35: fijo: profesor | N35: fijo: teqp
... A39: 6.1b · piso de cavitación a 30.4 °C | B39: barrido: 390 – 623.15 | C39: barrido: 278.15 – 302.581 | D39: barrido: 3000 – 5000 | E39: barrido: 393.75 – 2494.53 | F39: barrido: 0.5 – 0.85 | G39: fijo: profesor | H39: barrido: 0.78075 – 0.95 | I39: barrido: 0.576066 – 0.871783 | J39: barrido: 0.4 – 0.95 | K39: barrido: 0.685115 – 0.95 | L39: barrido: 0.8 – 0.95 | M39: fijo: 303.55 | N39: fijo: teqp
A40: 6.1c · costo de exigir subenfriamiento | E40: barrido: 393.75 – 2500
A41: 4.3 T_fuente · ronda 0 | B41: fijo: profesor | C41: barrido: 278.344 – 303.376 | D41: barrido: 2028.57 – 4974.75 | E41: barrido: 310.761 – 1986.56 | F41: barrido: 0.503397 – 0.849888 | G41: fijo: profesor | H41: barrido: 0.402288 – 0.949109 | I41: barrido: 0.400204 – 0.94989 | J41: barrido: 0.402751 – 0.945231 | K41: barrido: 0.400958 – 0.948253 | L41: barrido: 0.400592 – 0.949047 | M41: barrido: 278.344 – 303.376 | N41: fijo: teqp
A42: 4.3 eficiencias · ronda 0 | B42: barrido: 380.438 – 519.56 | C42: barrido: 278.188 – 303.528 | D42: barrido: 2000.1 – 4999.52 | E42: barrido: 310.675 – 1987 | F42: barrido: 0.502398 – 0.847662 | G42: fijo: profesor | H42: fijo: profesor | I42: fijo: profesor | J42: fijo: profesor | K42: fijo: profesor | L42: fijo: profesor | M42: barrido: 278.188 – 303.528 | N42: fijo: teqp
A43: 4.3 P_alta · ronda 0 | B43: barrido: 380.828 – 519.225 | C43: barrido: 278.18 – 303.381 | D43: fijo: profesor | E43: barrido: 302.713 – 1996.13 | F43: barrido: 0.500418 – 0.847315 | G43: fijo: profesor | H43: barrido: 0.400005 – 0.94581 | I43: barrido: 0.400638 – 0.945013 | J43: barrido: 0.404197 – 0.949495 | K43: barrido: 0.400361 – 0.947758 | L43: barrido: 0.401597 – 0.945166 | M43: barrido: 278.18 – 303.381 | N43: fijo: teqp
A44: 4.3 P_baja · ronda 0 | B44: barrido: 380.174 – 519.32 | C44: barrido: 278.201 – 303.38 | D44: barrido: 2021.51 – 4978.35 | E44: fijo: profesor | F44: barrido: 0.501974 – 0.84661 | G44: fijo: profesor | H44: barrido: 0.405301 – 0.946598 | I44: barrido: 0.404692 – 0.949946 | J44: barrido: 0.401138 – 0.947534 | K44: barrido: 0.401253 – 0.945947 | L44: barrido: 0.402164 – 0.944624 | M44: barrido: 278.201 – 303.38 | N44: fijo: teqp
A45: 4.3 T_sumidero · ronda 0 | B45: barrido: 380.151 – 519.053 | C45: fijo: profesor | D45: barrido: 2007.35 – 4982.75 | E45: barrido: 306.34 – 1990.7 | F45: barrido: 0.50254 – 0.847062 | G45: fijo: profesor | H45: barrido: 0.405475 – 0.945276 | I45: barrido: 0.400228 – 0.944989 | J45: barrido: 0.403663 – 0.947828 | K45: barrido: 0.402938 – 0.948362 | L45: barrido: 0.400499 – 0.946093 | M45: fijo: profesor | N45: fijo: teqp
A46: 4.3 x_b · ronda 0 | B46: barrido: 380.962 – 519.59 | C46: barrido: 278.161 – 303.421 | D46: barrido: 2022.35 – 4977.25 | E46: barrido: 316.784 – 1998.76 | F46: fijo: profesor | G46: fijo: profesor | H46: barrido: 0.401545 – 0.949561 | I46: barrido: 0.401724 – 0.945897 | J46: barrido: 0.401599 – 0.949613 | K46: barrido: 0.402429 – 0.944798 | L46: barrido: 0.403976 – 0.947693 | M46: barrido: 278.161 – 303.421 | N46: fijo: teqp
A47: 4.3 x_b+T_fuente · ronda 1 | B47: fijo: profesor | C47: barrido: 278.848 – 302.949 | D47: barrido: 2053.48 – 4944.13 | E47: barrido: 340.403 – 1956.57 | F47: fijo: profesor | G47: fijo: profesor | H47: barrido: 0.40522 – 0.947004 | I47: barrido: 0.41022 – 0.939823 | J47: barrido: 0.413797 – 0.935431 | K47: barrido: 0.400784 – 0.939213 | L47: barrido: 0.405791 – 0.944173 | M47: barrido: 278.848 – 302.949 | N47: fijo: teqp
A48: 4.3 x_b+eficiencias · ronda 1 | B48: barrido: 384.037 – 517.014 | C48: barrido: 278.55 – 303.53 | D48: barrido: 2057.91 – 4961.27 | E48: barrido: 330.145 – 1943.5 | F48: fijo: profesor | G48: fijo: profesor | H48: fijo: profesor | I48: fijo: profesor | J48: fijo: profesor | K48: fijo: profesor | L48: fijo: profesor | M48: barrido: 278.55 – 303.53 | N48: fijo: teqp
A49: 4.3 x_b+P_alta · ronda 1 | B49: barrido: 382.6 – 518.065 | C49: barrido: 278.393 – 302.731 | D49: fijo: profesor | E49: barrido: 342.086 – 1989.51 | F49: fijo: profesor | G49: fijo: profesor | H49: barrido: 0.410945 – 0.935766 | I49: barrido: 0.416423 – 0.946515 | J49: barrido: 0.403456 – 0.945563 | K49: barrido: 0.415539 – 0.933999 | L49: barrido: 0.414188 – 0.945692 | M49: barrido: 278.393 – 302.731 | N49: fijo: teqp
A50: 4.3 x_b+P_baja · ronda 1 | B50: barrido: 383.998 – 516.488 | C50: barrido: 278.739 – 303.442 | D50: barrido: 2074.92 – 4986.77 | E50: fijo: profesor | F50: fijo: profesor | G50: fijo: profesor | H50: barrido: 0.40304 – 0.948479 | I50: barrido: 0.417836 – 0.947774 | J50: barrido: 0.404429 – 0.942632 | K50: barrido: 0.404476 – 0.940524 | L50: barrido: 0.417173 – 0.942729 | M50: barrido: 278.739 – 303.442 | N50: fijo: teqp
A51: 4.3 x_b+T_sumidero · ronda 1 | B51: barrido: 383.808 – 519.796 | C51: fijo: profesor | D51: barrido: 2083.43 – 4923.78 | E51: barrido: 312.409 – 1972.61 | F51: fijo: profesor | G51: fijo: profesor | H51: barrido: 0.401911 – 0.933327 | I51: barrido: 0.413781 – 0.941285 | J51: barrido: 0.417369 – 0.949934 | K51: barrido: 0.412106 – 0.93198 | L51: barrido: 0.414827 – 0.935609 | M51: fijo: profesor | N51: fijo: teqp
A52: 4.3 x_b+P_alta+T_fuente · ronda 2 | B52: fijo: profesor | C52: barrido: 278.604 – 303.079 | D52: fijo: profesor | E52: barrido: 311.166 – 1974.73 | F52: fijo: profesor | G52: fijo: profesor | H52: barrido: 0.405029 – 0.943342 | I52: barrido: 0.407698 – 0.93892 | J52: barrido: 0.40971 – 0.933939 | K52: barrido: 0.409906 – 0.946414 | L52: barrido: 0.410205 – 0.946098 | M52: barrido: 278.604 – 303.079 | N52: fijo: teqp
... A65: 6.2c · malla x_b × P_baja (x_b 0.30–0.70) | B65: fijo: 394.15 | C65: fijo: 278.15 | D65: fijo: 3300 | E65: barrido: 200 – 700 | F65: barrido: 0.3 – 0.7 | G65: fijo: profesor | H65: fijo: 0.9 | I65: fijo: 0.8 | J65: fijo: profesor | K65: fijo: profesor | L65: fijo: 0.95 | M65: fijo: 283.15 | N65: fijo: teqp
A67: Notas: Filtro: todas las partes (sin el anexo A.1). n = 58 filas en la tabla. † = fuera del rango confiable (IAPWS G4-01); ‡ = falso convergido. Fuente: casos_x_variables.csv. fijo: profesor = igual al dato del profesor; fijo: <valor> = fijo en otro valor; barrido: a – b = barrida en ese rango; vacío = sin dato en la fuente.

Sheet S-3 Rangos KALINA comparados
A1: Tabla S-3 · Rangos KALINA comparados
A2: Síntesis de toda la campaña: cada fila es un estudio o una parte con sus propios datos fijos.
A4: Síntesis: cada fila es un estudio o una parte con sus propios datos fijos.
A5: Fuente: todos_los_puntos.csv
A7: Estudio | B7: Parte | C7: Datos fijos | D7: Variable | E7: n KALINA confiables | F7: p5 | G7: Mediana | H7: p95
A8: estudio 3.2 | B8: 3.2 | C8: Datos fijos: m_b = 1 kg/s; motor de propiedades = teqp. | D8: Presión de alta, P_alta [kPa] | E8: 83 | F8: 2161.5 | G8: 3558.4 | H8: 4906.7
A9: estudio 3.2 | B9: 3.2 | C9: Datos fijos: m_b = 1 kg/s; motor de propiedades = teqp. | D9: Presión de baja, P_baja [kPa] | E9: 83 | F9: 681.28 | G9: 1152.8 | H9: 1464.5
A10: estudio 3.2 | B10: 3.2 | C10: Datos fijos: m_b = 1 kg/s; motor de propiedades = teqp. | D10: Diferencia de presiones, ΔP [kPa] | E10: 83 | F10: 972.66 | G10: 2529 | H10: 3761.5
A11: estudio 3.2 | B11: 3.2 | C11: Datos fijos: m_b = 1 kg/s; motor de propiedades = teqp. | D11: Razón de presiones, r_P [–] | E11: 83 | F11: 1.7115 | G11: 3.2108 | H11: 6.1966
A12: estudio 3.2 | B12: 3.2 | C12: Datos fijos: m_b = 1 kg/s; motor de propiedades = teqp. | D12: Temperatura de la fuente, T_fuente [K] | E12: 83 | F12: 382.47 | G12: 409.35 | H12: 455.28
A13: estudio 3.2 | B13: 3.2 | C13: Datos fijos: m_b = 1 kg/s; motor de propiedades = teqp. | D13: Fracción de amoníaco de la mezcla base, x_b [–] | E13: 83 | F13: 0.51458 | G13: 0.66017 | H13: 0.80791
A14: estudio 4.1 escenario S1 | B14: 4.1a | C14: Datos fijos: T_fuente = 623.15 K; T_sumidero = 300.03 K; m_b = 1 kg/s; piso de O2 = 300.03 K; motor de propiedades = teqp. | D14: Presión de alta, P_alta [kPa] | E14: 2 | F14: 3242.4 | G14: 3556.7 | H14: 3871
A15: estudio 4.1 escenario S1 | B15: 4.1a | C15: Datos fijos: T_fuente = 623.15 K; T_sumidero = 300.03 K; m_b = 1 kg/s; piso de O2 = 300.03 K; motor de propiedades = teqp. | D15: Presión de baja, P_baja [kPa] | E15: 2 | F15: 1389.9 | G15: 1662.6 | H15: 1935.3
A16: estudio 4.1 escenario S1 | B16: 4.1a | C16: Datos fijos: T_fuente = 623.15 K; T_sumidero = 300.03 K; m_b = 1 kg/s; piso de O2 = 300.03 K; motor de propiedades = teqp. | D16: Diferencia de presiones, ΔP [kPa] | E16: 2 | F16: 1307.1 | G16: 1894.1 | H16: 2481.2
A17: estudio 4.1 escenario S1 | B17: 4.1a | C17: Datos fijos: T_fuente = 623.15 K; T_sumidero = 300.03 K; m_b = 1 kg/s; piso de O2 = 300.03 K; motor de propiedades = teqp. | D17: Razón de presiones, r_P [–] | E17: 2 | F17: 1.6939 | G17: 2.2524 | H17: 2.8109
A18: estudio 4.1 escenario S1 | B18: 4.1a | C18: Datos fijos: T_fuente = 623.15 K; T_sumidero = 300.03 K; m_b = 1 kg/s; piso de O2 = 300.03 K; motor de propiedades = teqp. | D18: Temperatura de la fuente, T_fuente [K] | E18: 2 | F18: 623.15 | G18: 623.15 | H18: 623.15
A19: estudio 4.1 escenario S1 | B19: 4.1a | C19: Datos fijos: T_fuente = 623.15 K; T_sumidero = 300.03 K; m_b = 1 kg/s; piso de O2 = 300.03 K; motor de propiedades = teqp. | D19: Fracción de amoníaco de la mezcla base, x_b [–] | E19: 2 | F19: 0.71922 | G19: 0.77145 | H19: 0.82368
A20: estudio 4.1 escenario S2 | B20: 4.1b | C20: Datos fijos: P_alta = 3000 kPa; P_baja = 400 kPa; m_b = 1 kg/s; motor de propiedades = teqp. | D20: — (sin KALINA confiables) | E20: 0
A21: estudio 4.1 escenario S3 | B21: 4.1c | C21: Datos fijos: T_sumidero = 300.03 K; P_alta = 3000 kPa; P_baja = 400 kPa; m_b = 1 kg/s; piso de O2 = 300.03 K; motor de propiedades = teqp. | D21: — (sin KALINA confiables) | E21: 0
A22: estudio 4.1 escenario S4 | B22: 4.1d | C22: Datos fijos: T_fuente = 623.15 K; T_sumidero = 300.03 K; P_alta = 3000 kPa; m_b = 1 kg/s; piso de O2 = 300.03 K; motor de propiedades = teqp. | D22: — (sin KALINA confiables) | E22: 0
A23: estudio 4.1 escenario S5 | B23: 4.1e | C23: Datos fijos: T_fuente = 623.15 K; x_b = 0.5; m_b = 1 kg/s; motor de propiedades = teqp. | D23: — (sin KALINA confiables) | E23: 0
A24: 4.2 | B24: 4.2 | C24: Datos fijos: P_alta = 3000 kPa; P_baja = 400 kPa; x_b = 0.5; m_b = 1 kg/s; η_t = 0.85; η_p = 0.75; ε_HRVG = 0.85; ε_reg = 0.75; motor de propiedades = teqp. | D24: Presión de alta, P_alta [kPa] | E24: 104 | F24: 3000 | G24: 3000 | H24: 3000
A25: 4.2 | B25: 4.2 | C25: Datos fijos: P_alta = 3000 kPa; P_baja = 400 kPa; x_b = 0.5; m_b = 1 kg/s; η_t = 0.85; η_p = 0.75; ε_HRVG = 0.85; ε_reg = 0.75; motor de propiedades = teqp. | D25: Presión de baja, P_baja [kPa] | E25: 104 | F25: 400 | G25: 400 | H25: 400
A26: 4.2 | B26: 4.2 | C26: Datos fijos: P_alta = 3000 kPa; P_baja = 400 kPa; x_b = 0.5; m_b = 1 kg/s; η_t = 0.85; η_p = 0.75; ε_HRVG = 0.85; ε_reg = 0.75; motor de propiedades = teqp. | D26: Diferencia de presiones, ΔP [kPa] | E26: 104 | F26: 2600 | G26: 2600 | H26: 2600
A27: 4.2 | B27: 4.2 | C27: Datos fijos: P_alta = 3000 kPa; P_baja = 400 kPa; x_b = 0.5; m_b = 1 kg/s; η_t = 0.85; η_p = 0.75; ε_HRVG = 0.85; ε_reg = 0.75; motor de propiedades = teqp. | D27: Razón de presiones, r_P [–] | E27: 104 | F27: 7.5 | G27: 7.5 | H27: 7.5
A28: 4.2 | B28: 4.2 | C28: Datos fijos: P_alta = 3000 kPa; P_baja = 400 kPa; x_b = 0.5; m_b = 1 kg/s; η_t = 0.85; η_p = 0.75; ε_HRVG = 0.85; ε_reg = 0.75; motor de propiedades = teqp. | D28: Temperatura de la fuente, T_fuente [K] | E28: 104 | F28: 390 | G28: 400 | H28: 410
A29: 4.2 | B29: 4.2 | C29: Datos fijos: P_alta = 3000 kPa; P_baja = 400 kPa; x_b = 0.5; m_b = 1 kg/s; η_t = 0.85; η_p = 0.75; ε_HRVG = 0.85; ε_reg = 0.75; motor de propiedades = teqp. | D29: Fracción de amoníaco de la mezcla base, x_b [–] | E29: 104 | F29: 0.5 | G29: 0.5 | H29: 0.5
A30: estudio 4.3 conjunto final x_b+P_alta+eficiencias+P_baja | B30: 4.3 x_b+P_alta+eficiencias+P_baja | C30: Datos fijos: P_alta = 3000 kPa; P_baja = 400 kPa; x_b = 0.5; m_b = 1 kg/s; η_t = 0.85; η_p = 0.75; ε_HRVG = 0.85; ε_reg = 0.75; ε_cond = 0.8; motor de propiedades = teqp. | D30: Presión de alta, P_alta [kPa] | E30: 5 | F30: 3000 | G30: 3000 | H30: 3000
A31: estudio 4.3 conjunto final x_b+P_alta+eficiencias+P_baja | B31: 4.3 x_b+P_alta+eficiencias+P_baja | C31: Datos fijos: P_alta = 3000 kPa; P_baja = 400 kPa; x_b = 0.5; m_b = 1 kg/s; η_t = 0.85; η_p = 0.75; ε_HRVG = 0.85; ε_reg = 0.75; ε_cond = 0.8; motor de propiedades = teqp. | D31: Presión de baja, P_baja [kPa] | E31: 5 | F31: 400 | G31: 400 | H31: 400
A32: estudio 4.3 conjunto final x_b+P_alta+eficiencias+P_baja | B32: 4.3 x_b+P_alta+eficiencias+P_baja | C32: Datos fijos: P_alta = 3000 kPa; P_baja = 400 kPa; x_b = 0.5; m_b = 1 kg/s; η_t = 0.85; η_p = 0.75; ε_HRVG = 0.85; ε_reg = 0.75; ε_cond = 0.8; motor de propiedades = teqp. | D32: Diferencia de presiones, ΔP [kPa] | E32: 5 | F32: 2600 | G32: 2600 | H32: 2600
A33: estudio 4.3 conjunto final x_b+P_alta+eficiencias+P_baja | B33: 4.3 x_b+P_alta+eficiencias+P_baja | C33: Datos fijos: P_alta = 3000 kPa; P_baja = 400 kPa; x_b = 0.5; m_b = 1 kg/s; η_t = 0.85; η_p = 0.75; ε_HRVG = 0.85; ε_reg = 0.75; ε_cond = 0.8; motor de propiedades = teqp. | D33: Razón de presiones, r_P [–] | E33: 5 | F33: 7.5 | G33: 7.5 | H33: 7.5
A34: estudio 4.3 conjunto final x_b+P_alta+eficiencias+P_baja | B34: 4.3 x_b+P_alta+eficiencias+P_baja | C34: Datos fijos: P_alta = 3000 kPa; P_baja = 400 kPa; x_b = 0.5; m_b = 1 kg/s; η_t = 0.85; η_p = 0.75; ε_HRVG = 0.85; ε_reg = 0.75; ε_cond = 0.8; motor de propiedades = teqp. | D34: Temperatura de la fuente, T_fuente [K] | E34: 5 | F34: 392.17 | G34: 399.37 | H34: 408.78
A35: estudio 4.3 conjunto final x_b+P_alta+eficiencias+P_baja | B35: 4.3 x_b+P_alta+eficiencias+P_baja | C35: Datos fijos: P_alta = 3000 kPa; P_baja = 400 kPa; x_b = 0.5; m_b = 1 kg/s; η_t = 0.85; η_p = 0.75; ε_HRVG = 0.85; ε_reg = 0.75; ε_cond = 0.8; motor de propiedades = teqp. | D35: Fracción de amoníaco de la mezcla base, x_b [–] | E35: 5 | F35: 0.5 | G35: 0.5 | H35: 0.5
... A41: estudio 6.2 malla | B41: 6.2c | C41: Datos fijos: T_fuente = 394.15 K; T_sumidero = 278.15 K; P_alta = 3300 kPa; m_b = 1 kg/s; η_t = 0.9; η_p = 0.8; ε_HRVG = 0.85; ε_reg = 0.75; ε_cond = 0.95; piso de O2 = 283.15 K; motor de propiedades = teqp. | D41: Fracción de amoníaco de la mezcla base, x_b [–] | E41: 70 | F41: 0.5 | G41: 0.73 | H41: 0.91
A43: Notas: Filtro: solo KALINA confiables. n = 34 filas en la tabla. † = fuera del rango confiable (IAPWS G4-01); ‡ = falso convergido. Fuente: todos_los_puntos.csv. Cada caso tiene datos fijos distintos: comparar rangos entre filas, no puntos. Percentiles con numpy (método lineal).

Sheet S-4 Datos del profesor conserva
A1: Tabla S-4 · Datos del profesor conservables
A2: Síntesis de toda la campaña: cada fila es un estudio o una parte con sus propios datos fijos.
A4: Síntesis: cada fila es un estudio o una parte con sus propios datos fijos.
A5: Fuente: fichas 4.2 y 4.3; validación cruzada
A7: Dato | B7: Valor del profesor | C7: ¿Se conserva con KALINA? | D7: Respaldo
A8: P_alta | B8: 3000 kPa | C8: sí | D8: estudio 4.3 (x_b+P_alta+eficiencias+P_baja), estudio 4.2
A9: P_baja | B9: 400 kPa | C9: sí | D9: estudio 4.3; con su clima de 300 K exige ε_cond ≥ 0.875 (estudio 4.2)
A10: x_b | B10: 0.50 | C10: sí | D10: estudio 4.3 (η hasta 10.6 %); con el ancla de Húsavík queda al límite, η < 1.3 % (estudio 6.2)
A11: η_t | B11: 0.85 | C11: sí | D11: estudio 4.3 (grupo EF)
A12: η_p | B12: 0.75 | C12: sí | D12: estudio 4.3 (grupo EF)
A13: ε_HRVG | B13: 0.85 | C13: sí | D13: estudio 4.3 (grupo EF)
A14: ε_reg | B14: 0.75 | C14: sí | D14: estudio 4.3 (grupo EF)
A15: ε_cond | B15: 0.80 | C15: sí, si el sitio es más frío (≤ ~293 K) | D15: estudio 4.3; con 300 K hace falta ≥ 0.875 (estudio 4.2)
A16: T_sumidero | B16: 300.03 K | C16: con condiciones: o se baja a 280–293 K, o se sube ε_cond | D16: estudio 4.3, estudio 4.2
A17: T_fuente | B17: 623.15 K | C17: no (bloqueo estructural) | D17: estudio 1.1, estudios 2.1 y 2.2, estudio 4.3 (0 confiables con TF)
A18: m_b | B18: 1 kg/s | C18: sí (base de cálculo) | D18: todas
A20: Notas: Filtro: conclusiones validadas por A4. n = 11 filas en la tabla. † = fuera del rango confiable (IAPWS G4-01); ‡ = falso convergido. Fuente: fichas 4.2 y 4.3; validación cruzada.

Sheet S-5 Criterios que bloquean, por
A1: Tabla S-5 · Criterios que bloquean, por estudio
A2: Síntesis de toda la campaña: cada fila es un estudio o una parte con sus propios datos fijos.
A4: Síntesis: cada fila es un estudio o una parte con sus propios datos fijos.
A5: Fuente: todos_los_puntos.csv
A7: Estudio | B7: Genuinos no KALINA | C7: O1 (n) | D7: O1 [%] | E7: O2 (n) | F7: O2 [%] | G7: O3 (n) | H7: O3 [%] | I7: O5 (n) | J7: O5 [%]
A8: 1.1 | B8: 0 | C8: 0 | E8: 0 | G8: 0 | I8: 0
A9: 2.1 | B9: 15 | C9: 11 | D9: 73.333 | E9: 15 | F9: 100 | G9: 0 | H9: 0 | I9: 2 | J9: 13.333
A10: 2.2 | B10: 106 | C10: 5 | D10: 4.717 | E10: 106 | F10: 100 | G10: 0 | H10: 0 | I10: 0 | J10: 0
A11: 2.3 | B11: 134 | C11: 17 | D11: 12.687 | E11: 134 | F11: 100 | G11: 0 | H11: 0 | I11: 0 | J11: 0
A12: 2.4 | B12: 116 | C12: 14 | D12: 12.069 | E12: 116 | F12: 100 | G12: 3 | H12: 2.5862 | I12: 0 | J12: 0
A13: 3.1 | B13: 62 | C13: 0 | D13: 0 | E13: 61 | F13: 98.387 | G13: 4 | H13: 6.4516 | I13: 0 | J13: 0
A14: 3.2 | B14: 331 | C14: 21 | D14: 6.3444 | E14: 324 | F14: 97.885 | G14: 22 | H14: 6.6465 | I14: 0 | J14: 0
A15: 3.3 | B15: 45 | C15: 0 | D15: 0 | E15: 44 | F15: 97.778 | G15: 1 | H15: 2.2222 | I15: 1 | J15: 2.2222
A16: 4.1 | B16: 362 | C16: 20 | D16: 5.5249 | E16: 362 | F16: 100 | G16: 142 | H16: 39.227 | I16: 1 | J16: 0.27624
A17: 4.2 | B17: 45 | C17: 0 | D17: 0 | E17: 30 | F17: 66.667 | G17: 15 | H17: 33.333 | I17: 0 | J17: 0
A18: 6.1 | B18: 9 | C18: 0 | D18: 0 | E18: 9 | F18: 100 | G18: 0 | H18: 0 | I18: 0 | J18: 0
A19: 5.1 | B19: 130 | C19: 29 | D19: 22.308 | E19: 114 | F19: 87.692 | G19: 0 | H19: 0 | I19: 0 | J19: 0
A20: 4.3 | B20: 625 | C20: 30 | D20: 4.8 | E20: 613 | F20: 98.08 | G20: 149 | H20: 23.84 | I20: 0 | J20: 0
A21: 6.2 | B21: 65 | C21: 0 | D21: 0 | E21: 65 | F21: 100 | G21: 0 | H21: 0 | I21: 0 | J21: 0
A23: Notas: Filtro: genuinos que no son KALINA. n = 14 filas en la tabla. † = fuera del rango confiable (IAPWS G4-01); ‡ = falso convergido. Fuente: todos_los_puntos.csv. Un punto puede violar varios criterios: los % no suman 100. O1 título, O2 cavitación, O3 trabajo neto, O5 separador.

Sheet S Gráficos
A1: Síntesis de toda la campaña
A2: Gráficos nativos de Excel: pase el cursor sobre un punto para ver su valor. Los números de cada gráfico están en la hoja «S Datos de gráficos» (el subtítulo de cada figura lleva un vínculo a su bloque).
A4: Figura S-1 · Resultado de cada barrido: puntos por clase
A27: Figura S-1. Resultado de cada barrido: puntos por clase.
A28: Estudios 1.1 a 6.2 (figura de síntesis: una barra por estudio), sin el anexo A.1.
A29: Datos fijos: no aplica (figura de síntesis).
A30: Filtro: todos los puntos menos los de A.1.
A31: n = 4560. Fuente: todos_los_puntos.csv.
A34: La Figura S-2 (qué se movió en cada barrido) está como tabla con colores en la hoja «S-2 Qué se movió en cada barrido».

Sheet S Datos de gráficos
A1: Datos de los gráficos de la síntesis
A2: Cada bloque de columnas es una figura; cada serie ocupa dos columnas (valores de x y de y, o categoría y valor).
A4: Figura S-1 · Resultado de cada barrido: puntos por clase
A5: Resultado de cada barrido: puntos por clase · categoría: Estudio | B5: Resultado de cada barrido: puntos por clase · KALINA (n = 1662) | C5: Resultado de cada barrido: puntos por clase · Corregible (n = 1701) | D5: Resultado de cada barrido: puntos por clase · Inviable (n = 344) | E5: Resultado de cada barrido: puntos por clase · No convergió (n = 718) | F5: Resultado de cada barrido: puntos por clase · Falso convergido (n = 135)
A6: 1.1 | B6: 0 | C6: 0 | D6: 0 | E6: 42 | F6: 0
A7: 2.1 | B7: 0 | C7: 13 | D7: 2 | E7: 96 | F7: 21
A8: 2.2 | B8: 59 | C8: 106 | D8: 0 | E8: 3 | F8: 12
A9: 2.3 | B9: 20 | C9: 133 | D9: 1 | E9: 67 | F9: 4
A10: 2.4 | B10: 153 | C10: 113 | D10: 3 | E10: 51 | F10: 0
A11: 3.1 | B11: 86 | C11: 57 | D11: 5 | E11: 17 | F11: 6
A12: 3.2 | B12: 121 | C12: 308 | D12: 23 | E12: 35 | F12: 13
A13: 3.3 | B13: 75 | C13: 43 | D13: 2 | E13: 9 | F13: 6
A14: 4.1 | B14: 20 | C14: 219 | D14: 143 | E14: 204 | F14: 12
A15: 4.2 | B15: 104 | C15: 30 | D15: 15 | E15: 1 | F15: 15
A16: 4.3 | B16: 181 | C16: 475 | D16: 150 | E16: 148 | F16: 29
A17: 5.1 | B17: 419 | C17: 130 | D17: 0 | E17: 10 | F17: 1
... A19: 6.2 | B19: 282 | C19: 65 | D19: 0 | E19: 19 | F19: 16

Sheet 1.1-1 Condiciones qué quedó fij
A1: Tabla 1.1-1 · Condiciones: qué quedó fijo y qué se barrió
A2: Estudio 1.1 · Repetir el caso del profesor · Partes: 1.1b, 1.1a, 1.1c, 1.1d
A3: Punto base: PP = punto del profesor (los 11 datos del enunciado; ver GLOSARIO)
A4: Datos fijos: T_fuente = 623.15 K; P_baja = 400 kPa; m_b = 1 kg/s; η_t = 0.85; η_p = 0.75; ε_HRVG = 0.85; ε_reg = 0.75; ε_cond = 0.8.
A5: Datos barridos: T_sumidero [297.95–303.55] K (23 valores); P_alta [2000–4000] kPa (9 valores); x_b [0.4–0.7] (7 valores); motor de propiedades (2 valores).
A6: Fuente: analisis_final/00_inventario/condiciones_por_subcaso.csv
A8: Parte | B8: Variable | C8: Estado | D8: Valor o rango | E8: n valores | F8: ¿Igual al profesor? | G8: Unidad
A9: 1.1b · solo P_alta | B9: Temperatura de la fuente, T_fuente [K] | C9: Fija | D9: 623.15 | F9: sí | G9: K
A10: 1.1b · solo P_alta | B10: Temperatura del sumidero, T_sumidero [K] | C10: Fija | D10: 300.032917 | F10: sí | G10: K
A11: 1.1b · solo P_alta | B11: Presión de alta, P_alta [kPa] | C11: Barrida | D11: 2000 – 4000 | E11: 9 | G11: kPa
A12: 1.1b · solo P_alta | B12: Presión de baja, P_baja [kPa] | C12: Fija | D12: 400.0 | F12: sí | G12: kPa
A13: 1.1b · solo P_alta | B13: Fracción de amoníaco de la mezcla base, x_b [–] | C13: Fija | D13: 0.5 | F13: sí | G13: –
A14: 1.1b · solo P_alta | B14: Flujo másico base, m_b [kg/s] | C14: Fija | D14: 1.0 | F14: sí | G14: kg/s
A15: 1.1b · solo P_alta | B15: Eficiencia isentrópica de la turbina, η_t [–] | C15: Fija | D15: 0.85 | F15: sí | G15: –
A16: 1.1b · solo P_alta | B16: Eficiencia isentrópica de la bomba, η_p [–] | C16: Fija | D16: 0.75 | F16: sí | G16: –
A17: 1.1b · solo P_alta | B17: Efectividad del generador de vapor, ε_HRVG [–] | C17: Fija | D17: 0.85 | F17: sí | G17: –
A18: 1.1b · solo P_alta | B18: Efectividad del regenerador, ε_reg [–] | C18: Fija | D18: 0.75 | F18: sí | G18: –
A19: 1.1b · solo P_alta | B19: Efectividad del condensador, ε_cond [–] | C19: Fija | D19: 0.8 | F19: sí | G19: –
A20: 1.1b · solo P_alta | B20: Piso de O2 (T de diseño de la bomba) [K] | C20: Sin dato | G20: K
A21: 1.1b · solo P_alta | B21: motor de propiedades | C21: Fija | D21: teqp | G21: –
A22: 1.1a · punto del profesor | B22: Temperatura de la fuente, T_fuente [K] | C22: Fija | D22: 623.15 | F22: sí | G22: K
A23: 1.1a · punto del profesor | B23: Temperatura del sumidero, T_sumidero [K] | C23: Fija | D23: 300.032917 | F23: sí | G23: K
A24: 1.1a · punto del profesor | B24: Presión de alta, P_alta [kPa] | C24: Fija | D24: 3000.0 | F24: sí | G24: kPa
A25: 1.1a · punto del profesor | B25: Presión de baja, P_baja [kPa] | C25: Fija | D25: 400.0 | F25: sí | G25: kPa
A26: 1.1a · punto del profesor | B26: Fracción de amoníaco de la mezcla base, x_b [–] | C26: Fija | D26: 0.5 | F26: sí | G26: –
A27: 1.1a · punto del profesor | B27: Flujo másico base, m_b [kg/s] | C27: Fija | D27: 1.0 | F27: sí | G27: kg/s
A28: 1.1a · punto del profesor | B28: Eficiencia isentrópica de la turbina, η_t [–] | C28: Fija | D28: 0.85 | F28: sí | G28: –
A29: 1.1a · punto del profesor | B29: Eficiencia isentrópica de la bomba, η_p [–] | C29: Fija | D29: 0.75 | F29: sí | G29: –
A30: 1.1a · punto del profesor | B30: Efectividad del generador de vapor, ε_HRVG [–] | C30: Fija | D30: 0.85 | F30: sí | G30: –
A31: 1.1a · punto del profesor | B31: Efectividad del regenerador, ε_reg [–] | C31: Fija | D31: 0.75 | F31: sí | G31: –
A32: 1.1a · punto del profesor | B32: Efectividad del condensador, ε_cond [–] | C32: Fija | D32: 0.8 | F32: sí | G32: –
A33: 1.1a · punto del profesor | B33: Piso de O2 (T de diseño de la bomba) [K] | C33: Sin dato | G33: K
A34: 1.1a · punto del profesor | B34: motor de propiedades | C34: Barrida | D34: – | E34: 2 | G34: –
A35: 1.1c · solo x_b | B35: Temperatura de la fuente, T_fuente [K] | C35: Fija | D35: 623.15 | F35: sí | G35: K
A36: 1.1c · solo x_b | B36: Temperatura del sumidero, T_sumidero [K] | C36: Fija | D36: 300.032917 | F36: sí | G36: K
A37: 1.1c · solo x_b | B37: Presión de alta, P_alta [kPa] | C37: Fija | D37: 3000.0 | F37: sí | G37: kPa
A38: 1.1c · solo x_b | B38: Presión de baja, P_baja [kPa] | C38: Fija | D38: 400.0 | F38: sí | G38: kPa
A39: 1.1c · solo x_b | B39: Fracción de amoníaco de la mezcla base, x_b [–] | C39: Barrida | D39: 0.400 – 0.700 | E39: 7 | G39: –
A40: 1.1c · solo x_b | B40: Flujo másico base, m_b [kg/s] | C40: Fija | D40: 1.0 | F40: sí | G40: kg/s
A41: 1.1c · solo x_b | B41: Eficiencia isentrópica de la turbina, η_t [–] | C41: Fija | D41: 0.85 | F41: sí | G41: –
A42: 1.1c · solo x_b | B42: Eficiencia isentrópica de la bomba, η_p [–] | C42: Fija | D42: 0.75 | F42: sí | G42: –
A43: 1.1c · solo x_b | B43: Efectividad del generador de vapor, ε_HRVG [–] | C43: Fija | D43: 0.85 | F43: sí | G43: –
A44: 1.1c · solo x_b | B44: Efectividad del regenerador, ε_reg [–] | C44: Fija | D44: 0.75 | F44: sí | G44: –
A45: 1.1c · solo x_b | B45: Efectividad del condensador, ε_cond [–] | C45: Fija | D45: 0.8 | F45: sí | G45: –
A46: 1.1c · solo x_b | B46: Piso de O2 (T de diseño de la bomba) [K] | C46: Sin dato | G46: K
A47: 1.1c · solo x_b | B47: motor de propiedades | C47: Fija | D47: teqp | G47: –
A48: 1.1d · temperatura ambiente hora a hora | B48: Temperatura de la fuente, T_fuente [K] | C48: Fija | D48: 623.15 | F48: sí | G48: K
A49: 1.1d · temperatura ambiente hora a hora | B49: Temperatura del sumidero, T_sumidero [K] | C49: Barrida | D49: 297.9 – 303.6 | E49: 23 | G49: K
A50: 1.1d · temperatura ambiente hora a hora | B50: Presión de alta, P_alta [kPa] | C50: Fija | D50: 3000.0 | F50: sí | G50: kPa
A51: 1.1d · temperatura ambiente hora a hora | B51: Presión de baja, P_baja [kPa] | C51: Fija | D51: 400.0 | F51: sí | G51: kPa
A52: 1.1d · temperatura ambiente hora a hora | B52: Fracción de amoníaco de la mezcla base, x_b [–] | C52: Fija | D52: 0.5 | F52: sí | G52: –
A53: 1.1d · temperatura ambiente hora a hora | B53: Flujo másico base, m_b [kg/s] | C53: Fija | D53: 1.0 | F53: sí | G53: kg/s
A54: 1.1d · temperatura ambiente hora a hora | B54: Eficiencia isentrópica de la turbina, η_t [–] | C54: Fija | D54: 0.85 | F54: sí | G54: –
A55: 1.1d · temperatura ambiente hora a hora | B55: Eficiencia isentrópica de la bomba, η_p [–] | C55: Fija | D55: 0.75 | F55: sí | G55: –
A56: 1.1d · temperatura ambiente hora a hora | B56: Efectividad del generador de vapor, ε_HRVG [–] | C56: Fija | D56: 0.85 | F56: sí | G56: –
A57: 1.1d · temperatura ambiente hora a hora | B57: Efectividad del regenerador, ε_reg [–] | C57: Fija | D57: 0.75 | F57: sí | G57: –
A58: 1.1d · temperatura ambiente hora a hora | B58: Efectividad del condensador, ε_cond [–] | C58: Fija | D58: 0.8 | F58: sí | G58: –
A59: 1.1d · temperatura ambiente hora a hora | B59: Piso de O2 (T de diseño de la bomba) [K] | C59: Sin dato | G59: K
A60: 1.1d · temperatura ambiente hora a hora | B60: motor de propiedades | C60: Fija | D60: teqp | G60: –
A62: Notas: Filtro: cada parte y cada variable. n = 52 filas en la tabla. † = fuera del rango confiable (IAPWS G4-01); ‡ = falso convergido. Fuente: analisis_final/00_inventario/condiciones_por_subcaso.csv.

Sheet 1.1-2 Corridas por parte y por
A1: Tabla 1.1-2 · Corridas por parte y por clase
A2: Estudio 1.1 · Repetir el caso del profesor · Partes: 1.1b, 1.1a, 1.1c, 1.1d
A3: Punto base: PP = punto del profesor (los 11 datos del enunciado; ver GLOSARIO)
A4: Datos fijos: T_fuente = 623.15 K; P_baja = 400 kPa; m_b = 1 kg/s; η_t = 0.85; η_p = 0.75; ε_HRVG = 0.85; ε_reg = 0.75; ε_cond = 0.8.
A5: Datos barridos: T_sumidero [297.95–303.55] K (23 valores); P_alta [2000–4000] kPa (9 valores); x_b [0.4–0.7] (7 valores); motor de propiedades (2 valores).
A6: Fuente: analisis_final/00_inventario/conteo_por_subcaso.csv
A8: Parte | B8: Corridas | C8: Omitidos | D8: Genuinos | E8: KALINA | F8: KALINA confiables | G8: Corregibles | H8: Inviables | I8: No convergidos | J8: Falsos convergidos | K8: Fuera de rango
A9: 1.1b · solo P_alta | B9: 9 | C9: 0 | D9: 0 | E9: 0 | F9: 0 | G9: 0 | H9: 0 | I9: 9 | J9: 0 | K9: 0
A10: 1.1a · punto del profesor | B10: 2 | C10: 0 | D10: 0 | E10: 0 | F10: 0 | G10: 0 | H10: 0 | I10: 2 | J10: 0 | K10: 0
A11: 1.1c · solo x_b | B11: 7 | C11: 0 | D11: 0 | E11: 0 | F11: 0 | G11: 0 | H11: 0 | I11: 7 | J11: 0 | K11: 0
A12: 1.1d · temperatura ambiente hora a hora | B12: 24 | C12: 0 | D12: 0 | E12: 0 | F12: 0 | G12: 0 | H12: 0 | I12: 24 | J12: 0 | K12: 0
A14: Notas: Filtro: conteo por parte. n = 4 filas en la tabla. † = fuera del rango confiable (IAPWS G4-01); ‡ = falso convergido. Fuente: analisis_final/00_inventario/conteo_por_subcaso.csv.

Sheet 1.1-3 Comparación antes y despu
A1: Tabla 1.1-3 · Comparación antes y después de la F1
A2: Estudio 1.1 · Repetir el caso del profesor · Partes: 1.1b, 1.1a, 1.1c, 1.1d
A3: Punto base: PP = punto del profesor (los 11 datos del enunciado; ver GLOSARIO)
A4: Datos fijos: T_fuente = 623.15 K; P_baja = 400 kPa; m_b = 1 kg/s; η_t = 0.85; η_p = 0.75; ε_HRVG = 0.85; ε_reg = 0.75; ε_cond = 0.8.
A5: Datos barridos: T_sumidero [297.95–303.55] K (23 valores); P_alta [2000–4000] kPa (9 valores); x_b [0.4–0.7] (7 valores); motor de propiedades (2 valores).
A6: Fuente: resultados/2026-10-06_final_M1/m1_comparacion.csv
A8: Grupo | B8: Valor | C8: Clase (antes) | D8: Clase (ahora) | E8: Misma clase | F8: η (antes) [%] | G8: η (ahora) [%] | H8: Δη [pp] | I8: Mensaje (antes) | J8: Mensaje (ahora)
A9: base | C9: NO_CONVERGIO | D9: NO_CONVERGIO | E9: sí | J9: presupuesto de tiempo agotado: 1 evaluaciones de F en 316.5 s (presupuesto 300 s
A10: P_alta | B10: 2000 | C10: NO_CONVERGIO | D10: NO_CONVERGIO | E10: sí | I10: equilibrio_liquido_vapor(P=2000.0 kPa, T=623.0000091226806 K): no existe equilib | J10: extremos [301.0329, 307.1500] K sin cambio de signo de F (F(lo)=76.814, F(hi)=71
A11: P_alta | B11: 2250 | C11: NO_CONVERGIO | D11: NO_CONVERGIO | E11: sí | I11: equilibrio_liquido_vapor(P=2250.0 kPa, T=623.0000058142358 K): no existe equilib | J11: extremos [301.0329, 317.1500] K sin cambio de signo de F (F(lo)=79.155, F(hi)=65
A12: P_alta | B12: 2500 | C12: NO_CONVERGIO | D12: NO_CONVERGIO | E12: sí | I12: equilibrio_liquido_vapor(P=2500.0 kPa, T=623.0000024147047 K): no existe equilib | J12: extremos [301.0329, 327.1500] K sin cambio de signo de F (F(lo)=81.794, F(hi)=59
A13: P_alta | B13: 2750 | C13: NO_CONVERGIO | D13: NO_CONVERGIO | E13: sí | I13: equilibrio_liquido_vapor(P=2750.0 kPa, T=622.9999988927121 K): no existe equilib | J13: extremos [301.0329, 337.1500] K sin cambio de signo de F (F(lo)=84.509, F(hi)=52
A14: P_alta | B14: 3000 | C14: NO_CONVERGIO | D14: NO_CONVERGIO | E14: sí | I14: equilibrio_liquido_vapor(P=3000.0 kPa, T=622.9999953066318 K): no existe equilib | J14: extremos [301.0329, 347.1500] K sin cambio de signo de F (F(lo)=87.376, F(hi)=45
A15: P_alta | B15: 3250 | C15: NO_CONVERGIO | D15: NO_CONVERGIO | E15: sí | I15: equilibrio_liquido_vapor(P=3250.0 kPa, T=622.9999916547947 K): no existe equilib | J15: extremos [301.0329, 352.1500] K sin cambio de signo de F (F(lo)=90.346, F(hi)=43
A16: P_alta | B16: 3500 | C16: NO_CONVERGIO | D16: NO_CONVERGIO | E16: sí | I16: equilibrio_liquido_vapor(P=3500.0 kPa, T=622.9999884354551 K): no existe equilib | J16: extremos [301.0329, 362.1500] K sin cambio de signo de F (F(lo)=93.153, F(hi)=36
A17: P_alta | B17: 3750 | C17: NO_CONVERGIO | D17: NO_CONVERGIO | E17: sí | I17: equilibrio_liquido_vapor(P=3750.0 kPa, T=622.9999846467892 K): no existe equilib | J17: extremos [301.0329, 367.1500] K sin cambio de signo de F (F(lo)=93.01, F(hi)=33.
A18: P_alta | B18: 4000 | C18: NO_CONVERGIO | D18: NO_CONVERGIO | E18: sí | I18: equilibrio_liquido_vapor(P=4000.0 kPa, T=622.9999807869 K): no existe equilibrio | J18: extremos [301.0329, 372.1500] K sin cambio de signo de F (F(lo)=92.621, F(hi)=30
A19: x_b | B19: 0.4 | C19: NO_CONVERGIO | D19: NO_CONVERGIO | E19: sí | I19: equilibrio_liquido_vapor(P=3000.0 kPa, T=622.999986634595 K): no existe equilibr | J19: extremos [306.0329, 387.1500] K sin cambio de signo de F (F(lo)=92.575, F(hi)=21
A20: x_b | B20: 0.45 | C20: NO_CONVERGIO | D20: NO_CONVERGIO | E20: sí | I20: equilibrio_liquido_vapor(P=3000.0 kPa, T=622.9999908239907 K): no existe equilib | J20: extremos [301.0329, 367.1500] K sin cambio de signo de F (F(lo)=94.732, F(hi)=33
A21: x_b | B21: 0.5 | C21: NO_CONVERGIO | D21: NO_CONVERGIO | E21: sí | I21: equilibrio_liquido_vapor(P=3000.0 kPa, T=622.9999953066318 K): no existe equilib | J21: extremos [301.0329, 347.1500] K sin cambio de signo de F (F(lo)=87.376, F(hi)=45
... A49: T_amb | B49: 299.15 | C49: NO_CONVERGIO | D49: NO_CONVERGIO | E49: sí | I49: equilibrio_liquido_vapor(P=3000.0 kPa, T=622.9999953066318 K): no existe equilib | J49: extremos [300.1500, 347.1500] K sin cambio de signo de F (F(lo)=88.016, F(hi)=45
A51: Notas: Filtro: sin filtro (comparación punto a punto). n = 41 filas en la tabla. † = fuera del rango confiable (IAPWS G4-01); ‡ = falso convergido. Fuente: resultados/2026-10-06_final_M1/m1_comparacion.csv.

Sheet 1.1-R Resultados por barrido
A1: Resultados por barrido · Estudio 1.1 · Repetir el caso del profesor
A2: Cada fila es un punto calculado (n = 42); mismas columnas que la tabla del tablero HTML. Solo se comparan puntos de la misma parte.
A3: Los gráficos de este estudio están en la hoja de gráficos de su pregunta; los números que dibuja cada uno, en su hoja «Datos de gráficos».
A4: «Falso convergido»: el solver dijo que convergió pero no es un ciclo real; su η y W_net no se muestran («—»), igual que en los gráficos.
A6: Parte 1.1a · punto del profesor · 2 puntos
A8: Barrido de la parte 1.1a · 2 puntos
A9: Fijos en este barrido: T_fuente = 623.15, T_sumidero = 300.03, P_alta = 3000, P_baja = 400, x_b = 0.5, η_t = 0.85, η_p = 0.75, ε_HRVG = 0.85, ε_reg = 0.75, ε_cond = 0.8.
A10: id_punto | B10: Clase | C10: η [%] | D10: W_net [kW] (m_b = 1 kg/s) | E10: ΔP [kPa] | F10: r_P [–] | G10: Fuera de rango
A11: KF-M01-base-0000 | B11: No convergió | C11: — | D11: — | E11: 2600 | F11: 7.5 | G11: no
A12: KF-M01-base-0001 | B12: No convergió | C12: — | D12: — | E12: 2600 | F12: 7.5 | G12: no
A14: Parte 1.1b · solo P_alta · 9 puntos
A16: Barrido de la parte 1.1b · 9 puntos
A17: Fijos en este barrido: T_fuente = 623.15, T_sumidero = 300.03, P_baja = 400, x_b = 0.5, η_t = 0.85, η_p = 0.75, ε_HRVG = 0.85, ε_reg = 0.75, ε_cond = 0.8.
A18: id_punto | B18: P_alta [kPa] | C18: Clase | D18: η [%] | E18: W_net [kW] (m_b = 1 kg/s) | F18: ΔP [kPa] | G18: r_P [–] | H18: Fuera de rango
A19: KF-M01-P_alta-0003 | B19: 2000 | C19: No convergió | D19: — | E19: — | F19: 1600 | G19: 5 | H19: no
A20: KF-M01-P_alta-0001 | B20: 2250 | C20: No convergió | D20: — | E20: — | F20: 1850 | G20: 5.625 | H20: no
A21: KF-M01-P_alta-0002 | B21: 2500 | C21: No convergió | D21: — | E21: — | F21: 2100 | G21: 6.25 | H21: no
A22: KF-M01-P_alta-0000 | B22: 2750 | C22: No convergió | D22: — | E22: — | F22: 2350 | G22: 6.875 | H22: no
A23: KF-M01-P_alta-0006 | B23: 3000 | C23: No convergió | D23: — | E23: — | F23: 2600 | G23: 7.5 | H23: no
A24: KF-M01-P_alta-0004 | B24: 3250 | C24: No convergió | D24: — | E24: — | F24: 2850 | G24: 8.125 | H24: no
A25: KF-M01-P_alta-0005 | B25: 3500 | C25: No convergió | D25: — | E25: — | F25: 3100 | G25: 8.75 | H25: no
A26: KF-M01-P_alta-0007 | B26: 3750 | C26: No convergió | D26: — | E26: — | F26: 3350 | G26: 9.375 | H26: no
A27: KF-M01-P_alta-0008 | B27: 4000 | C27: No convergió | D27: — | E27: — | F27: 3600 | G27: 10 | H27: no
A29: Parte 1.1c · solo x_b · 7 puntos
A31: Barrido de la parte 1.1c · 7 puntos
A32: Fijos en este barrido: T_fuente = 623.15, T_sumidero = 300.03, P_alta = 3000, P_baja = 400, η_t = 0.85, η_p = 0.75, ε_HRVG = 0.85, ε_reg = 0.75, ε_cond = 0.8.
A33: id_punto | B33: x_b [–] | C33: Clase | D33: η [%] | E33: W_net [kW] (m_b = 1 kg/s) | F33: ΔP [kPa] | G33: r_P [–] | H33: Fuera de rango
A34: KF-M01-x_b-0000 | B34: 0.4 | C34: No convergió | D34: — | E34: — | F34: 2600 | G34: 7.5 | H34: no
